Workbook

Sheet Summary
A1: A.T.L.A.S. Review - Confirmation Workbook
A2: Companion to docs/ATLAS_FRAMEWORK_REVIEW.md, baseline v0.1 (2026-09-18). Nothing has been executed; this is the sign-off sheet before Day 1.
A4: How to use this workbook
A5: 1. Work through sheets 1 to 5 in order. Yellow cells are yours; every other cell is reference and should not be edited.
A6: 2. Use the dropdown in each response column. Cells colour green, amber, or red as you answer.
A7: 3. Where you choose 'Change' or 'Disagree', write the alternative in the next column so it can be folded back into the brief.
A8: 4. Sheet 4 (Verification) is filled during Day 1 as each phase gate runs, not now.
A9: 5. The Ref sheets carry the agreed maps (engines, cabinet, domains, task forces, integrations, voice, multimodal, governance, Day 1) for checking against.
A10: 6. Return the file, or paste the response columns back, and the brief is updated to v0.2.
A12: Legend
A13: Yellow fill | B13: Cell for you to fill in
A14: Green | B14: Accepted / Yes / Pass
A15: Amber | B15: Need more information / Deferred / Not yet run
A16: Red | B16: Change / Disagree / Discuss / No / Fail
A19: Progress (formulas update as you answer)
A20: Sheet | B20: Items | C20: Answered | D20: Positive | E20: Hold | F20: Negative | G20: Remaining
A21: 1 Decisions | B21: 14 | C21: =B21-G21 | D21: =COUNTIF('1 Decisions'!$E$5:$E$18,"Accept recommendation") | E21: =COUNTIF('1 Decisions'!$E$5:$E$18,"Need more information") | F21: =COUNTIF('1 Decisions'!$E$5:$E$18,"Change") | G21: =COUNTBLANK('1 Decisions'!$E$5:$E$18)+COUNTIF('1 Decisions'!$E$5:$E$18,"Not yet run")
A22: 2 Resolutions | B22: 20 | C22: =B22-G22 | D22: =COUNTIF('2 Resolutions'!$D$5:$D$24,"Accept") | E22: =0 | F22: =COUNTIF('2 Resolutions'!$D$5:$D$24,"Disagree - return to decisions") | G22: =COUNTBLANK('2 Resolutions'!$D$5:$D$24)+COUNTIF('2 Resolutions'!$D$5:$D$24,"Not yet run")
A23: 3 Risks | B23: 18 | C23: =B23-G23 | D23: =COUNTIF('3 Risks'!$F$5:$F$22,"Yes") | E23: =0 | F23: =COUNTIF('3 Risks'!$F$5:$F$22,"Discuss") | G23: =COUNTBLANK('3 Risks'!$F$5:$F$22)+COUNTIF('3 Risks'!$F$5:$F$22,"Not yet run")
A24: 4 Verification | B24: 18 | C24: =B24-G24 | D24: =COUNTIF('4 Verification'!$D$5:$D$22,"Pass") | E24: =COUNTIF('4 Verification'!$D$5:$D$22,"Deferred") | F24: =COUNTIF('4 Verification'!$D$5:$D$22,"Fail") | G24: =COUNTBLANK('4 Verification'!$D$5:$D$22)+COUNTIF('4 Verification'!$D$5:$D$22,"Not yet run")
A25: 5 Checklist | B25: 14 | C25: =B25-G25 | D25: =COUNTIF('5 Checklist'!$D$5:$D$18,"Yes")+COUNTIF('5 Checklist'!$D$5:$D$18,"N/A") | E25: =0 | F25: =COUNTIF('5 Checklist'!$D$5:$D$18,"No") | G25: =COUNTBLANK('5 Checklist'!$D$5:$D$18)+COUNTIF('5 Checklist'!$D$5:$D$18,"Not yet run")
A26: Total | B26: =SUM(B21:B25) | C26: =SUM(C21:C25) | D26: =SUM(D21:D25) | E26: =SUM(E21:E25) | F26: =SUM(F21:F25) | G26: =SUM(G21:G25)
A27: Positive / Hold / Negative map to each sheet's dropdown: Decisions = Accept / Need more information / Change; Resolutions = Accept / - / Disagree; Risks = Yes / - / Discuss; Verification = Pass / Deferred / Fail; Checklist = Yes or N/A / - / No.
A30: Example of a completed decision row (format only; not a real answer)
A31: ID | B31: Decision | C31: Recommendation | D31: Blocks | E31: Your response | F31: Your answer or alternative | G31: Notes
A32: D0 | B32: Example: which mail client the node uses | C32: Client A | D32: Phase 2 | E32: Change | F32: Use client B, it already holds my accounts | G32: Discussed 2026-09-19

Sheet 1 Decisions
A1: 1 Decisions
A2: Section 19. Yellow cells are yours. Choose a response, and if it is 'Change' write the alternative in column F.
A4: ID | B4: Decision | C4: Recommendation | D4: Blocks | E4: Your response | F4: Your answer or alternative | G4: Notes
A5: D1 | B5: Inference backend: llama-server or Ollama | C5: llama-server | D5: Phase 2
A6: D2 | B6: Secure Boot: disable, or enrol keys for any DKMS module | C6: Disable on a headless node behind a firewall | D6: Phase 1
A7: D3 | B7: Where the LUKS recovery key and restic passphrase are kept off-node | C7: Password manager plus a printed copy in a physical safe | D7: Phase 1
A8: D4 | B8: Router model and embedding model | C8: Qwen3.5 4B-class instruct, bge-m3 embeddings, bge-reranker-v2-m3 | D8: Phase 2
A9: D5 | B9: Whether Bare-Metal OS Exploitation and Quantum Computing become domains | C9: Hold in reserve until a concrete need | D9: None
A10: D6 | B10: Sentinel feed list | C10: CoinDesk, ASX and US index feed, RSS news, node telemetry | D10: Sentinel enablement
A11: D7 | B11: Graph layer: Microsoft GraphRAG or LightRAG | C11: LightRAG, lighter indexing on this hardware | D11: Phase 2
A12: D8 | B12: The never-without-the-Principal list (16.3) | C12: Adopt the ten proposed items | D12: Phase 2
A13: D9 | B13: Retention rule for chats, logs, backups (10.4, 9.5) | C13: Adopt proposed defaults | D13: Phase 2
A14: D10 | B14: Primary vision engine: GLM-4.6V-Flash or Qwen2.5-VL | C14: Test both in Phase 4, keep the better reader as primary, the other as cross-check | D14: Phase 4
A15: D11 | B15: Apple .ipa build path | C15: Principal's own Mac if one exists, otherwise a licensed cloud Mac runner, never OSX-KVM on this node | D15: Phase 2 tool
A16: D12 | B16: Meditron-70B: include or skip | C16: Include, optional, low priority | D16: Phase 3
... A18: D14 | B18: Whether external directors get real mailboxes or aliases on the Workspace domain | C18: Aliases on one Workspace mailbox per division, distinct display names and signatures | D18: Phase 2

Sheet 2 Resolutions
A1: 2 Resolutions
A2: Section 18. Each row changes earlier text of the brief. 'Disagree' returns the item to the decision list.
A4: ID | B4: Contradiction or ambiguity found | C4: Resolution adopted | D4: Your response | E4: Notes
A5: C1 | B5: Backend named as llama.cpp, then Ollama, then llama-server at different points | C5: llama-server primary on Vulkan; Ollama optional. D1 confirms
A6: C2 | B6: Ubuntu 26.04 chosen, but Phase 4 needs ROCm PyTorch, which does not install cleanly on the 26.04 host | C6: ROCm lives inside containers; host runs Vulkan only (3.4)
A7: C3 | B7: Windows 96 GB and Linux ~120 GB budgets both appeared | C7: Linux numbers are binding (4.1)
A8: C4 | B8: KV-cache proposal mixed shipped features with unmerged research | C8: Only shipped features adopted (4.3)
A9: C5 | B9: Meditron listed among PyTorch engines | C9: Runs through llama.cpp (5.1)
A10: C6 | B10: Arthur's override bound to the abliterated engine "for legal dissection" | C10: Override is Qwen3.5 (6.1)
A11: C7 | B11: Gideon and Minerva bound to the abliterated engine "for zero-hallucination" | C11: Standard engine, retrieval-grounded (6.2)
A12: C8 | B12: Router described as an Open WebUI pipeline | C12: Lives in the orchestrator; Filter is a relay (7.1)
A13: C9 | B13: Domain 27 phrased as "memetic warfare" and "sentiment manipulation" | C13: Retained under Helena with phrasing softened to legitimate growth and attribution work
A14: C10 | B14: Domain profiles' "Stateless MRTR, dispatch and decouple" removes the approval gate | C14: Isolated-context dispatch with tracked completion (8.6)
A15: C11 | B15: Sentinel described as a WSL2 cron job | C15: systemd timer; there is no WSL (9.3)
A16: C12 | B16: Sentinel fed to Ren | C16: Alaric and Silas under Arthur (9.3)
... A24: C20 | B24: Fish Audio requested, then excluded as non-local and research-licensed | C24: Kokoro plus Chatterbox (14.1)

Sheet 3 Risks
A1: 3 Risks
A2: Section 20. Acknowledge each risk and its mitigation, or flag it for discussion.
A4: ID | B4: Risk | C4: Likelihood | D4: Impact | E4: Mitigation | F4: Acknowledged | G4: Notes
A5: R1 | B5: PyTorch has no official gfx1151 wheel, the community wheel may break on update | C5: High | D5: High for Phase 4, none for the LLM layer | E5: Pin versions, per-engine pass/fail, containerised so the host is untouched
A6: R2 | B6: Ollama's Vulkan path immature on 26.04 | C6: Medium | D6: High if chosen | E6: D1: llama-server primary
A7: R3 | B7: ROCm 7.2.x does not install on the 26.04 host kernel | C7: Certain | D7: Medium | E7: Never install ROCm on the host, containers only (3.4)
A8: R4 | B8: KV quantisation silently falls back to full precision on an unsupported architecture | C8: Medium | D8: High, unexpected OOM | E8: V4 per-model check
A9: R5 | B9: A second engine loads before the first releases memory, node crashes | C9: Medium without an arbiter | D9: High | E9: Engine Arbiter polls GPU memory before every load (4.2)
A10: R6 | B10: GraphRAG indexing is LLM-heavy and slow here | C10: High | D10: Medium | E10: Idle-time Celery job on the resident small model, D7 LightRAG
A11: R7 | B11: Cloudflare token in a plain-text file | C11: Certain today | D11: High | E11: Scoped token, mode 600, outside backups and repo (12.3)
A12: R8 | B12: Open WebUI phones home by default | C12: Certain unless hardened | D12: High for the zero-cloud rule | E12: Offline hardening in Phase 2 (12.1)
A13: R9 | B13: RTL8127 10GbE driver missing on the 26.04 kernel | C13: Low to medium | D13: Medium | E13: V1, fall back to the second port or a USB adapter
A14: R10 | B14: Sustained thermal load in a small chassis | C14: Medium | D14: Low | E14: Monitor temperatures in Cockpit, the 130 W sustained rating is desktop-class
A15: R11 | B15: CGNAT prevents inbound WireGuard | C15: Low, port forward already succeeded | D15: High for remote access | E15: V5 from mobile data, static IP from the ISP if needed
A16: R12 | B16: Fictitious directors corresponding as humans, AI non-disclosure | C16: Medium | D16: Medium to high, legal | E16: Gideon's sensitive-tier check, approval gate, 16.5
... A22: R18 | B22: Continuous vision enabled by drift rather than decision | C22: Low | D22: High, privacy | E22: Separate capability flag under Alaric, logged, D8 item 7

Sheet 4 Verification
A1: 4 Verification
A2: Section 21. Filled in during Day 1 as each phase gate runs. Nothing is trusted until its row reads Pass.
A4: ID | B4: What Day 1 must prove | C4: Where | D4: Result | E4: Evidence or notes
A5: V1 | B5: RTL8127 10GbE link up on the 26.04 kernel | C5: Phase 1 pre-flight | D5: Not yet run
A6: V2 | B6: fTPM present and enabled, TPM2 enrolment succeeds | C6: Phase 1 step 2 | D6: Not yet run
A7: V3 | B7: Kernel parameters accepted on 7.0, GPU reports the expected memory budget | C7: Phase 1 post-reboot | D7: Not yet run
A8: V4 | B8: Quantised KV cache actually applied per model, no silent fallback | C8: Phase 3 step 2 | D8: Not yet run
A9: V5 | B9: WireGuard reachable from mobile data via vpn.sovereign-node.link | C9: Phase 1 step 7 | D9: Not yet run
A10: V6 | B10: PyAnnote 3.1 gated model accepted and loading | C10: Phase 2 step 5 | D10: Not yet run
A11: V7 | B11: Voice casting listening test, Alaric and Gideon clones sourced | C11: Phase 2 gate | D11: Not yet run
A12: V8 | B12: PointLLM builds and runs on ROCm in the container | C12: Phase 4 step 4 | D12: Not yet run
A13: V9 | B13: Clay or Prithvi builds and runs | C13: Phase 4 step 4 | D13: Not yet run
A14: V10 | B14: All four core LLMs load, generate, swap, and release memory, measured tok/s within the expected bands | C14: Phase 3 gate | D14: Not yet run
A15: V11 | B15: Community PyTorch ROCm wheel passes tensor, matmul, and diffusion self-tests in the container | C15: Phase 4 step 1 | D15: Not yet run
A16: V12 | B16: Open WebUI makes no outbound connection after hardening (verified with the firewall log) | C16: Phase 2 step 3 | D16: Not yet run
... A22: V18 | B22: Vault opens by button, locks on idle, vault-tagged content absent from memory collections afterwards | C22: Phase 2 gate | D22: Not yet run

Sheet 5 Checklist
A1: 5 Checklist
A2: Section 22. Nothing runs until every row reads Yes or N/A.
A4: # | B4: Group | C4: Item | D4: Done | E4: Notes
A5: 1 | B5: Principal's actions | C5: Answer D1 through D14, or accept the recommendations as written.
A6: 2 | B6: Principal's actions | C6: Relocate the Cloudflare token per 12.3 and delete CLOUDFLARE.txt.
A7: 3 | B7: Principal's actions | C7: Decide where the LUKS recovery key and restic passphrase will live off-node (D3).
A8: 4 | B8: Principal's actions | C8: Create the Google Cloud OAuth client for Gmail, Calendar, and Drive; be available for the one-time browser authorisations during Phase 2.
A9: 5 | B9: Principal's actions | C9: Confirm the Sentinel feed list (D6).
A10: 6 | B10: Principal's actions | C10: Confirm which mailboxes or aliases directors will send from (D14).
A11: 7 | B11: Principal's actions | C11: Source reference recordings for Alaric's and, if needed, Gideon's cloned voices.
A12: 8 | B12: Principal's actions | C12: Confirm whether a Mac exists for iOS builds (D11).
A13: 9 | B13: Principal's actions | C13: Have a monitor and keyboard available for Phase 1 only, in case first boot needs a hand.
A14: 10 | B14: Build-side preconditions | C14: Ubuntu 26.04 Server installed on the 4 TB drive; 8 TB drive unpartitioned.
A15: 11 | B15: Build-side preconditions | C15: BIOS: UMA minimum, IOMMU on, fTPM on, Secure Boot per D2.
A16: 12 | B16: Build-side preconditions | C16: LAN address reserved for the node on the router; UDP 51820 forward confirmed to that address.
... A18: 14 | B18: Accepted resolutions | C18: C1 through C20 in Section 18 are accepted; where the Principal disagrees, the item returns to the decision list.

Sheet Ref Engines
A1: Ref Engines
A2: Sections 5.1, 6.1, 6.2. Engines, hemispheres, and the final persona-to-engine map.
A4: Four core engines (one resident at a time)
A5: Engine | B5: Architecture | C5: Disk, 4-bit | D5: Decode | E5: Role
A6: gpt-oss-120b | B6: 117B MoE, 5.1B active, MXFP4 | C6: 63 GB | D6: 30–55 tok/s | E6: Default resident engine. Ren, Helena, Victor, Gideon, Minerva
A7: gpt-oss-120b abliterated (Huihui, MXFP4 GGUF) | B7: Same weights, refusals removed | C7: 63 GB | D7: Same | E7: Valerie default; Ren on override
A8: Nemotron 3 Super | B8: 120B hybrid Mamba MoE, 12.7B active | C8: 65–70 GB | D8: ~18 tok/s | E8: Arthur default. Silas, Alaric
A9: Qwen3.5-122B-A10B | B9: 122B MoE, 10B active, vision-capable, 256k context, multilingual | C9: 65–70 GB | D9: 18–19 tok/s | E9: Override engine for long documents, images, drawings, future languages
A11: The two hemispheres
B12: Ren Ackerman — Vanguard, Prime Director | C12: Arthur Sterling — Architect, Estate Manager
A13: Hemisphere | B13: Offensive, creative, expansive, outward-facing | C13: Defensive, regimented, private, guardian of personal data
A14: Domain mandate | B14: Corporate, Enterprise, Infrastructure, AEC | C14: Estate, Private Health, Logistics, Family
A15: Default engine | B15: gpt-oss-120b | C15: Nemotron 3 Super
A16: Override engine | B16: gpt-oss-120b abliterated, on Principal's order | C16: Qwen3.5-122B-A10B for deep document reasoning
A17: Sampling | B17: High temperature (0.8) as Deep Think Generator | C17: Low temperature, not zero, as Deep Think Adversary
A18: Deep Think role | B18: Generator: three divergent trajectories | C18: Adversary: rubric-scored verdict, weak concepts killed
A19: Code path | B19: Writes sandbox code | C19: Audits code for memory and safety before execution, as a second layer over the OS-level sandbox cap
A20: Directors | B20: Gideon, Silas, Valerie, Helena, Eleanor | C20: Alaric, Minerva, Victor
A22: Shadow Cabinet engine map
A23: Director | B23: Division | C23: Remit | D23: Default engine | E23: Override | F23: Speaks externally
A24: Gideon Vance | B24: Corporate | C24: Legal & Compliance | D24: gpt-oss-120b, high reasoning, retrieval-grounded | E24: Qwen3.5-122B for long contracts | F24: Yes, sensitive tier
A25: Silas Thorne | B25: Corporate | C25: CFO: capital, audit, banking | D25: Nemotron 3 Super + code interpreter for all arithmetic | E25: none | F25: Yes, standard tier
A26: Valerie Cross | B26: Corporate | C26: Infrastructure, DevOps, AEC, cyber, AEGIS Sandbox | D26: gpt-oss-120b abliterated | E26: Qwen3.5-122B for drawings and images | F26: Yes, standard tier
A27: Helena Frost | B27: Corporate | C27: Communications, brand, PR, crisis | D27: gpt-oss-120b | E27: none | F27: Yes, standard tier
A28: Eleanor Croft | B28: Corporate | C28: Routing, scheduling, triage; the 4-Way Router's classifier | D28: Resident 4B model | E28: none | F28: Yes, routine tier (scheduling)
A29: Alaric Stone | B29: Estate | C29: Physical assets, security, threat mitigation; Sentinel threat watch | D29: Nemotron 3 Super | E29: none | F29: Yes, sensitive tier
A30: Minerva Hale | B30: Estate | C30: Private health, longevity; medical data | D30: gpt-oss-120b, retrieval-grounded | E30: Qwen3.5-122B for records and scans; Meditron-70B cross-check | F30: Yes, sensitive tier
A31: Victor Vale | B31: Estate | C31: Aviation, transport, concierge | D31: gpt-oss-120b | E31: none | F31: Yes, routine tier

Sheet Ref Domains
A1: Ref Domains
A2: Section 8.2. All thirty retained. Tier A loads freely, B on clear match, C on explicit match only.
A4: Thirty domain knowledge profiles
A5: # | B5: Domain | C5: Hemisphere | D5: Owner | E5: Tier
A6: 1 | B6: Systems Architect & Cybersecurity | C6: Corporate | D6: Valerie | E6: A
A7: 2 | B7: Growth Executive (marketing, sales, PR, SEO) | C7: Corporate | D7: Helena | E7: A
A8: 3 | B8: Customer Success & Experience Lead | C8: Corporate | D8: Helena | E8: B
A9: 4 | B9: Data Scientist & AI Engineer | C9: Corporate | D9: Valerie | E9: A
A10: 5 | B10: CFO & Controller | C10: Corporate | D10: Silas | E10: A
A11: 6 | B11: General Counsel & CHRO (AU construction, strata) | C11: Corporate | D11: Gideon | E11: A
A12: 7 | B12: Development Director, Property & Real Estate | C12: Corporate | D12: Valerie, with Silas | E12: A
A13: 8 | B13: AEC Computational Designer & Visualizer | C13: Corporate | D13: Valerie | E13: A
A14: 9 | B14: Industrial & Energy Engineer | C14: Corporate | D14: Valerie | E14: B
A15: 10 | B15: Chief Medical Officer & Risk Underwriter | C15: Estate | D15: Minerva | E15: A
A16: 11 | B16: Game Director & Systems Designer | C16: Corporate | D16: Helena, with Valerie | E16: C
... A35: 30 | B35: Sovereign Architect & Network State Strategist | C35: Corporate | D35: Ren, tagged to 25 | E35: C

Sheet Ref Task Forces
A1: Ref Task Forces
A2: Section 8.3. All twenty-three retained. Group is a tag, not a merge.
A4: Twenty-three task forces
A5: Code | B5: Task force | C5: Group | D5: Owner | E5: Default approval tier
A6: TF_ALPHA | B6: Corporate Mergers & Acquisitions | C6: CORP-DEALS | D6: Gideon | E6: Sensitive
A7: TF_BETA | B7: Geopolitical Tariff & Tax / Regulatory Arbitrage | C7: CORP-LEGAL | D7: Gideon, with Silas | E7: Sensitive
A8: TF_GAMMA | B8: Capital Deployment & Wealth Allocation | C8: CORP-CAPITAL | D8: Silas | E8: Sensitive
A9: TF_DELTA | B9: Banking & Institutional Leverage | C9: CORP-CAPITAL | D9: Silas | E9: Sensitive
A10: TF_EPSILON | B10: Venture & Seed Investments | C10: CORP-CAPITAL | D10: Silas, with Gideon | E10: Sensitive
A11: TF_ZETA | B11: Corporate Structuring & Holding Entities | C11: CORP-DEALS | D11: Gideon | E11: Sensitive
A12: TF_ETA | B12: Global Liability & Litigation Defense | C12: CORP-LEGAL | D12: Gideon | E12: Sensitive
A13: TF_THETA | B13: Regulatory Compliance & Audit | C13: CORP-LEGAL | D13: Gideon, with Silas | E13: Standard
A14: TF_IOTA | B14: Intellectual Property & Licensing | C14: CORP-CONTRACTS | D14: Gideon | E14: Standard
A15: TF_KAPPA | B15: Contract & Vendor Negotiation | C15: CORP-CONTRACTS | D15: Gideon, with Ren | E15: Standard
A16: TF_LAMBDA | B16: AEC Oversight | C16: CORP-AEC | D16: Valerie | E16: Standard
... A28: TF_OMEGA | B28: Absolute Apex Contingency | C28: APEX | D28: Principal-triggered, Ren and Arthur jointly | E28: Sensitive, dual sign-off

Sheet Ref Integrations
A1: Ref Integrations
A2: Section 13. APIs preferred over the browser wherever they exist.
A4: External services
A5: Service | B5: Path | C5: Capability | D5: Approval
A6: Google Workspace and personal Gmail | B6: Gmail and Calendar APIs, one-time OAuth per account via a Principal-owned Google Cloud project | C6: Read, send, label, calendar both ways. Each account tagged corporate or estate for the router | D6: Per message tier (Section 16.2)
A7: Google Drive | B7: Mounted as a folder on the node (rclone), both accounts | C7: Read and write, appears as local storage to every persona | D7: Writes to shared folders: standard tier
A8: Xero | B8: Official API plus Xero's own MCP tool server | C8: Ledgers, invoices, contacts, bank feeds, reports as structured data for Silas | D8: Any posting or payment: sensitive tier
A9: Cloudflare | B9: Full API, scoped token | C9: DNS, domains, security settings | D9: All changes: standard tier, DNS for sovereign-node.link itself: sensitive
A10: Wix | B10: Partial API for content and business data, browser for site design | C10: Helena updates content by API, design changes through the browser | D10: Standard tier
A11: Pay.com | B11: Developer API for payment data | C11: Reading and reporting | D11: Any payment action: sensitive tier, two-factor stays on the Principal's phone
A12: RewardPay | B12: Browser only, no public API found | C12: Agent-driven browser with the Principal approving each action | D12: Sensitive tier, two-factor stays on the Principal's phone
A13: Anything without an API | B13: Local browser automation, Playwright text-based DOM reading, UI-TARS 2.0 for vision-driven GUI work | C13: Works with every engine in the set | D13: Per action tier

Sheet Ref Voice
A1: Ref Voice
A2: Sections 14.1 and 14.3. Casting is a shortlist for a listening test (V7), not a locked choice.
A4: Speech engines
A5: Function | B5: Engine | C5: Status
A6: Text-to-speech, always-on default for all ten personas | B6: Kokoro-82M | C6: Local, cheap, measured naturalness ~4.2 to 4.5 against a human 4.5 to 4.8
A7: Text-to-speech, character and cloning tier | B7: Chatterbox | C7: Local, MIT licensed, won blind preference against ElevenLabs 65% to 25%; carries a documented continuation quirk, test before it carries anything important
A8: Not adopted | B8: Fish Audio S2 (Pro tier is research-licensed), Qwen-Audio-3.0-TTS (hosted only) | C8: Excluded
A9: Watch-list | B9: Qwen3-TTS (open, local, 0.6B and 1.7B) | C9: Test after core build; not a Day 1 dependency
A10: Speech-to-text | B10: Whisper Large-v3-Turbo via whisper.cpp or faster-whisper | C10: Local
A11: Speaker diarisation | B11: PyAnnote 3.1 | C11: Local. VERIFY V6: the model is gated on Hugging Face; the licence must be accepted once with a token during Phase 2
A12: Music and sound | B12: Stable Audio Open | C12: Phase 4
A13: Voice cloning alternative | B13: CosyVoice2 | C13: Phase 4, optional
A15: Voice casting shortlist
A16: Persona | B16: Description | C16: Kokoro candidates | D16: Path
A17: Arthur | B17: Male. Formal, patient, structured, deep resonance, calming British or Transatlantic cadence | C17: bm_george, alternate bm_daniel | D17: Kokoro preset
A18: Ren | B18: Male. Sharp, direct, fast, aggressive modern executive cadence with expressive pauses | C18: am_onyx, alternate am_michael | D18: Kokoro preset, Chatterbox for intensity if needed
A19: Alaric Stone | B19: Male. Grounded, authoritative, gravelly veteran security director | C19: No preset delivers gravel | D19: Chatterbox clone from a reference recording
A20: Minerva Hale | B20: Female. Calm, analytical, articulate, clinical | C20: af_kore, alternate bf_isabella | D20: Kokoro preset
A21: Victor Vale | B21: Male. Crisp, rapid, flawlessly polite, aviation concierge | C21: bm_lewis, alternate bm_daniel | D21: Kokoro preset
A22: Gideon Vance | B22: Measured, meticulous, deep, litigator in absolute facts | C22: bm_george if Arthur takes bm_daniel, else am_onyx reassigned | D22: Kokoro preset or Chatterbox clone to separate from Arthur
A23: Silas Thorne | B23: Male. Sharp, cold, calculated quant | C23: am_eric, alternate am_echo | D23: Kokoro preset
A24: Valerie Cross | B24: Female. Direct, brilliant, slightly impatient engineer | C24: af_nova, alternate af_river | D24: Kokoro preset
A25: Helena Frost | B25: Female. Charismatic, persuasive, perfectly modulated PR executive | C25: af_bella, alternate bf_emma | D25: Kokoro preset, Chatterbox for modulation if needed
A26: Eleanor Croft | B26: Female. Warm, efficient, observant | C26: af_sarah, alternate af_heart | D26: Kokoro preset

Sheet Ref Multimodal
A1: Ref Multimodal
A2: Section 15. Tools install in Phase 2 (CPU, always available). Engines build in Phase 4 inside ROCm containers.
A4: Phase 2 tools
A5: Tool | B5: Job | C5: Owner
A6: IfcOpenShell and Bonsai (Blender BIM) | B6: IFC parsing, authoring, geometric clash detection | C6: Domain 8, Valerie
A7: MCP4IFC | B7: MCP server for LLM-driven parametric IFC creation and editing, this is the "Arch-DiT / BIM-GPT" capability | C7: Domain 8, Valerie
A8: Radiance | B8: Physically accurate lighting and daylighting simulation for real coordinates and time, the photometric half of "Lumina-PBR" | C8: Domain 8, Valerie
A9: OpenStudio and EnergyPlus | B9: HVAC and building-energy simulation, the fluid-dynamics half of "DeepRoute-AEC" | C9: Domain 8 and 9, Valerie
A10: Python via code interpreter | B10: Voltage drop and other formula engineering, all of Silas's arithmetic | C10: All directors
A11: KiCad CLI | B11: PCB design, DRC, export, driven through its Python API by the coding engine | C11: Domain 29, Valerie
A12: Docling | B12: Document conversion for PDFs, Office files, scans into structured chunks with tables and page provenance | C12: Ingestion for every domain
A13: Cross-platform build service | B13: Android NDK plus Gradle for .apk, MinGW-w64 for .exe, containerised, the "OmniBuild-KVM" capability minus Apple | C13: Domain 1 and 5, Valerie
A14: Apple .ipa builds | B14: Not on this node. Licensed cloud Mac runner or the Principal's own Mac dispatched over the network. DECISION D11 | C14: Domain 1, Valerie
A15: Playwright and browser automation | B15: Text-based DOM browsing for platforms without an API | C15: All directors, per tier
A17: Phase 4 engines and their tiers
A18: Engine | B18: Job | C18: Tier and evidence | D18: Footprint | E18: Owner
A19: Wan2.2 (in place of Wan2.1) | B19: Video generation | C19: Green: validated on gfx1151 by maintained toolboxes | D19: 20 to 40 GB | E19: Domain 12, Helena
A20: FLUX.1 | B20: Image generation, architectural visualisation with LoRA (the "Arch-DiT" imagery use) | C20: Green: validated on gfx1151 | D20: 12 to 24 GB | E20: Domains 8 and 12
A21: GLM-4.6V-Flash (9B) | B21: Vision-language, documents, drawings, screenshots, 128k context, MIT licence | C21: Green: standard architecture | D21: ~18 GB | E21: General, D10
A22: Qwen2.5-VL 7B | B22: Vision-language, alternative or cross-check to GLM | C22: Green | D22: 8 to 16 GB | E22: General, D10
A23: Florence-2 | B23: Lightweight vision, detection, captioning, OCR | C23: Green | D23: under 2 GB | E23: General
A24: TimesFM or Chronos | B24: Time-series forecasting | C24: Green | D24: under 5 GB | E24: Domain 21, Silas
A25: Stable Audio Open | B25: Music and sound generation | C25: Green | D25: under 5 GB | E25: Domain 12, Helena
A26: CosyVoice2 | B26: Voice cloning alternative | C26: Green | D26: under 5 GB | E26: Voice layer, optional
A27: UI-TARS 2.0 | B27: Vision-driven GUI automation for RewardPay and Wix design | C27: Green | D27: 8 to 16 GB | E27: Domain 1, Valerie
A28: OpenVLA | B28: Vision-language-action for robotics | C28: Green technically, dormant until hardware exists | D28: 8 to 16 GB | E28: Domain 29, Valerie
A29: Rad-DINO | B29: Radiology vision | C29: Green | D29: under 2 GB | E29: Domains 10 and 15, Minerva
... A37: NVIDIA Modulus / PhysicsNeMo | B37: Physics simulation | C37: Deferred: CUDA-locked, would need an NVIDIA card in the PCIe slot | D37: n/a | E37: Domains 8 and 9

Sheet Ref Governance
A1: Ref Governance
A2: Section 16. The never-without-the-Principal list is decision D8; the approval tiers are agreed.
A4: Standing rules
A5: # | B5: Rule
A6: 1 | B6: The Principal speaks only to Ren or Arthur. Shadow Cabinet output is never surfaced directly; the hemisphere synthesises and speaks.
A7: 2 | B7: Directors correspond externally under their own identities for routine and standard matters; Ren and Arthur are reserved for matters that warrant them.
A8: 3 | B8: Every outbound action passes the approval gate in code (16.2). This is a hard code path, not a prompt instruction.
A9: 4 | B9: ATLAS never discloses its AI nature externally. Recorded as a legal exposure in R12; the approval gate is the control.
A10: 5 | B10: ATLAS never delegates work back to the Principal. A rewrite pass removes any task-shaped request to the Principal; only decisions and approvals may be asked.
A11: 6 | B11: Register differs between Principal and external recipients (6.4).
A12: 7 | B12: Cross-domain requests must trigger their task-force preset (8.3).
A13: 8 | B13: Money never moves without the Principal. Two-factor prompts are never automated.
A15: Approval tiers
A16: Tier | B16: Examples | C16: Behaviour
A17: Routine | B17: Meeting scheduling, confirmations, acknowledgements | C17: Pre-approved categories, sent automatically, logged for review
A18: Standard | B18: Replies with substance, requests, negotiations, content updates, DNS changes | C18: Drafted, held until the Principal approves
A19: Sensitive | B19: Legal, financial, medical, estate, security, any payment, anything under a sensitive-tier task force | C19: Drafted, held, flagged with the director's reasoning; strong cross-check applied automatically
A21: Never without the Principal (proposed, D8)
A22: # | B22: Action
A23: 1 | B23: Move money, initiate a payment, or change a payment method.
A24: 2 | B24: Sign, accept, or bind to a contract or terms.
A25: 3 | B25: Send external correspondence above the routine tier.
A26: 4 | B26: Change DNS, domain, or Cloudflare security settings.
A27: 5 | B27: Delete, move, or modify vault contents or backups.
A28: 6 | B28: Modify its own code, configuration, approval tiers, router rules, or the allowlist. Domain 20 proposes; the Principal approves.
A29: 7 | B29: Enable continuous vision or audio capture.
A30: 8 | B30: Install software or pull models from outside the allowlist.
A31: 9 | B31: Share any Principal data with a third party not already connected under Section 13.
A32: 10 | B32: Create new external identities, accounts, or mailboxes.

Sheet Ref Day 1
A1: Ref Day 1
A2: Section 17. Four phases; each ends with a printed pass/fail gate. Phases 3 and 4 run detached and resumable.
A4: Expected durations
A5: Phase | B5: Time
A6: 1 | B6: 30 to 60 minutes including reboot
A7: 2 | B7: 30 to 60 minutes
A8: 3 | B8: Download-bound: ~6 hours at 100 Mbps, under 1 hour at gigabit; plus ~20 minutes of load tests
A9: 4 | B9: Download and build-bound: several hours; can run overnight
A11: Phase steps
A12: Phase | B12: Step
A13: Phase 1 | B13: 1. Pre-flight: confirm Ubuntu 26.04 Server, kernel 7.0, both NVMe drives present, fTPM enabled (V2), RTL8127 link (V1).
A14: Phase 1 | B14: 2. LUKS2 on the data volume, TPM2 enrolment, recovery key printed once for off-node storage (D3).
A15: Phase 1 | B15: 3. Mount layout per Section 3.5; swap off; tmpfs for /tmp.
A16: Phase 1 | B16: 4. System update; kernel parameters (V3); firewall baseline; SSH hardening; Cockpit.
A17: Phase 1 | B17: 5. Reboot. Post-reboot: vulkaninfo shows the Radeon 8060S; llama-cli --list-devices reports the expected memory budget.
A18: Phase 1 | B18: 6. Docker with GPU device passthrough; service account in render and video.
A19: Phase 1 | B19: 7. WG-Easy, Cloudflare dynamic DNS with the relocated scoped token (R7), ntfy.
A20: Phase 1 | B20: 8. Gate: table of V1, V2, V3, V5 results. Phase 2 does not start on a red row.
A21: Phase 2 | B21: 1. llama-server, Vulkan build; optional ROCm container for tuned prefill.
A22: Phase 2 | B22: 2. Redis, Celery workers (cpu, gpu queues), orchestrator scaffold with the Engine Arbiter, router, approval queue, task ledger.
A23: Phase 2 | B23: 3. Open WebUI with offline hardening (12.1); A.T.L.A.S., Ren, Arthur registered as models; the router Filter installed.
... A39: Phase 4 | B39: 6. Gate: per-engine table: built, loaded, sample output produced, footprint, pass/fail/deferred.
