Workbook

Sheet Summary
A1: A.T.L.A.S. Build Baseline
A2: Companion to docs/ATLAS_FRAMEWORK_REVIEW.md v0.4.0 (2026-10-17), built from it by scripts/day1/tools/build-baseline-workbook.py (D-27). v0.4.0 records the action register the Principal returned on 2026-10-16, every row approved as recommended (P-10 with the Principal's change: Eleanor's router stays at 4B for classification only, and her own persona work moves to GLM-5.3-Flash; the questions on P-10 and on memory headroom, N-01 and N-03, are answered in the document's 5.3, 4.1 and 4.2): llama.cpp re-pinned to build tag b11474, with the old pin v0.4.1 kept only for the output-parity test V25 (sheet 4); GLM-5.3-Flash UD-IQ4_XS (with its glm5v projector, also the vision engine and the long-document route) and DeepSeek-V4-Flash-0731 UD-Q8_K_XL (Arthur and the Apex) as the Day 1 seats, gpt-oss-120b as the fast utility and fallback floor, the 4B router unchanged; one LLM seat resident at a time; the Engine Arbiter budgeting exact file bytes; the Qwen3 4B embedder and reranker on the CPU, replacing the bge pair before Day 1; the Phase 3 pull cut to about 448 GB; and pyannote community-1 now (C-06). D16 to D27 on sheet 1 record the decisions (D16 to D18 reopen D4, D10 and D12) and C28 to C30 on sheet 2 supersede C23, C25 and C26; R29 to R33 on sheet 3, with R4, R17, R19 and R20 restated, were acknowledged by the Principal on 2026-10-17, the day the Principal also approved the six RAM fixes (S55: an explicit prompt-cache cap on every engine, a 4 GiB /tmp, at most 8 Celery cpu workers, memory caps on Kokoro, speaches and Docling, an order for the out-of-memory killer, and a seat whose start failed stopped before its reservation goes) and confirmed V25's pass marks, with no new version number. The specialist seats (Intern-S1, Ling-3.0-flash-Fin, Baichuan-M3), slot save and restore, swap batching, the speech, image and OCR companions, the Qwen3.8-Flash-Next and Nemotron 3 Super pulls, the drafters and the DeepSeek V4.1 trial are phased after Day 1, each with its to-do; where an approved row leaves an input to the Principal (the decode floors, the context targets, the test sets), its default is built and a to-do raised (sheet 5). Later on 2026-10-17 (S56) the Principal approved the recommendations for those inputs: decode floors at 8k (gpt-oss-120b 25, GLM-5.3-Flash 6, DeepSeek-V4-Flash-0731 4, the router 20 tok/s) with prefill floors and placement checks, the D-16 profile of the phased medical and science seats, no dedicated coder seat (Qwen3-Coder-Next not pulled), EmbeddingGemma 2 dropped, MedGemma 1.5 4B only on conditions, and the designs of the seat test sets and the V4.1 trial set; and recorded a 2,000 Mbps line with the node moving to a cable on its 10 GbE port before Phase 1. What those answers still leave open is on sheet 5. The same day (S57) the Principal's statements were recorded: ATLAS's Australian law is that of the Commonwealth, VIC, NSW and QLD; an Australian Standard's text is held only under the Principal's own licence, otherwise its number, edition and free commentary; the briefs for the seat test sets are collected once ATLAS is live, from real examples; and the MedGemma licence decision is a task for the live ATLAS with the Principal present. Two proposals await the Principal, not decided: the 16 Australian-law tasks spread across the four jurisdictions, and about 10 Australian tax and finance tasks. The uncensored-seat items (D-07, D-08, D-09, D-58, N-10, P-05, P-17, S-05) are unchanged by this revision and remain the Principal's to configure. Until v0.4.0 this workbook was the closed v0.3.5 record of 2026-10-12: Ubuntu Server kept over Fedora 44 KDE Plasma (C27), the crash-kernel memory reclaimed with panic=10 (S48), kexec handover off (S49), the hardware watchdog (S50), torchaudio pinned so Phase 4 stays on ROCm 10.0.0 (S51), every request kept inside its engine's slot with the Phase 3 memory records (S52), and the pruning fixes (S53), with every decision and resolution confirmed and every risk acknowledged. The Day 1 scripts under scripts/day1 never stop on a missing input from the Principal (they ask once, defer, and keep a to-do list). Nothing has been executed.
A4: How to use this workbook
A5: 1. Sheets 1, 2 and 3 are a record of your answers of 2026-09-21, 2026-10-05 (D15: Secure Boot enabled), 2026-10-08 (C27: Ubuntu kept; R22 to R25 acknowledged), 2026-10-13 (R26 to R28 acknowledged), 2026-10-16 (the action register: D16 to D27 and C28 to C30) and 2026-10-17 (R29 to R33 and the restated R4, R17, R19 and R20 acknowledged; later, S56: your answers to the open inputs in D16 to D26, R9 and R20 restated with B-27; S57: in D20, the briefs collected once ATLAS is live). Nothing on them needs you now. Sheet 5 records the Secure Boot BIOS setting made and the USB recovery drive in hand (both confirmed 2026-10-13) and lists the optional items the scripts ask for at a prompt and the inputs still left to you, each with the default already built. Sheet 4 fills during Day 1.
A6: 2. Use the dropdown in each response column. Cells colour green, amber, or red as you answer.
A7: 3. Where you choose 'Change' or 'Disagree', write the alternative in the next column so it can be folded back into the brief.
A8: 4. Sheet 4 (Verification) is filled during Day 1 as each phase gate runs, not now; its Result column shows amber 'Not yet run' until then.
A9: 5. The Ref sheets carry the agreed maps (hardware, platform watch-list and memory budget, the Day 1 and phased engines, cabinet, domains, task forces, integrations, voice, multimodal, governance, Day 1 and its test plan) for checking against.
A10: 6. Outstanding before Phase 1: sheet 5 row 32, the cable (your choice of 2026-10-17, S56): plug it into the 10 GbE port not marked DASH and a 2.5 GbE router port, move the reservation and the UDP 51820 forward to that port's MAC and take Wi-Fi off the LAN subnet (pre-flight warns, never stops, if it is not done). The other blank sheet 5 rows are optional or wait until after Day 1, and can be given at the prompt or left for the live ATLAS; sheet 5 row 29 still asks you to confirm that the installer's encryption option was taken (if it was not, Day 1 warns and records a to-do, never a stop). To reopen any other item, change its response cell (Changed my mind, Disagree, Discuss or No) and write the reason beside it; the progress table below shows it at once.
A12: Legend
A13: Yellow fill | B13: Cell for you to fill in
A14: Green | B14: Confirmed / Accept / Yes / N/A / Pass
A15: Amber | B15: Deferred / Not yet run (Not yet run counts as Remaining, not Hold)
A16: Red | B16: Changed my mind / Disagree - return to decisions / Discuss / No / Fail
A19: Progress (formulas update as you answer)
A20: Sheet | B20: Items | C20: Answered | D20: Positive | E20: Hold | F20: Negative | G20: Remaining
A21: 1 Decisions | B21: =COUNTA('1 Decisions'!$A$5:$A$31) | C21: =B21-G21 | D21: =COUNTIF('1 Decisions'!$E$5:$E$31,"Confirmed") | E21: =0 | F21: =COUNTIF('1 Decisions'!$E$5:$E$31,"Changed my mind") | G21: =COUNTBLANK('1 Decisions'!$E$5:$E$31)
A22: 2 Resolutions | B22: =COUNTA('2 Resolutions'!$A$5:$A$34) | C22: =B22-G22 | D22: =COUNTIF('2 Resolutions'!$D$5:$D$34,"Accept") | E22: =0 | F22: =COUNTIF('2 Resolutions'!$D$5:$D$34,"Disagree - return to decisions") | G22: =COUNTBLANK('2 Resolutions'!$D$5:$D$34)
A23: 3 Risks | B23: =COUNTA('3 Risks'!$A$5:$A$37) | C23: =B23-G23 | D23: =COUNTIF('3 Risks'!$F$5:$F$37,"Yes") | E23: =0 | F23: =COUNTIF('3 Risks'!$F$5:$F$37,"Discuss") | G23: =COUNTBLANK('3 Risks'!$F$5:$F$37)
A24: 4 Verification | B24: =COUNTA('4 Verification'!$A$5:$A$29) | C24: =B24-G24 | D24: =COUNTIF('4 Verification'!$D$5:$D$29,"Pass") | E24: =COUNTIF('4 Verification'!$D$5:$D$29,"Deferred") | F24: =COUNTIF('4 Verification'!$D$5:$D$29,"Fail") | G24: =COUNTBLANK('4 Verification'!$D$5:$D$29)+COUNTIF('4 Verification'!$D$5:$D$29,"Not yet run")
A25: 5 Checklist | B25: =COUNTA('5 Checklist'!$A$5:$A$46) | C25: =B25-G25 | D25: =COUNTIF('5 Checklist'!$D$5:$D$46,"Yes")+COUNTIF('5 Checklist'!$D$5:$D$46,"N/A") | E25: =0 | F25: =COUNTIF('5 Checklist'!$D$5:$D$46,"No") | G25: =COUNTBLANK('5 Checklist'!$D$5:$D$46)
A26: Total | B26: =SUM(B21:B25) | C26: =SUM(C21:C25) | D26: =SUM(D21:D25) | E26: =SUM(E21:E25) | F26: =SUM(F21:F25) | G26: =SUM(G21:G25)
A27: Positive / Hold / Negative map to each sheet's dropdown: Decisions = Confirmed / - / Changed my mind; Resolutions = Accept / - / Disagree; Risks = Yes / - / Discuss; Verification = Pass / Deferred / Fail, with Not yet run counted as Remaining; Checklist = Yes or N/A / - / No.
A30: Example of a completed decision row (format only, not editable, not counted; grey marks where your text would go)
A31: ID | B31: Decision | C31: Recommendation | D31: Blocks | E31: Your response | F31: Your answer or alternative | G31: Notes
A32: D0 | B32: Example: which mail client the node uses | C32: Client A | D32: Phase 2 | E32: Changed my mind | F32: Use client B, it already holds my accounts | G32: Discussed 2026-09-21

Sheet 1 Decisions
A1: 1 Decisions
A2: Section 19. All twenty-seven are closed. D15 (Secure Boot and the TPM binding) was decided on 2026-10-05 as option (a), Secure Boot enabled in the BIOS. D16 to D27 (v0.4.0) record the action register the Principal returned on 2026-10-16, every row approved as recommended (P-10 with the Principal's change); D16, D17 and D18 reopen D4 (the retrieval models), D10 (the vision engine) and D12 (Meditron), whose rows say so in their Note. D16, D18, D20, D22, D24 and D26 carry the Principal's answers of 2026-10-17 to the inputs they had left open (S56: the decode, prefill and deep-tier floors, the D-16 profile, no dedicated coder seat, EmbeddingGemma 2 dropped, the test-set and trial designs). D20 also records S57: the D-49 briefs are collected once ATLAS is live, from real examples.
A4: ID | B4: Decision | C4: Your answer (as given) | D4: Note | E4: Still stands? | F4: If changed, what instead
A5: D1 | B5: Inference backend: llama-server or Ollama | C5: llama-server, Ollama not installed | D5: Accepted as recommended | E5: Confirmed
A6: D2 | B6: Secure Boot: disable, or enrol keys | C6: Disabled on a headless node behind a firewall | D6: Accepted as recommended; superseded by D15 (enabled) | E6: Confirmed
A7: D3 | B7: Where the LUKS recovery key and restic passphrase live | C7: On the node and on an external USB drive | D7: Changed by the Principal. See R16: the USB copy is the one that survives node loss, so it must be stored away from the node | E7: Confirmed
A8: D4 | B8: Router model and embedding model | C8: Qwen3.5 4B-class instruct, bge-m3, bge-reranker-v2-m3 | D8: Accepted as recommended; reopened in v0.4.0 by D16 | E8: Confirmed
A9: D5 | B9: Whether the reserve domains are adopted | C9: Adopted now, with nine further areas supplied. Six new domains, five subspecialty folds | D9: Changed by the Principal (8.2, C24) | E9: Confirmed
A10: D6 | B10: Sentinel feed list | C10: CoinDesk, ASX and US index feed, RSS news, node telemetry | D10: Accepted as recommended | E10: Confirmed
A11: D7 | B11: Graph layer: GraphRAG or LightRAG | C11: LightRAG | D11: Accepted as recommended | E11: Confirmed
A12: D8 | B12: The never-without-the-Principal list | C12: The ten items in 16.3 are binding | D12: Accepted as recommended | E12: Confirmed
A13: D9 | B13: Retention rule for chats, logs, backups | C13: Defaults in 10.4 and 9.5 are binding | D13: Accepted as recommended | E13: Confirmed
A14: D10 | B14: Primary vision engine | C14: Qwen2.5-VL-72B at Q8_0, sole vision engine. GLM-4.6V-Flash and the 7B and 32B variants dropped | D14: Changed by the Principal: maximum quality, slow speed accepted (15.2, C25); reopened in v0.4.0 by D17 | E14: Confirmed
A15: D11 | B15: Apple .ipa build path | C15: Removed from the design. No Mac, no cloud runner, no macOS virtualisation. iOS source is still written, compiled elsewhere if Mac access ever exists | D15: Changed by the Principal | E15: Confirmed
A16: D12 | B16: Meditron-70B: include or skip | C16: Included in Phase 3 at Q8_0 | D16: Accepted, with "include now" noted; reopened in v0.4.0 by D18 | E16: Confirmed
... A31: D27 | B31: Hardware, drafters and the watch-list | C31: No discrete GPU now (D-62 option (a)); no second machine (D-63 option (a)); Lucebox's no-hardware ideas recorded on the watch-list (D-64 option (a)); the drafters kept in the disk set and decided per engine after the node speed tests, native MTP or DSpark only (D-61) | D31: Approved by the Principal on 2026-10-16 in the returned action register, as recommended (3.7, 15.4, 15.5) | E31: Confirmed

Sheet 2 Resolutions
A1: 2 Resolutions
A2: Section 18. C1 to C26 accepted in the workbook returned 2026-09-21; C27 (Ubuntu Server kept over Fedora 44 KDE Plasma) decided by the Principal on 2026-10-08; C28 to C30 (v0.4.0: the least-quantised rung that fits each seat alone, one vision engine on the GLM unit, one LLM seat resident at a time), superseding C23, C25 and C26, approved by the Principal on 2026-10-16 in the returned action register. Closed record; change a cell only to reopen one.
A4: ID | B4: Contradiction or ambiguity found | C4: Resolution adopted | D4: Your response | E4: Notes
A5: C1 | B5: Backend named as llama.cpp, then Ollama, then llama-server at different points | C5: llama-server primary on Vulkan; Ollama optional. D1 confirms | D5: Accept
A6: C2 | B6: Ubuntu 26.04 chosen, but Phase 4 needs ROCm PyTorch, which does not install cleanly on the 26.04 host. Out of date since v0.3.5 (S51): AMD's ROCm 10.0.0 support data lists this chip on 26.04 with the GA 7.0 kernel and the in-box driver, and 26.04's universe carries ROCm 7.1 (VERIFIED) | C6: ROCm lives inside containers; host runs Vulkan only (3.4). The resolution stands for the design's own reasons: isolation, exact pinning, and independence from Ubuntu's ROCm line (3.4, S51) | D6: Accept | E6: Reason corrected in v0.3.5 (S51, approved by the Principal 2026-10-11); the resolution stands
A7: C3 | B7: Windows 96 GB and Linux ~120 GB budgets both appeared | C7: Linux numbers are binding (4.1) | D7: Accept
A8: C4 | B8: KV-cache proposal mixed shipped features with unmerged research | C8: Only shipped features adopted (4.3) | D8: Accept
A9: C5 | B9: Meditron listed among PyTorch engines | C9: Runs through llama.cpp (5.1) | D9: Accept
A10: C6 | B10: Arthur's override bound to the abliterated engine "for legal dissection" | C10: Override is Qwen3.5 (6.1). *v0.4.0:* that override is now GLM-5.3-Flash, since Qwen3.5-122B-A10B left the roster (6.1) | D10: Accept | E10: Override restated in v0.4.0 (GLM-5.3-Flash replaces the retired Qwen3.5-122B-A10B); the addendum is unchanged
A11: C7 | B11: Gideon and Minerva bound to the abliterated engine "for zero-hallucination" | C11: Standard engine, retrieval-grounded (6.2) | D11: Accept
A12: C8 | B12: Router described as an Open WebUI pipeline | C12: Lives in the orchestrator; Filter is a relay (7.1) | D12: Accept
A13: C9 | B13: Domain 27 phrased as "memetic warfare" and "sentiment manipulation" | C13: Retained under Helena with phrasing softened to legitimate growth and attribution work | D13: Accept
A14: C10 | B14: Domain profiles' "Stateless MRTR, dispatch and decouple" removes the approval gate | C14: Isolated-context dispatch with tracked completion (8.6) | D14: Accept
A15: C11 | B15: Sentinel described as a WSL2 cron job | C15: systemd timer; there is no WSL (9.3) | D15: Accept
A16: C12 | B16: Sentinel fed to Ren | C16: Alaric and Silas under Arthur (9.3) | D16: Accept
A17: C13 | B17: AEGIS described as a single zip | C17: restic (9.5) | D17: Accept
A18: C14 | B18: AEGIS destination on the same drive | C18: Second drive plus optional external (9.5) | D18: Accept
A19: C15 | B19: Celery framed as freeing "a background hardware thread" for a backtest that may call an LLM | C19: CPU work decouples; GPU calls still serialise (9.7) | D19: Accept
A20: C16 | B20: Estate memory inside the vault versus the vault as on-demand top-secret storage | C20: Estate memory on the LUKS volume; vault content never persisted (10.5) | D20: Accept
A21: C17 | B21: Four engine names that do not exist | C21: Real replacements (15.3) | D21: Accept
A22: C18 | B22: "Vector Cortex replaces chat logs" versus Open WebUI's own database | C22: Supplements; retention rule under D9 (10.4) | D22: Accept
... A26: C22 | B26: Whether to adopt the amd64v3 or amd64v4 optimised archives | C26: Neither. The gain is on CPU-bound distribution packages, not GPU inference (3.1) | D26: Accept
A27: C23 | B27: Everything quantised to 4-bit under a 128 GB constraint that no longer exists | C27: Q8_0 for Nemotron, Qwen3.5, Qwen2.5-VL-72B and Meditron; MXFP4 retained for gpt-oss as its native form; Q4_K_XL for the Apex engine (5.1). Superseded by C28 in v0.4.0 | D27: Accept | E27: Superseded by C28 in v0.4.0 (approved by the Principal 2026-10-16 in the returned action register); kept as the record
A28: C24 | B28: Two domains held in reserve pending a stated need (old D5) | C28: Reserve closed. Six new domains, five subspecialty folds (8.2) | D28: Accept
A29: C25 | B29: Vision split across GLM-4.6V-Flash, Qwen2.5-VL-7B and a 32B that v0.1 wrongly said did not exist | C29: One engine: Qwen2.5-VL-72B at Q8_0. The 32B is real and official, but the Principal chose maximum quality (15.2). Superseded by C29 in v0.4.0 | D29: Accept | E29: Superseded by C29 in v0.4.0 (approved by the Principal 2026-10-16 in the returned action register); kept as the record
A30: C26 | B30: "Two engines at once" ambiguous between residency and generation | C30: Two may be resident; exactly one generates, everywhere, including Celery jobs (4.2). Superseded by C30 in v0.4.0 | D30: Accept | E30: Superseded by C30 in v0.4.0 (approved by the Principal 2026-10-16 in the returned action register); kept as the record
A31: C27 | B31: Ubuntu Server 26.04.1 versus Fedora 44 KDE Plasma, raised by the Principal on 2026-10-07 | C31: Ubuntu Server 26.04.1, re-confirmed 2026-10-08: five years without a major upgrade, a fixed kernel series, a dependable Remote Desktop login without autologin, AMD's vendor support for the chip, and no rewrite of the reviewed scripts (3.1). New in v0.3.4 | D31: Accept
A32: C28 | B32: C23's rule (the highest quantisation that leaves working headroom) sized files for a co-resident partner and kept DeepSeek-V4-Flash-0731 at UD-Q4_K_XL on a misread size; the Principal's directives of 2026-10-15 put result quality first | C32: Supersedes C23 (v0.4.0, approved by the Principal on 2026-10-16 in the returned action register; D-11 (a), D-29 (a), D-59 (b)). Each seat runs the least-quantised rung that fits it alone, with its measured quality cost stated: DeepSeek-V4-Flash-0731 at UD-Q8_K_XL (bit-exact), GLM-5.3-Flash at UD-IQ4_XS (the one lossy rung, provisional until T-03), gpt-oss-120b with an F16 trunk and its native MXFP4 experts; the KV cache at f16 where it is cheap, q8_0 elsewhere and q4_0 nowhere, the abliterated entry unchanged (Section 1, 4.3, 5.1) | D32: Accept | E32: New in v0.4.0, approved by the Principal 2026-10-16 in the returned action register (D-11 (a), D-29 (a), D-59 (b))
A33: C29 | B33: C25 made Qwen2.5-VL-72B at Q8_0 the one vision engine; with one LLM seat resident, a separate 79 GB vision engine would cost a swap for every image | C33: Supersedes C25 (v0.4.0, approved by the Principal on 2026-10-16 in the returned action register; D-20 (a), D-21 (a)). Still one vision engine: GLM-5.3-Flash with its glm5v projector on its own unit, so a look costs no swap while GLM is resident. Qwen2.5-VL-72B is retired. The phased OCR companion transcribes and does not reason, so it is not a second vision engine (5.1, 14.4, 15.2) | D33: Accept | E33: New in v0.4.0, approved by the Principal 2026-10-16 in the returned action register (D-20 (a), D-21 (a))
A34: C30 | B34: C26 read "two engines at once" as two resident and one generating; the two large Day 1 seats hold 147 to 151 GiB of weights each, so neither fits beside any other seat, and one seat at a time is made the rule for every seat | C34: Supersedes C26 (v0.4.0, approved by the Principal on 2026-10-16 in the returned action register; D-32 (a)). One LLM seat is resident at a time, and exactly one generation runs, everywhere, Celery jobs included. The limit is the setting ATLAS_ARBITER_MAX_RESIDENT (default 1, range 1 to 2), so two-seat residency can return without a code change; the companions, Chatterbox and the Phase 4 engines are not seats (4.2 rules 3 and 7) | D34: Accept | E34: New in v0.4.0, approved by the Principal 2026-10-16 in the returned action register (D-32 (a))

Sheet 3 Risks
A1: 3 Risks
A2: Section 20. R1 to R21 acknowledged in the workbook returned 2026-09-21; R22 and R23 (v0.3.2) and R24 and R25 (v0.3.4: the xrdp exposure and the unattended-reboot gap) acknowledged by the Principal on 2026-10-08. R23 is mitigated by D15 (Secure Boot enabled; the BIOS setting confirmed made on 2026-10-13). R26 to R28 (v0.3.5, S53, 2026-10-12: the ledger's 30-day purge not yet wired into the sweep, Chroma 1.5.9's soft deletes, and the once-silent failed sweep, now pushed to the phone) acknowledged by the Principal on 2026-10-13. R29 to R33 (v0.4.0, S-47: the re-pin, GLM-5.3-Flash's lossy rung, swap and re-prefill latency, the companions' share of the engine budget, the phased DeepSeek V4.1 trial engine) and R4, R17, R19 and R20 as restated in v0.4.0 acknowledged by the Principal on 2026-10-17 (S55). Later that day (S56) R9 (applicable, the node moving to the cable on its 10 GbE port) and R20 (lowered to Low) were restated with B-27 and R33's mitigation amended with D-47, both approved by the Principal with the other open-input recommendations.
A4: ID | B4: Risk | C4: Likelihood | D4: Impact | E4: Mitigation | F4: Acknowledged | G4: Notes
A5: R1 | B5: PyTorch on gfx1151 fails in Phase 4. As first written: no official gfx1151 wheel, and the community wheel may break on update. Amended (S15, S51): AMD now publishes the wheels (ROCm 10.0.0, torch 2.13.0); what remains is the open hang report #6530 (3.4); S51 pinned torchaudio, the one package that could have pulled a build for another ROCm version into the image | C5: High | D5: High for Phase 4, none for the LLM layer | E5: Pin versions (every package the Dockerfile names from AMD's index, torchaudio included since S51), per-engine pass/fail, containerised so the host is untouched | F5: Yes | G5: Amended in v0.3.5 (S51, approved by the Principal 2026-10-11): wheel and hang-report facts corrected
A6: R2 | B6: Ollama's Vulkan path immature on 26.04 | C6: Medium | D6: High if chosen | E6: D1: llama-server primary | F6: Yes
A7: R3 | B7: ROCm 7.2.x does not install on the 26.04 host kernel. Amended in v0.3.5 (S51): out of date, since AMD's ROCm 10.0.0 support data lists this chip on 26.04 with the GA 7.0 kernel and the in-box driver, and 26.04's universe carries ROCm 7.1 (VERIFIED) | C7: Low since S51 (was Certain) | D7: Medium | E7: Never install ROCm on the host, containers only (3.4), now for isolation, exact pinning and independence from Ubuntu's ROCm line | F7: Yes | G7: Amended in v0.3.5 (S51, approved by the Principal 2026-10-11): out of date, likelihood lowered from Certain to Low
A8: R4 | B8: KV quantisation silently falls back to full precision on an unsupported architecture. *Restated in v0.4.0 (S-48):* GLM-5.3-Flash and DeepSeek-V4-Flash-0731 run an f16 cache (D-29 option (a)), so on Day 1 only gpt-oss-120b, the router and the CPU pair, and the unchanged abliterated entry (q4_0, as in v0.3.5), run a quantised one. GLM may need flash attention off on Vulkan (T-04), which would rule out a quantised V cache for it. Each architecture prints its own number of KV proof lines (two on GLM, its attention and indexer caches), and a phased engine's count is set at its pull. The restatement was acknowledged by the Principal on 2026-10-17. | C8: Medium | D8: High, unexpected OOM | E8: V4 per-model check, on every proof line an engine prints (kv_proof_lines) | F8: Yes | G8: Restated in v0.4.0 (S-48, 2026-10-16); acknowledged 2026-10-17
A9: R5 | B9: A second engine loads before the first releases memory, node crashes | C9: Medium without an arbiter | D9: High | E9: Engine Arbiter polls GPU memory before every load (4.2) | F9: Yes
A10: R6 | B10: GraphRAG indexing is LLM-heavy and slow here | C10: High | D10: Medium | E10: Idle-time Celery job on the resident small model, D7 LightRAG | F10: Yes
A11: R7 | B11: Cloudflare token in a plain-text file | C11: Certain today | D11: High | E11: Scoped token, mode 600, outside backups and repo (12.3) | F11: Yes
A12: R8 | B12: Open WebUI phones home by default | C12: Certain unless hardened | D12: High for the zero-cloud rule | E12: Offline hardening in Phase 2 (12.1) | F12: Yes
A13: R9 | B13: 10GbE driver unavailable. *Restated in S56 (B-27, approved by the Principal on 2026-10-17): applicable,* since the node moves to the cable on its 10 GbE port not marked DASH. With it: a DASH-enabled port would expose an out-of-band management path on the LAN that ufw does not see (INFERRED), and Wi-Fi left on the LAN subnet can make the interface-bound DNS, ufw and DOCKER-USER rules drop traffic | C13: Low (was Not applicable): kernel 7.0's r8169 carries the RTL8127A family and handles its DASH variant, and linux-firmware ships rtl_nic/rtl8127a-1.fw (VERIFIED) | D13: Medium (was None): no LAN until Wi-Fi is set back as LAN_IFACE and Phase 1 step 4 is re-run | E13: Pre-flight notes the driver and MAC and warns, never stops, on the controller the driver treats as the DASH part, on Wi-Fi as LAN_IFACE and on a second interface on the LAN subnet; V1 records the driver and link speed and stays informational; the non-DASH port, with DASH left off; Wi-Fi taken off the LAN subnet (Section 22) | F13: Yes | G13: Restated in S56 (B-27, approved by the Principal 2026-10-17): applicable with the cable
A14: R19 | B14: DeepSeek V4 Flash llama.cpp support is newer than the other engines. *Generalised in v0.4.0 (S-26, S-47):* every engine whose support is newer than the rest; on Day 1 the Apex, DeepSeek-V4-Flash-0731, and GLM-5.3-Flash (glm5-next, first in b11279); at its pull Qwen3.8-Flash-Next (qwen4exp). The restatement was acknowledged by the Principal on 2026-10-17. | C14: Medium | D14: Medium for the Apex; high for GLM-5.3-Flash, which carries seven seats, vision and long documents | E14: Its own V22 row in the Phase 3 gate; a failure defers the engine without blocking the phase or the other engines, and its seats move to their recorded fallbacks by the Principal's decision (6.2, D-40) | F14: Yes | G14: Restated in v0.4.0 (S-26, S-47, 2026-10-16); acknowledged 2026-10-17
A15: R20 | B15: Wi-Fi throughput and stability over a ~690 GB download. *Restated in v0.4.0 (S-34):* about 448 GB in Phase 3 (D-42 option (b)), about 842 GB of phased engines in a later pull, about 1.9 TB in all (D-41 option (a)). The restatement was acknowledged by the Principal on 2026-10-17. *Restated again in S56 (B-27, approved by the Principal on 2026-10-17):* the node is on the cable, so Wi-Fi no longer applies. What remains is the rate one download stream gets from Hugging Face's CDN to Australia, unmeasured: 400 Mbps planned (about 2.5 hours for the 448 GB), about 5 hours at 200 Mbps; about 757 GB of phased engines, about 1.8 TB in all | C15: Low (was Medium) | D15: Low, time only | E15: Phases 3 and 4 detached and resumable; retries are free; only the core seats are pulled before Day 1's tests; the optional 60-second single-stream test sets DOWNLOAD_MBPS; parallel shard downloads (ATLAS_PULL_JOBS) for the phased pull after a short test | F15: Yes | G15: Restated in v0.4.0 (S-34, 2026-10-16); acknowledged 2026-10-17; restated again in S56 (B-27, approved by the Principal 2026-10-17): lowered to Low
A16: R21 | B16: XFCE and xrdp widen the surface beyond a headless server | C16: Low | D16: Medium | E16: Bound to LAN and WireGuard only, never internet-facing; no desktop autologin | F16: Yes
A17: R22 | B17: The atlas service user is in the docker group, which is root-equivalent on the host; the orchestrator needs the socket for the sandbox and Phase 4 containers | C17: Medium | D17: High if the orchestrator is ever compromised | E17: Accepted for Day 1 and recorded in every script header; Day 2 options are rootless Docker or a socket proxy that allows only the sandbox and engine images. New in v0.3.2 | F17: Yes | G17: Acknowledged 2026-10-08
A18: R23 | B18: TPM2 unlock bound to PCR 7 with Secure Boot disabled unseals for any boot medium (see D15) | C18: Medium | D18: High for physical theft of the node | E18: D15 closed as Secure Boot enabled (v0.3.3); the Principal confirmed the BIOS setting made on 2026-10-13 (workbook sheet 5), so the risk is mitigated subject to pre-flight's own check on Day 1: were it found off, pre-flight warns, V2 notes it and the to-do secure-boot stays open; the enrolment itself proceeds. New in v0.3.2 | F18: Yes | G18: Acknowledged 2026-10-08
A19: R24 | B19: xrdp is the LAN service with known unpatched flaws reachable before login: 26.04 packages 0.10.1 in universe, eighteen 2026 xrdp CVEs (fixed upstream in 0.10.6 and 0.10.6.1) are still "needs-triage" for 26.04, Ubuntu Pro's esm-apps carries no fix, and 0.10.1 runs as root. (SSH, Cockpit, Open WebUI and ntfy are also reachable before login from the LAN; none has a comparable open list.) | C19: Medium | D19: High (code execution as root) if a LAN device or a WireGuard peer is hostile | E19: v0.3.4: port 3389 only from the LAN subnet and WireGuard; the VNC proxy entry (vnc-any, the CVSS 9.8 CVE-2026-41252 path, also commented out upstream in 0.10.6.1), the NeutrinoRDP proxy entry (its module is not shipped) and Xvnc switched off; no root login, no alternate shell, TLS only; optional RDP_ALLOW_FROM (addresses inside the LAN, never the WireGuard bridge, checked before the firewall is touched) narrows the LAN side to the Principal's PC, and step 5b records the to-do with the LAN address the PC connected from. Residual: the remaining pre-login bugs from those hosts. Watch for a 26.04 xrdp security update; a later option is to keep 3389 on WireGuard only. New in v0.3.4 | F19: Yes | G19: Acknowledged 2026-10-08
A20: R25 | B20: Unattended upgrades install security updates from the release and security pockets but never reboot, and do not update Docker CE or Google Chrome (third-party repositories), so kernel and library fixes take effect only at the next reboot | C20: Medium | D20: Medium | E20: Accepted for Day 1: an automatic reboot would interrupt long jobs. Day 2: the live ATLAS reports "reboot required" and pending Docker CE/Chrome updates through ntfy and schedules the reboot with the Principal. New in v0.3.4 | F20: Yes | G20: Acknowledged 2026-10-08
A21: R26 | B21: The ledger's 30-day purge of operational rows (D9, 10.4) is written (Ledger.purge_expired, which refuses to run without an archive callback) but nothing calls it: arbiter_decisions, routing_decisions, tasks and decided approvals (30 days) and sentinel_pulses (365 days) grow without bound (VERIFIED at this commit; strikes are permanent by design) | C21: Certain that the tables grow; Low that it harms (one owner, small rows, a WAL SQLite file on the 8 TB drive, in every nightly backup) | D21: Low | E21: Phased item (S53, with the measurement layer in the first months): the sweep calls purge_expired with the cold archive as its callback. Until then the growth is slow and bounded only by disk, which Sentinel's hourly disk telemetry watches; the measurement layer also records the table sizes. New in v0.3.5 (S53) | F21: Yes | G21: Acknowledged 2026-10-13
A22: R27 | B22: The pinned Chroma 1.5.9 soft-deletes: a deleted vector is only marked in the HNSW index, labels are never reused, the index's capacity grows to the next power of two of everything ever added and never shrinks, and Chroma has no TTL (feature request #2139, open since 2024) and no compaction, so each collection's index tracks inserts ever, not live notes (VERIFIED in the source at the tag and in its hnswlib fork); a query falls back to brute force once more than a fifth of a small index is deleted | C22: Medium over years (chat turns are inserted and expire continually; Sentinel BLUFs yearly) | D22: Low (disk and RAM under the container's 8 GiB cap; one owner's volumes, roughly 4 to 6 KiB per vector, INFERRED) | E22: The sweep's measurement layer (phased, S53) records live counts per collection and cumulative inserts, the proxy for the tombstone count Chroma does not expose; a collection rebuild (re-insert the live documents into a fresh collection, re-embedding them, outside a backup freeze) when the inserted-ever to live ratio warrants it, as a Principal-approved maintenance proposal: W-CHROMA-REBUILD, at these volumes a yearly question at most. New in v0.3.5 (S53) | F22: Yes | G22: Acknowledged 2026-10-13
A23: R28 | B23: A sweep that failed inside the Celery worker was silent: atlas-prune.service touches its cadence stamp after a successful enqueue (no --wait), so systemd records success, nothing retries before the next 71-hour slot, and only the ledger's task row and the journal held the error; a broken store, a locked index or a full /srv/cold could have gone unnoticed for weeks (VERIFIED at e6cadea) | C23: Medium (any sweep failure; a long AEGIS freeze only spools, which is not a failure) | D23: Low (expired notes linger; nothing is lost, since the archive is written and verified before any delete) | E23: Since S53 the task pushes one ntfy line ("ATLAS prune: sweep failed", priority high) whether it raised or finished with errors, after the ledger row and before re-raising; the push can neither mask the error nor block the sweep. The sweep is still not retried before the next slot: the alert is what makes it visible, and the weekly summary with its two-in-a-row rule is a phased item. New in v0.3.5 (S53) | F23: Yes | G23: Acknowledged 2026-10-13
A24: R29 | B24: The re-pin changes every engine's behaviour: b11474 is 510 commits after v0.4.1, and the Vulkan fixes between them include wrong KV rows without flash attention (llama.cpp #28956) and flash-attention fixes (#29591, #29988), so results can depend on the -fa setting (UNVERIFIED on this node). New in v0.4.0 (S-47); acknowledged by the Principal on 2026-10-17 | C24: Medium | D24: High (every engine) | E24: V25, required at the Phase 3 gate: the old and new builds compared on gpt-oss-120b, DeepSeek-V4-Flash-0731 and the router, flash attention on for the verdict and off recorded (3.4). GLM-5.3-Flash cannot be compared, since the old pin cannot load it, so V4, V22, the coherence prompt, T-03 and T-04 carry its checks. The pin changes only by a deliberate edit | F24: Yes | G24: New in v0.4.0 (S-47, 2026-10-16); acknowledged 2026-10-17
A25: R30 | B25: GLM-5.3-Flash's only fitting rung is lossy (UD-IQ4_XS: published mean KLD 0.117, the same top token 88.2% of the time; UNVERIFIED on this node), and it carries seven seats, vision and long documents. New in v0.4.0 (S-47); acknowledged by the Principal on 2026-10-17 | C25: Certain that the rung is lossy; Medium that it matters on the Principal's work | D25: Medium to high: hard reasoning magnifies quantisation loss (INFERRED from the 2026 review) | E25: Provisional on every seat until the KLD run (D-02 option (c), T-03); the Phase 3 quality record and the to-do kld-run; the reasoning and Apex seats on the bit-exact DeepSeek-V4-Flash-0731; strong cross-checks on the other family (9.2); the Principal's test sets (D-49) | F25: Yes | G25: New in v0.4.0 (S-47, 2026-10-16); acknowledged 2026-10-17
A26: R31 | B26: Swap and re-prefill latency: with one LLM seat resident, every change of seat is a swap of about 50 to 85 seconds through LUKS, plus re-prefill of the task's context (DeepSeek-V4-Flash-0731 about 1.5 to 4.5 minutes at 16k to 32k and up to 13 at 64k; INFERRED until T-14). New in v0.4.0 (S-47); acknowledged by the Principal on 2026-10-17 | C26: Certain on every swap | D26: Medium (usability; nothing is lost) | E26: GLM-5.3-Flash carries most seats and stays resident (6.3); Deep Think phases are batched (9.1); on Day 1 each strong cross-check swaps on its own (9.2); deep runs are reserved for the Principal's acceptance (D-43, built, 9.1); Phase 3 records each swap; the phased swap batching and slot restore (4.4, 6.3; T-13, T-14) | F26: Yes | G26: New in v0.4.0 (S-47, 2026-10-16); acknowledged 2026-10-17
A27: R32 | B27: Companions shrink the engine budget: every resident GiB comes off every seat. GLM-5.3-Flash at 8 × 32k projects to 155.05 GiB against about 156 GiB expected and is refused below a MemTotal of about 186.1 GiB, and the CPU pair's host memory and the servers' host-RAM prompt caches sit at the edge of the Arbiter's budget or outside it (INFERRED). New in v0.4.0 (S-47); acknowledged by the Principal on 2026-10-17 | C27: Medium | D27: High for the seat refused (never an out-of-memory crash: the Arbiter refuses first) | E27: The Qwen3 pair on the CPU, charged its weights in full plus its measured anonymous memory, never below its projection (D-14 option (e)); Phase 3's measured footprints replace the projections (to-do kv-estimates); the relief orders of 4.1; the to-do cache-ram; the prompt-cache caps and the other host-RAM bounds of S55 (4.1, 4.4); the OCR companion's test re-checks the budget before it is added (5.3) | F27: Yes | G27: New in v0.4.0 (S-47, 2026-10-16); acknowledged 2026-10-17
A28: R33 | B28: The phased DeepSeek V4.1 trial engine: ROCm on gfx1151 for an LLM (stability with the inbox driver only; llama.cpp #25992, ROCm #6186), a fast-moving source (1,984 commits in six months for the Lucebox engine), published speeds measured with greedy sampling only, and a router-bias switch that trades fidelity for speed. New in v0.4.0 (S-47); acknowledged by the Principal on 2026-10-17 | C28: Medium, after Day 1 only | D28: Low (evaluation only, outside the routed roster) | E28: Phased (15.5); the inbox amdgpu driver only, no DKMS, locked memory for that container alone, the image digest, source commit and file hashes pinned and never refreshed by themselves (D-52, D-57, B-36, B-37); speeds measured greedy and at the node's own temperatures, not 1.0 alone (D-47, S56); approximate switches only in scored trials (16.1 rule 9); promotion only by a blind-scored win (T-30) | F28: Yes | G28: New in v0.4.0 (S-47, 2026-10-16); acknowledged 2026-10-17; mitigation amended in S56 (D-47, approved by the Principal 2026-10-17)
A29: R10 | B29: Sustained thermal load in a small chassis | C29: Medium | D29: Low | E29: Monitor temperatures in Cockpit; the chip's configurable ceiling is 120 W and the Principal is adding external cooling | F29: Yes
A30: R11 | B30: CGNAT prevents inbound WireGuard | C30: Low, port forward already succeeded | D30: High for remote access | E30: V5 from mobile data, static IP from the ISP if needed | F30: Yes
A31: R12 | B31: Fictitious directors corresponding as humans, AI non-disclosure | C31: Medium | D31: Medium to high, legal | E31: Gideon's sensitive-tier check, approval gate, 16.5 | F31: Yes
A32: R13 | B32: Abliterated engine used for external output | C32: Medium | D32: Medium | E32: Abliterated output always passes the same gate, never routine tier | F32: Yes
A33: R14 | B33: Chatterbox continuation quirk in production speech | C33: Medium | D33: Low | E33: V7 testing, Kokoro fallback per line | F33: Yes
A34: R15 | B34: Prompt bloat from domain injection makes every dispatch slow | C34: High without limits | D34: High, usability | E34: Three-card limit, compact cards, stable-prefix ordering (8.4, 4.4) | F34: Yes
A35: R16 | B35: Backup passphrase or LUKS key lost with the node | C35: Low | D35: Catastrophic | E35: Sharpened under D3. The Principal keeps a copy on the node and on an external USB drive. The on-node copy is convenience only; the USB copy is the one that matters, and it must live away from the node, since a fire or burglary that takes the node takes anything beside it. Quarterly restore test | F35: Yes
A36: R17 | B36: PyAnnote gated model not accepted, diarisation silently absent. *Restated in v0.4.0 (S-48, C-06):* the gated pipeline is now speaker-diarization-community-1 (CC-BY-4.0, an automatically approved form). Once the phased Nemotron 3 Diarization (OpenMDW-1.1, not gated) is primary, community-1 is only its fallback for recordings with more than eight speakers, and the risk narrows to that case. The restatement was acknowledged by the Principal on 2026-10-17. | C36: Medium | D36: Low | E36: V6, recorded deferred with the to-do input-hf-token while the token or the licence is missing | F36: Yes | G36: Restated in v0.4.0 (S-48, C-06, 2026-10-16); acknowledged 2026-10-17
A37: R18 | B37: Continuous vision enabled by drift rather than decision | C37: Low | D37: High, privacy | E37: Separate capability flag under Alaric, logged, D8 item 7 | F37: Yes

Sheet 4 Verification
A1: 4 Verification
A2: Section 21 (V1 to V25; V25, the output parity of the llama.cpp re-pin, is new in v0.4.0, its pass marks confirmed by the Principal on 2026-10-17, and V21 now proves single residency). Filled in during Day 1 as each phase gate runs. Nothing is trusted until its row reads Pass.
A4: ID | B4: What Day 1 must prove | C4: Where | D4: Result | E4: Evidence or notes
A5: V1 | B5: Network link up and stable. Informational only, not a gate. *S56 (B-27):* on the cable it records the driver and the link speed (ethtool's Speed: line, else sysfs) and warns below 2,500 Mb/s; Wi-Fi is recorded as before | C5: Phase 1 pre-flight | D5: Not yet run
A6: V2 | B6: fTPM present and enabled, TPM2 enrolment succeeds | C6: Phase 1 step 2 | D6: Not yet run
A7: V3 | B7: Kernel parameters accepted on 7.0 and the GTT pool matches them (Phase 1; since S48 the same check also proves the crash settings: no crashkernel= on the booted command line and no crash-kernel memory reserved, exactly one panic=10, kernel.panic 10 and kernel.panic_on_oops 0; since S49 also exactly one kho=, the literal kho=off, and no CMA memory: no kexec handover scratch and no named CMA area); llama-cli --list-devices then lists the GPU as Vulkan0 with at least the larger of 160000 MiB (156.25 GiB) and the largest Day 1 seat with its context memory as the Arbiter projects it (v0.4.0, D-36 option (c), S-28: 155.05 GiB for GLM-5.3-Flash on Day 1, so 160000 MiB stands; the weights alone before the venv exists) of Vulkan device memory, and records the figure, which is not the engine budget (Phase 2); the measured heap decides every rung above about 149 GiB (T-01). rocminfo's gfx1151 confirmation sits in the Phase 4 container under V11 | C7: Phase 1 gate, then Phase 2 gate | D7: Not yet run
A8: V4 | B8: Quantised KV cache actually applied per model, no silent fallback (v0.4.0, S-48: the requested type, f16 included, on every proof line an engine prints; kv_proof_lines is four on DeepSeek-V4-Flash-0731 and two on GLM-5.3-Flash and gpt-oss-120b) | C8: Phase 3 step 2 | D8: Not yet run
A9: V5 | B9: WireGuard reachable from mobile data via vpn.sovereign-node.link | C9: Phase 1 step 7 | D9: Not yet run
A10: V6 | B10: The pyannote gated pipeline accepted and loading: speaker-diarization-community-1 since v0.4.0 (C-06; it was 3.1, which V6 now probes only as a diagnostic when community-1 is refused) | C10: Phase 2 step 5 | D10: Not yet run
A11: V7 | B11: Voice casting listening test, Alaric and Gideon clones sourced | C11: Phase 2 gate | D11: Not yet run
A12: V8 | B12: PointLLM builds and runs on ROCm in the container | C12: Phase 4 step 4 | D12: Not yet run
A13: V9 | B13: Clay or Prithvi builds and runs | C13: Phase 4 step 4 | D13: Not yet run
A14: V10 | B14: Every Day 1 LLM seat (gpt-oss-120b, its abliterated twin, GLM-5.3-Flash and DeepSeek-V4-Flash-0731) loads, generates, swaps and releases memory at its fixed quantisation. *v0.4.0 (S-24, S-25; D-33 option (c)):* decode is recorded beside each seat's projection and fails only below a per-seat floor the Principal sets. *S56 (D-33, D-47, approved by the Principal on 2026-10-17):* the floors are set at 8k, gpt-oss-120b 25, GLM-5.3-Flash 6 and DeepSeek-V4-Flash-0731 4 tok/s, judged on the slower of the 512 and 8k points with at least 64 generated tokens; the 8k prefill fails below 200, 40 and 40; the placement checks fail a partial offload or a GTT delta under 0.85 × the weights (a line not found is UNKNOWN); a review line at 70% of the projection raises the to-do decode-review and never fails; the Apex line carries T-06's 8k decode with DSpark off. The abliterated entry keeps its v0.3.5 band and rule; the GLM and Apex lines point to their V22 rows. Eleanor's resident 4B router model is verified separately at the Phase 2 gate (V10a), since it is pulled there; since S56 V10a also times 128 tokens at temperature 0 and fails below the router's 20 tok/s floor, read from engines.json; below its review line (70% of its projection's low end) Phase 2 raises the to-do decode-review-router, never a fail | C14: Phase 3 gate | D14: Not yet run
A15: V11 | B15: Inside the ROCm container: rocminfo reports gfx1151, and AMD's gfx1151 PyTorch wheels (pinned ROCm 10.0.0 / torch 2.13.0 / torchvision 0.28.0 / torchaudio 2.11.0.2) pass tensor, matmul and diffusion self-tests; since S51 torchaudio's installed version must also be exactly the pin, 2.11.0.2+rocm10.0.0 (whether it imports is recorded, not required: an import failure fails CosyVoice 2 and Stable Audio Open, not Phase 4) | C15: Phase 4 step 1 | D15: Not yet run
A16: V12 | B16: Open WebUI makes no outbound connection after hardening (verified with the firewall log) | C16: Phase 2 step 3 | D16: Not yet run
... A29: V25 | B29: Output parity between the pin b11474 and the old pin v0.4.1 (new in v0.4.0, S-02; the condition D-01 set on the pin): on the chat engines both builds load (gpt-oss-120b, DeepSeek-V4-Flash-0731, the router), base logits for 16 × 512 tokens of the domain profiles written by the old build and scored by the new with --kl-divergence, and a 24-task deterministic set run on both. The verdict is taken with flash attention on (off is recorded): a mean KLD of at most 0.01, the same top token at least 98% of the time and no fewer tasks correct (thresholds confirmed by the Principal on 2026-10-17, S55). A file the old build cannot load records deferred; GLM-5.3-Flash and the embedder and reranker are listed as not covered | C29: Phase 3 step 2b; Phase 3 gate (required) | D29: Not yet run

Sheet 5 Checklist
A1: 5 Checklist
A2: Section 22. The original rows were ticked in the workbook returned 2026-09-21; the rows added or reopened since were closed as each records: D15 decided and the Windows share deferred on 2026-10-05, C27 decided and R22 to R25 acknowledged by the Principal on 2026-10-08, the Secure Boot BIOS setting, the USB recovery drive and R26 to R28 ticked in the workbook returned 2026-10-13, and the action register, its licences, C28 to C30 and D16 to D27 ticked on 2026-10-16 (v0.4.0), R29 to R33 with the restated R4, R17, R19 and R20 acknowledged on 2026-10-17, and later that day the answers to the open inputs, the bandwidth and R9 and R20 as restated (S56). S57 records the Principal's statements the same day: the states answered (VIC, NSW and QLD, with the Commonwealth), the briefs collected once ATLAS is live, the standards list a new open row, and the MedGemma decision a task for the live ATLAS with the Principal present. Blank rows: the optional items the scripts ask for at a prompt (Yes when provided, N/A to leave them for the live ATLAS to-do list); the inputs still left to the Principal, each already built with its stated default and kept as a to-do (the seat profiles and reasoning settings; the HAI-DEF decision for MedGemma, taken with the live ATLAS; and after Day 1 the briefs for the seat test sets, from real examples, the standards list, the TF_OMEGA situations and the T-03 coding tasks); and the optional 60-second download test. One row is to do before Phase 1: row 32, the cable on the 10 GbE port not marked DASH, with the reservation and the forward moved to its MAC and Wi-Fi off the LAN subnet (S56; pre-flight warns, never stops, if it is not done). The Secure Boot row and the install rows are ticked. One request still stands on row 29, to confirm that the installer's encryption option (Encrypt the LVM group with LUKS) was taken; pre-flight checks the OS volume on Day 1, and an unencrypted one is a warning and the to-do os-volume-encryption, never a stop.
A4: # | B4: Group | C4: Item | D4: Done | E4: Notes
A5: 1 | B5: Principal's actions — what is genuinely left | C5: Answer D1 through D14. Done, all fourteen closed in Section 19. | D5: Yes
A6: 2 | B6: Principal's actions — what is genuinely left | C6: New in v0.4.0: return the action register (64 decisions D-01 to D-64, 12 named models, 18 persona rows, 12 companions, 60 structure rows, 80 baseline items and 33 tests). Returned by the Principal on 2026-10-16, every row approved, P-10 and P-17 marked "Approve with changes" (P-10 with a change and a question, answered in 5.3; P-17 is among the uncensored-seat items, unchanged by this revision; N-01 and N-03 with a question, answered in 4.1 and 4.2); recorded as D16 to D27 (Section 19). | D6: Yes
A7: 3 | B7: Principal's actions — what is genuinely left | C7: New in v0.4.0: accept the Qwen Community License 1.0 for Qwen3.8-Flash-Next (D-03), the NVIDIA Nemotron Open Model License for Nemotron 3 Super (D-04) and OpenMDW-1.1 for Nemotron 3 Diarization (D-05). Accepted by the Principal on 2026-10-16 in the returned action register; each applies when its phased engine is pulled. | D7: Yes
A8: 4 | B8: Principal's actions — what is genuinely left | C8: New in v0.4.0: accept the remaining licences with each engine as it is approved (D-34 option (b), D-35 option (a)): MIT for GLM-5.3-Flash, DeepSeek-V4-Flash-0731 and Ling-3.0-flash-Fin; Apache 2.0 for the Qwen3 embedder and reranker, Intern-S1 and Baichuan-M3 (Qwen3-Coder-Next and EmbeddingGemma 2 left the arsenal on 2026-10-17, D-19 (c), D-60 (b)); CC-BY-4.0 for pyannote community-1; and, with their phased companions, the OCR, speech, voice and image licences D-35 names. Accepted by the Principal on 2026-10-16 in the returned action register. The Hugging Face click-through for community-1 is part of the token box below. MedGemma 1.5 4B's HAI-DEF terms are not among these (C-12; the open box below). | D8: Yes
A9: 5 | B9: Principal's actions — what is genuinely left | C9: Decide where the LUKS recovery key and restic passphrase live (D3). Done: node plus external USB. | D9: Yes
A10: 6 | B10: Principal's actions — what is genuinely left | C10: Confirm the Sentinel feed list (D6), the director alias pattern (D14), and the Apple build path (D11, removed). | D10: Yes
A11: 7 | B11: Principal's actions — what is genuinely left | C11: Have the USB recovery drive present on Day 1 and write it at the Day 1 close-out: the LUKS recovery key (shown once in Phase 1 step 2), the restic passphrase (/etc/atlas/secrets/restic.pass, shown once in Phase 2 step 7) and the vault passphrase you chose (step 9b); then store it away from the node, not beside it (R16). Drive in hand, confirmed by the Principal on 2026-10-13; the writing itself stays a Day 1 close-out step. *Reworded in v0.3.2: the material does not exist before Day 1, so the drive cannot be "stored" yet.* | D11: Yes
A12: 8 | B12: Principal's actions — what is genuinely left | C12: New in v0.4.0 (B-25, approved by the Principal on 2026-10-16): initialise the real gocryptfs vault before Day 1 and choose its passphrase: from a console, run sudo env ATLAS_VAULT_INIT=1 ./atlas-day1.sh phase2 --force 09b, then write the passphrase and the master key (shown once) with the other secrets for the USB drive (above). A plain phase2 proves the mechanics on a throw-away vault and records V18 deferred (Section 11, 17). | D12: Yes
A13: 9 | B13: Principal's actions — what is genuinely left | C13: New in v0.3.3: enable Secure Boot in the BIOS before Phase 1 (D15, option (a)). The one BIOS change since the workbook; without it pre-flight warns and the to-do secure-boot stays open, nothing stops. Done, confirmed by the Principal on 2026-10-13; pre-flight verifies it on Day 1. | D13: Yes
A14: 10 | B14: Principal's actions — what is genuinely left | C14: Optional, asked at the prompt (v0.3.3): your SSH public key, pasted when Phase 1 step 1 asks (the step prints the PowerShell command that shows it); skipped, password SSH stays on until the key is added (to-do ssh-key).
A15: 11 | B15: Principal's actions — what is genuinely left | C15: Optional, asked at the prompt (v0.3.3): GOOGLE_ACCOUNTS (two addresses, each tagged corporate or estate), FAMILY_NAMES (for the router's hard rule) and BUILDFARM_ACCEPT_ANDROID_SDK_LICENCE (Google's Android SDK licence, needed by the build container) are asked once by the first run, with an example each; a skip records a to-do and the dependent step defers itself. WINDOWS_SHARE is not asked (Section 12.4: live to-do).
A16: 12 | B16: Principal's actions — what is genuinely left | C16: ~~/etc/atlas/secrets/smb.cred for the Windows share account~~ Deferred to the live ATLAS (v0.3.3) with the share itself; Phase 2 step 9 is skipped. No action before Day 1. | D16: Yes
A17: 13 | B17: Principal's actions — what is genuinely left | C17: Decide D15 (Secure Boot and the TPM binding). Done 2026-10-05: option (a). | D17: Yes
A18: 14 | B18: Principal's actions — what is genuinely left | C18: Create the Google Cloud OAuth client for Gmail, Calendar and Drive, and be reachable for roughly five minutes during the Phase 2 pause (V20). Client created. The consent click itself still happens during Phase 2; Google requires the account owner to click Allow. The client must be of the Desktop app type (its JSON has a top-level installed key; a web key is the wrong type and Phase 2 stops at minute 0 saying so). Drop the JSON into /srv/atlas/staging/inbox/google-oauth-client.json once Phase 1 has created that folder. | D18: Yes
A19: 15 | B19: Principal's actions — what is genuinely left | C19: Optional, asked at the prompt (v0.3.1, relaxed in v0.3.3): create a Hugging Face access token (read scope) and, with the same account, accept the licences of the gated models on huggingface.co: pyannote/speaker-diarization-community-1 (V6; since v0.4.0, C-06, the one pyannote repository V6 needs, so pyannote/speaker-diarization-3.1 and pyannote/segmentation-3.0 are no longer required), black-forest-labs/FLUX.1-dev and stabilityai/stable-audio-open-1.0 (Phase 4). Phase 2 asks for the token once at its start (hidden input) and stores it under /etc/atlas/secrets/; skipped, V6 and the gated Phase 4 engines are deferred with the to-do input-hf-token. The four Phase 3 repositories are public, so Day 1 needs no further gated licence (v0.4.0).
A20: 16 | B20: Principal's actions — what is genuinely left | C20: Answered by the Principal on 2026-10-17 (S56): the inputs v0.4.0's approved rows had left open, from the open-input research: the per-seat decode floors and the deep-tier floor (D-33, D-47: 25, 6, 4 and 20 tok/s at 8k, prefill floors 200, 40 and 40, 4 tok/s for the deep tier; Section 1, 9.1, V10); the context targets of Baichuan-M3 and Intern-S1 (D-16: Q5_K_S with a rotated q8_0 cache at 1 × 32,768, Baichuan-M3 on the i1 file, Intern-S1 text only; 4.1, 5.1); no dedicated coder seat (D-19 (c): GLM-5.3-Flash codes, provisional until T-03); EmbeddingGemma 2 dropped (D-60 (b), 15.5); MedGemma 1.5 4B only on conditions, Rad-DINO alone until they hold (C-12, 15.2); the designs of the seat test sets and the trial set (D-49, D-46; 6.2, 15.5); and the bandwidth (B-27: a 2,000 Mbps line, 400 Mbps planned for the single-stream pull, the cable on the 10 GbE port not marked DASH to a 2.5 GbE router port; 2, 15.4). decode-floors is no longer raised while every seat has a floor, and context-targets is answered. | D20: Yes
A21: 17 | B21: Principal's actions — what is genuinely left | C21: Open, not needed for Day 1 (v0.4.0): the inputs still left to the Principal, each built with its stated default and kept as a to-do: the DeepSeek-V4-Flash-0731 context target (default 131,072 tokens, 4.3), GLM-5.3-Flash's cache type and slot profile (T-04, D-48; default f16 at 8 × 32k without --kv-unified, 4.3) and the long-document trigger (D-38, S-30; default 24,000 tokens, 7.1) (to-do seat-profiles); each seat's fixed reasoning setting (D-30 (b); the provisional settings of 5.1, in the to-do kld-run).
A22: 18 | B22: Principal's actions — what is genuinely left | C22: Open, a task for the live ATLAS with the Principal present (S56, C-12; S57): accept or decline Google's HAI-DEF Terms of Use and Prohibited Use Policy for MedGemma 1.5 4B. Not needed for Day 1. After Day 1 ATLAS raises it and shows a plain summary of both, with their links (15.2); no script raises it on Day 1. The Principal decides. On a yes, the Principal accepts on the model's Hugging Face page with their own account, never ATLAS (16.3 item 2); ATLAS records the date and the terms version in the ledger, like pyannote's, then pulls MedGemma 1.5 4B and runs the node test against GLM-5.3-Flash's own vision. Accepting means no diagnosis, a licensed clinician making any real decision, no serving to anyone else, family members' images only with their consent, an indemnity to Google, and every copy deleted if Google terminates (California law). Declining, or leaving it, keeps Rad-DINO alone, with GLM-5.3-Flash's own vision reading scans (15.2).
A23: 19 | B23: Principal's actions — what is genuinely left | C23: Optional (S56, B-27): before Phase 3, time one 60-second download on any computer on the same line: curl -L -o /dev/null --max-time 60 -w '%{speed_download}\n' https://huggingface.co/unsloth/DeepSeek-V4-Flash-0731-GGUF/resolve/main/UD-Q8_K_XL/DeepSeek-V4-Flash-0731-UD-Q8_K_XL-00003-of-00005.gguf (on Windows curl.exe, with -o NUL). It prints bytes per second: × 8 ÷ 1,000,000 gives Mbit/s. Set DOWNLOAD_MBPS in /etc/atlas/atlas.env to about 0.8 × that. Skipped, 400 stands (15.4).
A24: 20 | B24: Principal's actions — what is genuinely left | C24: Open, after Day 1 (v0.4.0; the set design approved on 2026-10-17, S56; S57): for the test sets of Australian law, HR, aviation, logistics, AEC, SCADA, game design, growth marketing, customer success and physical security / OSINT: a brief of about 15 minutes per domain (the 3 to 5 kinds of task you would give that seat, and 2 or 3 redacted real examples where they exist, which stay on the node), collected once ATLAS is live, from real examples as the work progresses (the Principal, 2026-10-17); the standards list (the box below); then approval or edits of ATLAS's drafts, wave by wave, and blind grades for the escalations and the 10% calibration sample (D-49 option (a), T-27; to-do seat-test-sets). Your states of operation are answered: VIC, NSW and QLD, with the Commonwealth (S57, Section 1). Awaiting the Principal, not decided: spreading wave 1's 16 Australian-law tasks across the Commonwealth, VIC, NSW and QLD, and adding about 10 Australian tax and finance tasks (6.2). Until the sets are scored, GLM-5.3-Flash carries those seats unproven (6.2).
A25: 21 | B25: Principal's actions — what is genuinely left | C25: Open, for the live ATLAS (S57): the list of Australian Standards you hold or subscribe to, with each licence's terms checked: whether it allows storing and processing the text in a private system. ATLAS holds the text of only those; every other standard it cites by number, edition and what free sources say, never its clauses (8.4). Accepting or renewing a licence stays your own act (16.3 item 2). Until the list is given, no standard's text is held. It also serves the D-49 test sets (to-do seat-test-sets).
A26: 22 | B26: Principal's actions — what is genuinely left | C26: Open, after Day 1 (v0.4.0; the 40-task design and its promotion rule approved on 2026-10-17, S56): write 8 to 10 one-paragraph real situations that would warrant TF_OMEGA, from which ATLAS drafts the trial's apex tasks; approve the 40 drafted tasks and references, the planted flaws included; grade the split verdicts and 10 calibration tasks blind (D-46 option (b), T-30; to-do trial-task-set).
A27: 23 | B27: Principal's actions — what is genuinely left | C27: Open, after Day 1 (S56, D-19 (c)): supply 20 to 30 of your own coding tasks for T-03. They run on GLM-5.3-Flash and DeepSeek-V4-Flash-0731 at each seat's real settings, and the result decides which of the two codes (17). Until then GLM-5.3-Flash codes.
A28: 24 | B28: Principal's actions — what is genuinely left | C28: Optional, asked at the prompt (v0.3.1, relaxed in v0.3.3): have the Cloudflare zone id for sovereign-node.link to hand (Overview page of the zone). A Zone:DNS:Edit-only token cannot look the zone up by name; Phase 1 step 7 asks for the id once if the token cannot list zones. A missing CLOUDFLARE.txt or a skipped zone id defers dynamic DNS and V23 with a to-do.
A29: 25 | B29: Principal's actions — what is genuinely left | C29: Source reference recordings for Alaric's gravelly voice and, if the British male presets collide, Gideon's. Sourced. Drop them as alaric.* and gideon.* (WAV, MP3 or M4A; step 5 converts to 16 kHz mono WAV) into /srv/atlas/staging/inbox/voice-references/ once Phase 1 has created the folder; if absent, both fall back to the nearest Kokoro preset and V7 is recorded as deferred, not failed. | D29: Yes
A30: 26 | B30: Principal's actions — what is genuinely left | C30: Have a monitor and keyboard available for Phase 1 only, in case first boot needs a hand. Done. | D30: Yes
A31: 27 | B31: Automated on the Principal's instruction, no action needed | C31: Cloudflare token relocation and deletion of CLOUDFLARE.txt: Phase 2 step 6b (V23). | D31: Yes
A32: 28 | B32: Automated on the Principal's instruction, no action needed | C32: Director aliases generated from names rather than confirmed one by one (D14). | D32: Yes
A33: 29 | B33: Build-side preconditions | C33: Ubuntu Server 26.04.1 installed on the 4 TB drive with the installer's encrypted-LVM (LUKS) option (installer storage step: *Use an entire disk*, the 4 TB drive, tick *Encrypt the LVM group with LUKS*, choose a disk passphrase; Section 3.5 requires both volumes encrypted; v0.3.3: an unencrypted OS volume is a warning and the to-do os-volume-encryption, not a stop); 8 TB drive unpartitioned. No desktop needed at install time: Phase 1 step 5b installs XFCE, xrdp and Chrome. Done per the returned workbook; confirm the encryption option was taken. | D33: Yes
A34: 30 | B34: Build-side preconditions | C34: BIOS: UMA minimum, IOMMU on, fTPM on. Done. Secure Boot: enabled (D15, v0.3.3; see the Principal's actions above). | D34: Yes
A35: 31 | B35: Build-side preconditions | C35: LAN address reserved for the node on the router (DHCP reservation for the node's MAC, Wi-Fi or cable: Phase 1 uses whichever interface is up); UDP 51820 forward confirmed to that address. Done. The reservation is what keeps the forward pointing at the node; no further IP action is needed beyond that move, and the VPN test from mobile data (V5) can be done whenever convenient. *S56:* the reservation and the forward move to the cable port's MAC before Phase 1 (box below). | D35: Yes
A36: 32 | B36: Build-side preconditions | C36: New in S56 (B-27, the Principal's choice of 2026-10-17), before Phase 1: plug the cable into the node's 10 GbE port not marked DASH (the one away from DC IN) and into a 2.5 GbE router port; move the DHCP reservation and the UDP 51820 forward above to that port's MAC; take Wi-Fi off the LAN subnet. Pre-flight notes the port and the MAC and warns, never stops, if any of this is missing. A move after Phase 1 means setting LAN_IFACE and LAN_CIDR and re-running Phase 1 step 4 (--force 04).
A37: 33 | B37: Build-side preconditions | C37: Internet bandwidth known, so the Phase 3 download can be planned (v0.4.0: about 448 GB in Phase 3, about 10 hours at 100 Mbps, D-42 option (b); about 842 GB of phased engines later; about 1.9 TB in all, D-41 option (a); v0.3.5 planned ~690 GB). Done; recorded on 2026-10-17 (S56, B-27): a 2,000 Mbps line, with 400 Mbps planned for the single-stream pull as written: about 2.5 hours for Phase 3's 448 GB, about 4.2 hours for the 757 GB of phased engines and about 10 hours for about 1.8 TB in all (15.4). | D37: Yes
A38: 34 | B38: Accepted resolutions | C38: C1 through C20 accepted in the returned workbook. C19 was reopened and re-decided in the Principal's favour. | D38: Yes
A39: 35 | B39: Accepted resolutions | C39: C21 through C26, new in v0.2, accepted in the returned workbook: the Ubuntu and amd64v3 rejections, the quantisation rise, the closed reserve list, the vision consolidation, and the residency-versus-generation reading. | D39: Yes
A40: 36 | B40: Accepted resolutions | C40: R9, R16, R19, R20 and R21 acknowledged in the returned workbook: two changed wording in v0.2, three were new. | D40: Yes
A41: 37 | B41: Accepted resolutions | C41: C27, new in v0.3.4: Ubuntu Server 26.04.1 kept over Fedora 44 KDE Plasma. Decided by the Principal on 2026-10-08. | D41: Yes
A42: 38 | B42: Accepted resolutions | C42: R22 to R25 acknowledged by the Principal on 2026-10-08 (R22 and R23 new in v0.3.2, R24 and R25 new in v0.3.4). | D42: Yes
A43: 39 | B43: Accepted resolutions | C43: R26 to R28 acknowledged by the Principal on 2026-10-13 (all three new in v0.3.5, S53, 2026-10-12; sheet 3). | D43: Yes
A44: 40 | B44: Accepted resolutions | C44: C28 to C30, new in v0.4.0 (superseding C23, C25 and C26), and D16 to D27 (reopening D4, D10 and D12): approved by the Principal on 2026-10-16 in the returned action register (D-25 option (a)). | D44: Yes
A45: 41 | B45: Accepted resolutions | C45: R29 to R33 and the restated R4, R17, R19 and R20 acknowledged by the Principal on 2026-10-17 (R29 to R33 new in v0.4.0, S-47, 2026-10-16; the four restated in S-47 and S-48; S55; sheet 3). | D45: Yes
A46: 42 | B46: Accepted resolutions | C46: R9 and R20 restated in S56 with B-27 (R9 applicable with the cable; R20 lowered to Low), and R33's mitigation naming the node's own sampling settings (D-47): approved by the Principal on 2026-10-17 with those recommendations (sheet 3). | D46: Yes

Sheet Ref Engines
A1: Ref Engines
A2: Sections 5.1, 5.3, 6.1 and 6.2 (v0.4.0). The Day 1 engines and their quantisations, the engines phased after Day 1, the resident small models, the two hemispheres, and the final persona-to-engine map with each seat's Day 1 fallback.
A4: The Day 1 LLM engines (one LLM seat resident at a time; exactly one generates at a time)
A5: Engine | B5: Architecture | C5: Quantisation | D5: File | E5: Decode | F5: Role
A6: GLM-5.3-Flash (glm-5.3-flash, MIT) | B6: 320B MoE, 18B active (glm5-next, first in llama.cpp b11279, hence the re-pin, 3.4); natively multimodal through its glm5v projector | C6: UD-IQ4_XS, the one lossy rung of the set (published mean KLD 0.117 and 88.2% same top token, UNVERIFIED on this node); provisional on every seat until the Phase 3 KLD run (T-03, D-02) | D6: 157.95 GB: 156.82 GB in five shards plus the 1.13 GB mmproj-F16.gguf at the repository root (147.10 GiB) | E6: 12–14 tok/s projected (Section 2) | F6: The default resident seat (D-23). Ren, Gideon, Silas, Helena, Minerva, Victor, Alaric and Eleanor's persona work (P-10); the vision engine (D-20 (a)); the long-document route (D-38 (a)); the Deep Think generator (D-22)
A7: DeepSeek-V4-Flash-0731 (deepseek-v4-flash, MIT) | B7: 284B MoE, 13B active (deepseek4) | C7: UD-Q8_K_XL, raised from UD-Q4_K_XL: bit-exact to the released weights (D-11 (a), S-42) | D7: 161.87 GB in five files (150.75 GiB) | E7: About 7 tok/s projected on mainline Vulkan, a floor (Section 2) | F7: The Apex engine and Arthur's default seat (P-02). TF_OMEGA, the Deep Think adversary and synthesis (D-22), strong cross-checks (D-39 (a)). Runs alone
A8: gpt-oss-120b (gpt-oss-120b, Apache 2.0) | B8: 117B MoE, 5.1B active (gpt-oss) | C8: F16 trunk, experts in native MXFP4 (D-59 (b)) | D8: 65.37 GB, one file (60.88 GiB) | E8: 41–44 tok/s projected for this file (S56, D-33; INFERRED: about 5 GB read per token; v0.4.0 said 57–60, computed for the Q8_0-trunk file); 53.8–55.6 measured with that MXFP4 file on 128 GB Ryzen AI Max+ 395 machines | F8: The fast utility and the fallback floor (D-12 (a), D-40 (a)): drafting, Sentinel escalation (9.3), the Day 1 Deep Think third opinion (9.1) and the Day 1 fallback of every seat whose planned runner-up is phased (6.2). No longer the default resident engine
A9: gpt-oss-120b abliterated (Huihui) | B9: Same weights, refusals removed | C9: MXFP4, re-quantised (Section 23: the abliteration is applied to the BF16 upcast; the MXFP4 GGUF is a requant, same size and speed, the "no accuracy cost" argument below does not transfer) | D9: 63 GB | E9: Same | F9: Valerie default; Ren and Arthur on explicit override
A10: v0.4.0 (approved by the Principal on 2026-10-16): GLM-5.3-Flash UD-IQ4_XS is the default resident seat, the vision engine (its glm5v projector loads on the same unit) and the long-document route; DeepSeek-V4-Flash-0731 UD-Q8_K_XL is Arthur's seat and the Apex; gpt-oss-120b is the fast utility and the fallback floor. Qwen2.5-VL-72B, Meditron-70B, Qwen3.5-122B-A10B and the bge pair leave the roster, and Nemotron 3 Super becomes a phased pull. Sizes are decimal GB as Hugging Face lists them; the Arbiter budgets the exact bytes in GiB (D-31). Phase 3 pulls about 448 GB. Since 2026-10-17 (S56, D-33, D-47) gpt-oss-120b, GLM-5.3-Flash and DeepSeek-V4-Flash-0731 have decode floors at 8k (25, 6 and 4 tok/s; the abliterated twin keeps its v0.3.5 band) and gpt-oss-120b is projected at 41-44.
A12: Phased after Day 1: recorded in the phased list of engines.json, not pulled, rendered or routed on Day 1
A13: Planned engine | B13: Architecture | C13: Planned file | D13: Size | E13: Planned role | F13: Also waits on
A14: Qwen3.8-Flash-Next (qwen3.8-flash-next, Qwen Community 1.0, D-03) | B14: 125B MoE plus 51B of n-gram embeddings, 6B active (qwen4exp; b11330 or later) | C14: unsloth UD-Q6_K_XL, six files (D-28 (a)) | D14: 169.17 GB (157.55 GiB) | E14: The Deep Think third opinion (S-43; gpt-oss-120b on Day 1); runner-up for Ren and Victor (D-40); corporate challenger | F14: Its weights alone exceed the ~156 GiB budget (4.1), so D-28 option (c), UD-Q5_K_XL (158.29 GB, 147.42 GiB), applies unless the measured budget allows (a); T-08
A15: Nemotron 3 Super (nemotron-3-super, NVIDIA Nemotron Open Model License, D-04) | B15: 120.6B MoE, 12.7B active (nemotron_h_moe) | C15: unsloth Q8_0, four shards | D15: 128.47 GB (119.65 GiB) | E15: Long-context utility (a 1M-token window) and the long-document runner-up (D-13 (b), D-38); no longer Arthur's default | F15: T-12: an alive check after a prompt of 20K tokens or more (#20732, B-32)
A16: Intern-S1 (intern-s1, Apache 2.0) | B16: 235B MoE, 22B active (qwen3moe) | C16: bartowski Q5_K_S, five files, text only (no mmproj); a q8_0 K and V cache with the pin's rotation at 1 × 32,768 tokens (D-16, approved 2026-10-17, S56) | D16: 161.96 GB (150.84 GiB) | E16: Science seat for domains 15, 35 and 36 (D-17), reached as in 8.4; Minerva's runner-up (D-40) | F16: 155.96 GiB projected, with 28,672 or 40,960 tokens as the measured budget allows (4.1); the q8_0 quality gate at its pull (T-03), with Q4_K_M (142.65 GB, 132.86 GiB) and an f16 cache at 40,960 if it fails
A17: Ling-3.0-flash-Fin (ling-3.0-flash-fin, MIT) | B17: 124B MoE, 5.1B active (bailingmoe3) | C17: bartowski Q8_0, four files | D17: 135.63 GB (126.32 GiB) | E17: Silas's finance-tuned second engine and runner-up (D-18, D-40), on TF_GAMMA, TF_DELTA and TF_EPSILON (8.4) | F17: Nothing beyond the event above
A18: Baichuan-M3-235B (baichuan-m3-235b, Apache 2.0) | B18: 235B MoE, 22B active (qwen3moe) | C18: mradermacher's imatrix i1-Q5_K_S, one file (Baichuan-M3-235B.i1-Q5_K_S.gguf, the same size as the static Q5_K_S it replaces); a q8_0 K and V cache with the pin's rotation at 1 × 32,768 tokens (D-16, approved 2026-10-17, S56) | D18: 161.88 GB (150.76 GiB) | E18: Minerva's medical cross-check (D-15 (a), S-31), on TF_UPSILON; replaces Meditron-70B | F18: T-11 (no independent score; it loads the i1 file); 155.88 GiB projected, with 28,672 or 40,960 tokens as for Intern-S1 (4.1); the q8_0 quality gate, with the official Q4_K_M (143.78 GB, 133.91 GiB) and an f16 cache at 40,960 if it fails. Recorded, not built: when it takes over Minerva's checks, the cross-check's 400-token cap (atlas/approval.py:386) must rise to cover its reasoning (D-30), and the cited sources must travel with the draft
A19: Where a persona's approved runner-up is one of these, its Day 1 fallback is gpt-oss-120b. To-do for each: the post-Day-1 pull, with the same checksum and load tests; the event: the Phase 3 gate passed with the measured budget recorded. Since 2026-10-17 (S56, D-16) Intern-S1 and Baichuan-M3 (on the i1-Q5_K_S file) run Q5_K_S with a q8_0 cache, the pin's rotation and one 32,768-token slot (about 155.9 GiB projected); Qwen3-Coder-Next and EmbeddingGemma 2 left the list (D-19 (c), D-60 (b)).
A21: Resident small models (D16, reopening D4)
A22: Role | B22: Requirement | C22: Day 1 model (v0.4.0)
A23: Eleanor's router and classifier | B23: ~4B, instruction-following, fast, always resident, separate from the seat | C23: Qwen3.5-4B Q8_0 (router-qwen3.5-4b), 4.48 GB, on the iGPU: unchanged (C-01)
A24: Embeddings | B24: Multilingual-ready, strong retrieval | C24: Qwen3-Embedding-4B Q8_0 (embed-qwen3-4b), 4.28 GB, on the CPU, its vectors truncated to the 1024-dim schema (C-02, S-41, 10.1)
A25: Reranker | B25: Improves RAG precision | C25: Qwen3-Reranker-4B Q8_0 (rerank-qwen3-4b), a 4.28 GB conversion that carries the rank head, on the CPU (C-03)
A26: The router stays at 4B and does classification only (P-10); Eleanor's own persona work runs on GLM-5.3-Flash. The Qwen3 embedder and reranker run on the CPU (--device none), indexed before Day 1 with the 1024-dim schema kept by truncation (D-45 (a)), and the Arbiter charges them as a host resident set. The reranker has no caller on Day 1 (to-do).
A28: The two hemispheres
A29: Attribute | B29: Ren Ackerman — Vanguard, Prime Director | C29: Arthur Sterling — Architect, Estate Manager
A30: Hemisphere | B30: Offensive, creative, expansive, outward-facing | C30: Defensive, regimented, private, guardian of personal data
A31: Domain mandate | B31: Corporate, Enterprise, Infrastructure, AEC | C31: Estate, Private Health, Logistics, Family
A32: Default engine | B32: GLM-5.3-Flash (v0.4.0, P-01; was gpt-oss-120b) | C32: DeepSeek-V4-Flash-0731, the Apex engine's own unit (v0.4.0, P-02; was Nemotron 3 Super)
A33: Override engine | B33: gpt-oss-120b abliterated, on Principal's order | C33: GLM-5.3-Flash for deep document reasoning, the long-document route (v0.4.0, D-38 (a); was Qwen3.5-122B-A10B); and the abliterated engine on the Principal's explicit command (C6 addendum)
A34: Apex escalation | B34: DeepSeek-V4-Flash-0731, on Deep Think deep tier or TF_OMEGA | C34: The same engine as his default since v0.4.0, so TF_OMEGA and the deep tier's synthesis cost Arthur no swap
A35: Fallback engine (v0.4.0, D-40 (a)) | B35: gpt-oss-120b on Day 1 (his runner-up, Qwen3.8-Flash-Next, is phased) | C35: GLM-5.3-Flash
A36: Sampling | B36: High temperature (0.8) as Deep Think Generator | C36: Low temperature, not zero, as Deep Think Adversary
A37: Deep Think role | B37: Generator: three divergent trajectories, on GLM-5.3-Flash | C37: Adversary: rubric-scored verdict, weak concepts killed, on DeepSeek-V4-Flash-0731
A38: Code path | B38: Writes sandbox code | C38: Audits code for memory and safety before execution, as a second layer over the OS-level sandbox cap
A39: Directors | B39: Gideon, Silas, Valerie, Helena, Eleanor | C39: Alaric, Minerva, Victor
A41: Shadow Cabinet engine map (each seat's Day 1 fallback in the Override column)
A42: Director | B42: Division | C42: Remit | D42: Default engine | E42: Override | F42: Speaks externally
A43: Gideon Vance | B43: Corporate | C43: Legal & Compliance | D43: GLM-5.3-Flash, high reasoning, retrieval-grounded (P-03; was gpt-oss-120b) | E43: Apex engine (DeepSeek-V4-Flash-0731) for TF_OMEGA; long contracts stay on GLM, the long-document engine (Qwen3.5-122B retired). Fallback: DeepSeek-V4-Flash-0731 | F43: Yes, sensitive tier
A44: Silas Thorne | B44: Corporate | C44: CFO: capital, audit, banking | D44: GLM-5.3-Flash + code interpreter for all arithmetic (P-04; was Nemotron 3 Super) | E44: none on Day 1; Ling-3.0-flash-Fin planned (D-18, phased). Fallback: gpt-oss-120b | F44: Yes, standard tier
A45: Valerie Cross | B45: Corporate | C45: Infrastructure, DevOps, AEC, cyber, AEGIS Sandbox | D45: gpt-oss-120b abliterated | E45: none on Day 1: Qwen2.5-VL-72B is retired (S-10); Intern-S1 planned (S-32, phased); Qwen3-Coder-Next dropped (D-19 (c), 2026-10-17) | F45: Yes, standard tier
A46: Helena Frost | B46: Corporate | C46: Communications, brand, PR, crisis | D46: GLM-5.3-Flash (P-06; was gpt-oss-120b) | E46: none. Fallback: DeepSeek-V4-Flash-0731 | F46: Yes, standard tier
A47: Eleanor Croft | B47: Corporate | C47: Routing, scheduling, triage; the 4-Way Router's classifier | D47: GLM-5.3-Flash for her persona work (P-10; was the resident 4B model); classification stays on the resident 4B router (5.3) | E47: none. Fallback: gpt-oss-120b | F47: Yes, routine tier (scheduling)
A48: Alaric Stone | B48: Estate | C48: Physical assets, security, threat mitigation; Sentinel threat watch | D48: GLM-5.3-Flash (was Nemotron 3 Super) | E48: none. Fallback: gpt-oss-120b | F48: Yes, sensitive tier
A49: Minerva Hale | B49: Estate | C49: Private health, longevity; medical data | D49: GLM-5.3-Flash, retrieval-grounded (P-07; was gpt-oss-120b), which also reads her scans and long records | E49: Strong cross-check by Arthur on DeepSeek-V4-Flash-0731 on Day 1 (9.2); Baichuan-M3-235B cross-check and Intern-S1 planned (D-15, D-17, phased). Fallback: gpt-oss-120b | F49: Yes, sensitive tier
A50: Victor Vale | B50: Estate | C50: Aviation, transport, concierge | D50: GLM-5.3-Flash (P-08; was gpt-oss-120b) | E50: none. Fallback: gpt-oss-120b | F50: Yes, routine tier

Sheet Ref Domains
A1: Ref Domains
A2: Section 8.2. Thirty original domains retained and six added, thirty-six in all. Tier A loads freely, B on clear match, C on explicit match only. S57 (2026-10-17): a compliance list's Australian law is that of the Commonwealth, VIC, NSW and QLD, the Principal's main locations; Australian Standards are cited by number unless the Principal holds a licence for the text (8.4).
A4: Thirty-six domain knowledge profiles
A5: # | B5: Domain | C5: Hemisphere | D5: Owner | E5: Tier
A6: 1 | B6: Systems Architect & Cybersecurity | C6: Corporate | D6: Valerie | E6: A
A7: 2 | B7: Growth Executive (marketing, sales, PR, SEO) | C7: Corporate | D7: Helena | E7: A
A8: 3 | B8: Customer Success & Experience Lead | C8: Corporate | D8: Helena | E8: B
A9: 4 | B9: Data Scientist & AI Engineer (incl. rapid data analysis) | C9: Corporate | D9: Valerie | E9: A
A10: 5 | B10: CFO & Controller (incl. financial fraud and risk modelling) | C10: Corporate | D10: Silas | E10: A
A11: 6 | B11: General Counsel & CHRO (AU construction, strata) | C11: Corporate | D11: Gideon | E11: A
A12: 7 | B12: Development Director, Property & Real Estate | C12: Corporate | D12: Valerie, with Silas | E12: A
A13: 8 | B13: AEC Computational Designer & Visualizer | C13: Corporate | D13: Valerie | E13: A
A14: 9 | B14: Industrial & Energy Engineer (incl. industrial SCADA systems) | C14: Corporate | D14: Valerie | E14: B
A15: 10 | B15: Chief Medical Officer & Risk Underwriter | C15: Estate | D15: Minerva | E15: A
A16: 11 | B16: Game Director & Systems Designer | C16: Corporate | D16: Helena, with Valerie | E16: C
... A41: 36 | B41: Synthetic Biology & Genomic Engineering | C41: Estate | D41: Minerva | E41: C

Sheet Ref Task Forces
A1: Ref Task Forces
A2: Section 8.3. All twenty-three retained. Group is a tag, not a merge.
A4: Twenty-three task forces
A5: Code | B5: Task force | C5: Group | D5: Owner | E5: Default approval tier
A6: TF_ALPHA | B6: Corporate Mergers & Acquisitions | C6: CORP-DEALS | D6: Gideon | E6: Sensitive
A7: TF_BETA | B7: Geopolitical Tariff & Tax / Regulatory Arbitrage | C7: CORP-LEGAL | D7: Gideon, with Silas | E7: Sensitive
A8: TF_GAMMA | B8: Capital Deployment & Wealth Allocation | C8: CORP-CAPITAL | D8: Silas | E8: Sensitive
A9: TF_DELTA | B9: Banking & Institutional Leverage | C9: CORP-CAPITAL | D9: Silas | E9: Sensitive
A10: TF_EPSILON | B10: Venture & Seed Investments | C10: CORP-CAPITAL | D10: Silas, with Gideon | E10: Sensitive
A11: TF_ZETA | B11: Corporate Structuring & Holding Entities | C11: CORP-DEALS | D11: Gideon | E11: Sensitive
A12: TF_ETA | B12: Global Liability & Litigation Defense | C12: CORP-LEGAL | D12: Gideon | E12: Sensitive
A13: TF_THETA | B13: Regulatory Compliance & Audit | C13: CORP-LEGAL | D13: Gideon, with Silas | E13: Standard
A14: TF_IOTA | B14: Intellectual Property & Licensing | C14: CORP-CONTRACTS | D14: Gideon | E14: Standard
A15: TF_KAPPA | B15: Contract & Vendor Negotiation | C15: CORP-CONTRACTS | D15: Gideon, with Ren | E15: Standard
A16: TF_LAMBDA | B16: AEC Oversight | C16: CORP-AEC | D16: Valerie | E16: Standard
... A28: TF_OMEGA | B28: Absolute Apex Contingency | C28: APEX | D28: Principal-triggered, Ren and Arthur jointly | E28: Sensitive, dual sign-off
A29: v0.4.0 (S-29, D-37): owners and tiers unchanged. A preset reaches a seat only through its owner's binding or its engine field, never a domain card; on Day 1 only TF_OMEGA carries one (deepseek-v4-flash, the Apex), and every other preset runs on its owner's default engine (GLM-5.3-Flash for every director but Valerie, whose engine is unchanged). The phased engines a preset will carry are named in task-forces.json notes: Ling-3.0-flash-Fin on TF_GAMMA, TF_DELTA and TF_EPSILON, Baichuan-M3 and Intern-S1 on TF_UPSILON; TF_MU has none, since D-19 (c) dropped Qwen3-Coder-Next on 2026-10-17. No new prefix.

Sheet Ref Integrations
A1: Ref Integrations
A2: Section 13. APIs preferred over the browser wherever they exist.
A4: External services
A5: Service | B5: Path | C5: Capability | D5: Approval
A6: Google Workspace and personal Gmail | B6: Gmail and Calendar APIs, one-time OAuth per account via a Principal-owned Google Cloud project | C6: Read, send, label, calendar both ways. Each account tagged corporate or estate for the router | D6: Per message tier (Section 16.2)
A7: Google Drive | B7: Mounted as a folder on the node (rclone), both accounts | C7: Read and write, appears as local storage to every persona | D7: Writes to shared folders: standard tier
A8: Xero | B8: Official API plus Xero's own MCP tool server | C8: Ledgers, invoices, contacts, bank feeds, reports as structured data for Silas | D8: Any posting or payment: sensitive tier
A9: Cloudflare | B9: Full API, scoped token | C9: DNS, domains, security settings | D9: All changes: standard tier, DNS for sovereign-node.link itself: sensitive
A10: Wix | B10: Partial API for content and business data, browser for site design | C10: Helena updates content by API, design changes through the browser | D10: Standard tier
A11: Pay.com | B11: Developer API for payment data | C11: Reading and reporting | D11: Any payment action: sensitive tier, two-factor stays on the Principal's phone
A12: RewardPay | B12: Browser only, no public API found | C12: Agent-driven browser with the Principal approving each action | D12: Sensitive tier, two-factor stays on the Principal's phone
A13: Anything without an API | B13: Local browser automation, Playwright text-based DOM reading, UI-TARS-1.5-7B for vision-driven GUI work (15.2; corrected in v0.4.0, B-11: UI-TARS 2.0 has no open weights and stays on the watch-list, 15.5) | C13: Works with every engine in the set | D13: Per action tier

Sheet Ref Voice
A1: Ref Voice
A2: Sections 14.1 and 14.3. Casting is a shortlist for a listening test (V7), not a locked choice.
A4: Speech engines
A5: Function | B5: Engine | C5: Status
A6: Text-to-speech, always-on default for all ten personas | B6: Kokoro-82M | C6: Local, cheap, measured naturalness ~4.2 to 4.5 against a human 4.5 to 4.8
A7: Text-to-speech, character and cloning tier | B7: Chatterbox | C7: Local, MIT licensed, won blind preference against ElevenLabs 65% to 25%; carries a documented continuation quirk, test before it carries anything important. *v0.4.0 (C-09, S-15):* 0.1.7 stays on Day 1. Chatterbox Turbo (350M, English) and Multilingual V3 (0.5B, 23 languages), both MIT, are phased. To-do: T-23, a test on the ROCm 10.0 image (load, real-time factor, the continuation quirk); the event: the Phase 4 gate passed
A8: Not adopted | B8: Fish Audio S2 (Pro tier is research-licensed), Qwen-Audio-3.0-TTS (hosted only); *v0.4.0 (S-52):* Higgs v3 and Fish S2-Pro (non-commercial) | C8: Excluded
A9: Text-to-speech, test (v0.4.0, S-57; was the watch-list) | B9: Qwen3-TTS-12Hz-1.7B-Base (open, local; ggml-org Q8_0, 1.85 GB plus a 0.45 GB mmproj) | C9: Phased test after Day 1 (C-10, T-22): through the llama-tts tool on the pinned Vulkan build, because llama-server has no speech endpoint until llama.cpp PR #26603 merges (15.5); then in the V7 listening set beside Kokoro and Chatterbox (T-24). Not a Day 1 dependency
A10: Speech-to-text | B10: Whisper Large-v3-Turbo via whisper.cpp or faster-whisper | C10: Local. *v0.4.0 (C-05, S-14):* kept on Day 1 and as the fallback. Qwen3-ASR-1.7B (ggml-org Q8_0, 2.17 GB plus a 0.36 GB mmproj, on llama-server's /v1/audio/transcriptions at the pin) and Phi-4-multimodal are candidates for a word-error-rate test on the Principal's audio (T-20), phased; Open WebUI's speech endpoint changes only if the test favours one
A11: Speaker diarisation | B11: pyannote speaker-diarization-community-1 (v0.4.0, C-06; was PyAnnote 3.1) | C11: Local, on the CPU, on the same pyannote.audio 4.0.7 install. VERIFY V6: the model is gated on Hugging Face (CC-BY-4.0, an automatically approved form, one self-contained repository); the licence must be accepted once with a token during Phase 2. V6 probes 3.1 only as a diagnostic when community-1 is refused
A12: Speaker diarisation, primary after Day 1 (v0.4.0, phased) | B12: Nemotron 3 Diarization (official Q8_0, 0.11 GB, OpenMDW-1.1 accepted under D-05) through NeMo-Speech.cpp on the node's ggml and Vulkan stack | C12: Phased (C-06, S-04); community-1 then becomes its fallback for recordings with more than eight speakers. To-do: a pinned NeMo-Speech.cpp build step and V6 rewritten for it. The event: T-21, its speed and diarisation error on gfx1151 against community-1 and 3.1 on the Principal's recordings, after Day 1
A13: Not adopted, diarisation and speech-to-text (v0.4.0, S-52) | B13: DiariZen (CC BY-NC, non-commercial); Sortformer (a four-speaker cap); pyannoteAI precision-2 and -3 (hosted, so they fail zero-cloud); Parakeet TDT and Canary-Qwen (NeMo, CUDA only) | C13: Excluded
A14: Music and sound | B14: Stable Audio Open | C14: Phase 4
A15: Voice cloning alternative | B15: CosyVoice2 | C15: Phase 4, optional
A16: v0.4.0 (approved by the Principal on 2026-10-16): the one Day 1 change is the diariser, pyannote speaker-diarization-community-1 in place of 3.1 (C-06; V6 probes 3.1 only as a diagnostic). Nemotron 3 Diarization, Chatterbox Turbo and Multilingual V3, Qwen3-TTS and the Qwen3-ASR word-error-rate test are phased after Day 1, each on its node test with the Principal's own audio (T-20 to T-24).
A18: Voice casting shortlist
A19: Persona | B19: Description | C19: Kokoro candidates | D19: Path
A20: Arthur | B20: Male. Formal, patient, structured, deep resonance, calming British or Transatlantic cadence | C20: bm_george, alternate bm_daniel | D20: Kokoro preset
A21: Ren | B21: Male. Sharp, direct, fast, aggressive modern executive cadence with expressive pauses | C21: am_onyx, alternate am_michael | D21: Kokoro preset, Chatterbox for intensity if needed
A22: Alaric Stone | B22: Male. Grounded, authoritative, gravelly veteran security director | C22: No preset delivers gravel | D22: Chatterbox clone from a reference recording
A23: Minerva Hale | B23: Female. Calm, analytical, articulate, clinical | C23: af_kore, alternate bf_isabella | D23: Kokoro preset
A24: Victor Vale | B24: Male. Crisp, rapid, flawlessly polite, aviation concierge | C24: bm_lewis, alternate bm_daniel | D24: Kokoro preset
A25: Gideon Vance | B25: Measured, meticulous, deep, litigator in absolute facts | C25: bm_george if Arthur takes bm_daniel, else am_onyx reassigned | D25: Kokoro preset or Chatterbox clone to separate from Arthur
A26: Silas Thorne | B26: Male. Sharp, cold, calculated quant | C26: am_eric, alternate am_echo | D26: Kokoro preset
A27: Valerie Cross | B27: Female. Direct, brilliant, slightly impatient engineer | C27: af_nova, alternate af_river | D27: Kokoro preset
A28: Helena Frost | B28: Female. Charismatic, persuasive, perfectly modulated PR executive | C28: af_bella, alternate bf_emma | D28: Kokoro preset, Chatterbox for modulation if needed
A29: Eleanor Croft | B29: Female. Warm, efficient, observant | C29: af_sarah, alternate af_heart | D29: Kokoro preset
A30: Known conflict: Arthur, Victor, and Gideon all pull toward the same four British male presets. Once heard, expect to spread them apart or move one to a Chatterbox clone, as Alaric is.

Sheet Ref Multimodal
A1: Ref Multimodal
A2: Section 15. Tools install in Phase 2 (CPU, always available). Engines build in Phase 4 inside ROCm containers; since v0.4.0 a Phase 4 engine never runs beside an LLM seat (D-50 (a)). The watch-list (15.5) is considered, not adopted.
A4: Phase 2 tools
A5: Tool | B5: Job | C5: Owner
A6: IfcOpenShell and Bonsai (Blender BIM) | B6: IFC parsing, authoring, geometric clash detection | C6: Domain 8, Valerie
A7: MCP4IFC | B7: MCP server for LLM-driven parametric IFC creation and editing, this is the "Arch-DiT / BIM-GPT" capability | C7: Domain 8, Valerie
A8: Radiance | B8: Physically accurate lighting and daylighting simulation for real coordinates and time, the photometric half of "Lumina-PBR" | C8: Domain 8, Valerie
A9: OpenStudio and EnergyPlus | B9: HVAC and building-energy simulation, the fluid-dynamics half of "DeepRoute-AEC" | C9: Domain 8 and 9, Valerie
A10: Python via code interpreter | B10: Voltage drop and other formula engineering, all of Silas's arithmetic | C10: All directors
A11: KiCad CLI | B11: PCB design, DRC, export, driven through its Python API by the coding engine | C11: Domain 29, Valerie
A12: Docling | B12: Document conversion for PDFs, Office files, scans into structured chunks with tables and page provenance | C12: Ingestion for every domain
A13: Cross-platform build service | B13: Android NDK plus Gradle for .apk, MinGW-w64 for .exe, containerised. This is the "OmniBuild-KVM" capability, Android and Windows only | C13: Domain 1 and 5, Valerie
A14: Playwright and browser automation | B14: Text-based DOM browsing for platforms without an API | C14: All directors, per tier
A16: Phase 4 engines and their tiers
A17: Engine | B17: Job | C17: Tier and evidence | D17: Footprint | E17: Owner
A18: Wan2.2 (in place of Wan2.1) | B18: Video generation | C18: Green: validated on gfx1151 by maintained toolboxes | D18: 20 to 40 GB | E18: Domain 12, Helena
A19: FLUX.1-dev | B19: Image generation, architectural visualisation with LoRA (the "Arch-DiT" imagery use). The dev variant, chosen for quality over the Apache-licensed schnell variant; the Principal accepts the dev non-commercial licence (15.5) | C19: Green: validated on gfx1151 | D19: 12 to 24 GB | E19: Domains 8 and 12
A20: Z-Image-Turbo; Qwen-Image-2512 for evaluation (v0.4.0, phased; C-11, S-16) | B20: Image generation: a permissive fast tier beside FLUX.1-dev (6B, Apache 2.0), and a larger Apache 2.0 engine to evaluate | C20: Phased after Day 1 (D-26 option (c)): not in phase4-engines.json on Day 1. To-do: their Phase 4 entries and build scripts, with stable-diffusion.cpp on Vulkan as the fallback runtime. The event: T-25 times them on gfx1151 in the ROCm 10.0 image after the Phase 4 gate | D20: about 12 GB (BF16); about 40 GB | E20: Domains 8 and 12
A21: Qwen2.5-VL-72B at Q8_0 (retired in v0.4.0) | B21: Was the sole vision engine: documents, drawings, screenshots, scans | C21: Retired (S-10, S-11; D-20 option (a), D-21 option (a)): the vision engine is GLM-5.3-Flash with its glm5v projector, a Phase 3 GGUF engine on the default seat's own unit (5.1, 14.4), so nothing is built or pulled for it | D21: was 79 GB | E21: General. Valerie for drawings, Minerva for scans, Gideon for scanned contracts, now on GLM-5.3-Flash
A22: Florence-2 | B22: Lightweight vision, detection, captioning, OCR | C22: Green; the native florence-community checkpoints, no remote code (Section 23). *v0.4.0 (S-08):* when the phased OCR companion lands (C-04, T-19), whether Florence-2 keeps detection and captioning only is decided with it | D22: under 2 GB | E22: General
A23: Chronos (Chronos-Bolt / Chronos-2) | B23: Time-series forecasting. TimesFM dropped in v0.3.1: its current 3.0 release is non-commercial (Section 23) | C23: Green, Apache-2.0 | D23: under 5 GB | E23: Domain 21, Silas
A24: Stable Audio Open | B24: Music and sound generation | C24: Green | D24: under 5 GB | E24: Domain 12, Helena
A25: CosyVoice2 | B25: Voice cloning alternative | C25: Green | D25: under 5 GB | E25: Voice layer, optional
A26: UI-TARS-1.5-7B | B26: Vision-driven GUI automation for RewardPay and Wix design. UI-TARS 2.0 has no open weights (Section 23, watch-list 15.5) | C26: Green | D26: 8 to 16 GB | E26: Domain 1, Valerie
A27: OpenVLA | B27: Vision-language-action for robotics | C27: Green technically, dormant until hardware exists | D27: 8 to 16 GB | E27: Domain 29, Valerie
A28: Rad-DINO | B28: Radiology vision | C28: Green. *S56 (C-12, approved by the Principal on 2026-10-17):* Rad-DINO alone. MedGemma 1.5 4B joins it as an on-demand imaging tool, a companion and not an LLM seat, never resident, only once three things hold: the Principal accepts Google's HAI-DEF terms (an open box, Section 22); a new non-seat Arbiter class is built and tested, so that a read evicts the resident seat only for memory, never by seat exclusivity; and a node test shows its reads beat GLM-5.3-Flash's own vision on the same public cases. Then: BF16 weights (7.77 GB) with the BF16 mmproj (0.85 GB) from unsloth/medgemma-1.5-4b-it-GGUF, Q8_0 (4.13 GB) as the fallback, 1 × 32,768, about 10.8 GiB projected (INFERRED); each read a preliminary draft that Minerva's seat reasons over, never sent to the Principal unreviewed; reads batched so GLM is evicted at most once per batch. The terms, in brief (VERIFIED, fetched 2026-10-17): they bind every copy, the ungated unsloth GGUF included; no diagnosis and no automated healthcare decision (a licensed clinician decides); no serving to anyone else; other people's images, family members' included, only with their consent; the Principal indemnifies Google; Google may terminate, and every copy is then deleted; California law. *S57 (the Principal, 2026-10-17):* the licence decision is a task for the live ATLAS, with the Principal present to approve. After Day 1 ATLAS raises it and shows a plain summary of the HAI-DEF Terms of Use and Prohibited Use Policy, with their links (https://developers.google.com/health-ai-developer-foundations/terms and https://developers.google.com/health-ai-developer-foundations/prohibited-use-policy). The Principal decides. On a yes, the Principal accepts on the model's Hugging Face page (google/medgemma-1.5-4b-it, gated; VERIFIED 2026-10-17) with their own account; ATLAS never accepts for them (16.3 item 2). ATLAS then records the date and the terms version in the ledger (on 2026-10-17 the two pages read "Last modified" 15 and 14 November 2024, VERIFIED), pulls MedGemma 1.5 4B and runs the node test against GLM-5.3-Flash's own vision; the Arbiter-class condition above still applies. On a no, Rad-DINO alone. Rad-DINO stays research-use only per its card | D28: under 2 GB | E28: Domains 10 and 15, Minerva
... A36: NVIDIA Modulus / PhysicsNeMo | B36: Physics simulation | C36: Deferred: CUDA-locked, would need an NVIDIA card in a USB4 external GPU dock, since this machine has no PCIe slot | D36: n/a | E36: Domains 8 and 9
A37: v0.4.0: Qwen2.5-VL-72B and Meditron-70B are retired, their rows kept as the record: the vision engine is GLM-5.3-Flash with its glm5v projector, a Phase 3 GGUF engine, and Minerva's cross-check moves to the phased Baichuan-M3. The image tier (Z-Image-Turbo, Qwen-Image-2512) is phased after Day 1 (T-25). Rad-DINO stands alone until MedGemma 1.5 4B's conditions hold: the Principal's acceptance of the HAI-DEF terms, a non-seat Arbiter class and a node test against GLM-5.3-Flash's own vision (C-12, S56). Since S57 the decision is a task for the live ATLAS with the Principal present: on a yes the Principal accepts on the model's Hugging Face page with their own account, and ATLAS never accepts for them.
A39: Engine watch-list: considered, not adopted (15.5; v0.4.0 adds the 2026 review's items, the phased DeepSeek V4.1 trial among them; S56 makes EmbeddingGemma 2's row the active one and adds Qwen3-Coder-Next and Qwen3-VL-Embedding-8B)
A40: Engine | B40: What it does | C40: Why not now | D40: What would change the answer | E40: Would replace
A41: Qwen3.8-LiveTranslate (19 Sep 2026) | B41: Real-time simultaneous interpretation: 60 languages understood, 29 spoken, about 2.3 s lag | C41: Hosted API only (Alibaba Cloud Model Studio, QwenCloud, WebSocket). No open weights. Fails the zero-cloud rule (Section 1) on inference off-node and audio leaving the machine | D41: An open-weights release. Qwen has released weights for Qwen3-Omni, so this is plausible | E41: Nothing. Live interpretation is an open gap; the Whisper to engine to Kokoro pipeline (14.1) does consecutive translation only, and only in Kokoro's eight languages
A42: UI-TARS 2.0 | B42: Vision-driven GUI agent, successor to the 1.5-7B build in 15.2 | C42: Technical report only; no open weights as of September 2026 | D42: An open-weights release | E42: UI-TARS-1.5-7B
A43: Qwen-Image-2.1 (20 Sep 2026) | B43: Image generation and editing in one 7B checkpoint: native RGBA, 2K, up to ten reference images, strongest text-in-image of its class; about 14 GB BF16, GGUF available, plain BF16 path on gfx1151 | C43: Qwen Research License, non-commercial only. Same restriction that excluded Fish Audio S2 (C20). Not a peer of the vision engine (Qwen2.5-VL-72B until v0.4.0, GLM-5.3-Flash since), which reads images; this one makes them | D43: Re-licensing to Apache-2.0 (Qwen did this for Qwen2.5 within months) or a commercial licence obtained by the Principal | E43: FLUX.1-dev outright: half the footprint, generate and edit in one model
A44: DeepSeek V4.1 Flash trial (v0.4.0, phased; S-51) | B44: A 552B successor to the Apex's 0731 checkpoint, run for evaluation only, outside the routed roster: DwarfStar with antirez's Q2 file (365.71 GB, 151.76 GiB resident, KL about 0.26; 14 to 16.5 tok/s measured by others on a Strix Halo machine, UNVERIFIED here) in kyuz0's ROCm 10.0 container | C44: Every fitting V4.1 file is 2 to 3 bits; mainline llama.cpp cannot run it (next row); it needs a ROCm LLM container the node has never run. Approved as a phased trial (D-46 option (b), D-51 option (a), D-52 option (b), D-54 option (a), D-57 option (b)): pinned by image digest, source commit and file hashes, the inbox amdgpu driver only, locked memory for that container alone, registered with the Arbiter as an exclusive external engine, built after Day 1 and never by atlas-day1.sh, one trial file at a time | D44: *S56 (D-46, D-47, approved by the Principal on 2026-10-17):* a private 40-task set, scored pairwise and blind: A 16 TF_OMEGA apex syntheses, B 10 Deep Think adversary tasks with planted flaws, C 6 deep-tier final syntheses, D 4 long dossiers of about 32K tokens, E 4 exact computations. GLM-5.3-Flash and gpt-oss-120b judge in both orders (neither is a DeepSeek model); the Principal grades only split verdicts and 10 calibration tasks. Both arms run the same tasks at the production sampling and caps per role, with each arm's truncation rate recorded. The rule is written to the ledger before unblinding: V4.1 is promoted only with at least 26 wins of 40 decided pairs (p = 0.040), no more fatal errors than 0731, no loss in B, D or E, and the 4 tok/s deep-tier floor met; ties above 25% add 10 tasks. T-32's promise is at least 45% preference with no fatal excess (it was 55%). The V4.1 container is to run with no network while it holds the tasks. The runner is built (atlas-admin eval, phased). PR #28696 is still open on 2026-10-17, so D-51 (a) stands and the trial does not wait for it. Order: B, D and E drafted first from public material, A and C once the node is live, the 0731 arm right after the Day 1 gate. To-do: the trial build script and image (S-51), with the Arbiter change that registering it as an exclusive external engine needs (at v0.4.0 an external process is never exclusive, atlas/arbiter.py:80); the Principal's 8 to 10 TF_OMEGA situations, then approval of the drafts (trial-task-set). The event: Day 1 complete. T-29 checks the container first and T-31 its speed; the Lucebox engine is a second stage only if the first shows promise (T-32) | E44: DeepSeek-V4-Flash-0731 as the Apex, only if V4.1 wins T-30
A45: DeepSeek V4.1 Flash runtimes: llama.cpp PR #28696 and ik_llama.cpp (added 2026-10-16, B-66) | B45: Mainline and fork support for V4.1 | C45: No deepseek41 architecture in the pin. #28696 is open (still on 2026-10-17, VERIFIED), CPU and CUDA only, with a cap near 16K context and no backend kernels; its Q2_K would need 186.17 GiB resident and spill 30.2 GiB to the SSD. ik_llama.cpp merged V4.1 on 2026-09-21, CPU and CUDA only, an unmeasured path here (UNVERIFIED) | D45: #28696 merges with Vulkan or HIP kernels | E45: The trial's ROCm container (row above)
A46: Single-stream speculative decoding (added 2026-10-16; D-61, B-34, D-64 option (a)) | B46: A draft with exact verification: native MTP heads (GLM-5.3-Flash, Qwen3.8-Flash-Next, Nemotron 3 Super) or DSpark for DeepSeek-V4-Flash-0731. It pays off here because the seats run one at a time | C46: No drafter is pulled on Day 1, and draft acceptance at the node's own temperatures (0.15, 0.2 and 0.6; 1.0 is only the server default, S56) is unmeasured. DSpark (10.90 GB) does not fit beside UD-Q8_K_XL in the ~156 GiB budget (160.90 GiB together, INFERRED), so it applies to DeepSeek only at a lower rung; separate draft models are never used | D46: Decided per engine after the Phase 3 speed records, with acceptance measured at temperatures 0, 0.15, 0.6 and 1.0 (T-06, D-47, S56), first in the V4.1 trial (T-31); phased with the drafters (5.1) | E46: Nothing: a lossless acceleration under 16.1 rule 9
A47: GLM Legal (added 2026-10-16, B-61) | B47: A legal model of the GLM family, the top open-weight result on Vals' LegalBench (about 86.2%, UNVERIFIED here) | C47: API beta only; parameter count, licence and GGUF unknown. Fails the zero-cloud rule (Section 1) | D47: Open weights with a GGUF that fits alone and a licence that can be read | E47: GLM-5.3-Flash on Gideon's legal work
A48: Mistral Large 4 (added 2026-10-16, B-61) | B48: About 1.05T parameters | C48: Vals lists it as open-weight (released 2026-10-06), but no mistralai weights repository existed on 2026-10-15; at that size no rung of 4 bits or more fits the budget (INFERRED) | D48: Weights published with a rung that fits alone | E48: Nothing named
A49: Nemotron 4 (added 2026-10-16, B-61) | B49: NVIDIA's next Nemotron line | C49: In training; no release date | D49: A release with a rung that fits alone | E49: Nemotron 3 Super (phased, 5.1)
A50: Nemotron 3 Puzzle 75B-A9B (added 2026-10-16, S-52, S-57) | B50: A 75B MoE with 9B active, OpenMDW-1.1 | C50: Not allocated a seat in the 2026 review; on Vulkan only its Q8_0 decodes correctly, 4-bit MoE quants collapse (llama.cpp PR #25444; UNVERIFIED here) | D50: A seat the Day 1 engines leave open, and a node test at Q8_0 | E50: Nothing named
A51: 300B-class engines at 3 bits: Qwen3.5-397B (UD-IQ3_XXS) and K2-Horizon-375B (IQ3_XXS, loadable since b11454) (added 2026-10-16, S-57) | B51: Large MoE engines whose only fitting rungs are 3-bit | C51: The least-quantised rule (Section 1; D-24 option (a), D-11 option (d)) | D51: A rung of 4 bits or more that fits alone: a smaller release, or a larger budget (W-DGPU, 3.7) | E51: Nothing named
... A56: A speech endpoint in llama-server, llama.cpp PR #26603 (added 2026-10-16, S-57) | B56: Text-to-speech served by llama-server itself | C56: Open upstream; until it merges, Qwen3-TTS runs only through the llama-tts tool (14.1) | D56: The PR merges into a build the node pins | E56: llama-tts for the Qwen3-TTS test
A57: Decision recorded 2026-09-21: FLUX.1-dev stays as the image engine, quality being the deciding factor. FLUX.1-dev carries the same non-commercial licence as Qwen-Image-2.1, so the licence does not separate them; validation on gfx1151 does.
A59: Considered and not adopted (15.5, v0.4.0): the rule each fails
A60: Rule it fails | B60: Engines and companions | C60: Register
A61: Below the 70B floor for an LLM seat (Section 1) | B61: Qwen3.8-27B, Gemma 4 31B and MedGemma-27B; Nemotron 3.5 Lightning 30B-A3B, Muse Glimmer 28B, Qwen3.6-27B and Qwen3.6-35B-A3B | C61: D-15 (d), D-19 (d), D-20 (f)
A62: Only 1- to 3-bit rungs fit (the least-quantised rule) | B62: Llama 4 Maverick, Mistral Large 3 (1-bit), Intern-S2-397B (2-bit), Hy3, and the two 3-bit engines on the watch-list above | C62: D-24 (a), D-11 (d)
A63: Dense 120B-class models decode at about 2 tok/s or less (D-24) | B63: Mistral Medium 3.5 (128B), Devstral 2 (123B); Mistral Large 2 Uncensored, the named Ollama build (legacy Q4_0, a system prompt that instructs falsification, a research-only licence), with its weight-edited XORTRON alternative (about 1.7 tok/s) | C63: D-06 (a), D-24 (a)
A64: Out-ranked at a fitting rung by the adopted engines (the 2026 allocation) | B64: Qwen3-235B-A22B (a 2025 generation; Intern-S1, its science post-train, carries the lineage), Step-3.7-Flash, Mistral Small 4 (its experts ran on the CPU on stock Vulkan builds), Qwen3-VL-235B (the vision runner-up), Apertus-70B-MeditronFO | C64: D-10 (a), D-15 (a), D-20 (a)
A65: Leaving the roster | B65: Qwen3.5-122B-A10B, Qwen2.5-VL-72B, Meditron-70B (5.1) | C65: D-21 (a)
A66: Out of envelope: no rung fits alone at a precision the rules accept | B66: Nemotron 3 Ultra 550B-A55B, Qwen3.8-2.4T-A95B (also under its own Qwen3.8-Max licence), MiMo-V2.6-Pro, GLM-5.3 (744B), Kimi K3 | C66: S-52
A67: Experimental, with no node test | B67: DeepSeek-V4-Flash-Vision-Exp (its projector type is in the pin) | C67: S-52
A68: Vision at the pin but not allocated: ATLAS keeps one vision engine (C29) | B68: Stock MiMo-V2.6-Flash, MiniMax-M3, Qwen3.8-Flash-Next with its mmproj | C68: D-20 (a)
A69: Non-commercial licence | B69: FLUX.2-dev (also a 24B text encoder); the voice and diarisation exclusions are in 14.1 | C69: C-11
A70: Router alternatives with no measured advantage (the 4B router is kept) | B70: Gemma 4 E4B, Granite 4.1 8B | C70: C-01
A71: Zero-cloud (Section 1) | B71: Lucebox's appliance software: its updater, Manage, Connect, Tailscale, crash reporting and cloud fallback. Of Lucebox's software only its Apache 2.0 engine may ever be built, from a pinned commit inside the trial container, and only if the trial reaches its second stage | C71: D-55 (b), S-56
A72: Recorded with the register rows that left each out (approved by the Principal on 2026-10-16). None is on the node, and none is re-checked unless a later release or a watch-list row changes the answer.

Sheet Ref Governance
A1: Ref Governance
A2: Section 16. The never-without-the-Principal list is decision D8; the approval tiers are agreed. v0.4.0 adds standing rules 9 (routed engines use only lossless accelerations, S-50) and 10 (the arsenal admission rules, S-13). S57: item 2 covers every licence and terms of use; ATLAS never accepts terms on the Principal's behalf.
A4: Standing rules
A5: # | B5: Rule
A6: 1 | B6: The Principal speaks only to Ren or Arthur. Shadow Cabinet output is never surfaced directly; the hemisphere synthesises and speaks.
A7: 2 | B7: Directors correspond externally under their own identities for routine and standard matters; Ren and Arthur are reserved for matters that warrant them.
A8: 3 | B8: Every outbound action passes the approval gate in code (16.2). This is a hard code path, not a prompt instruction.
A9: 4 | B9: ATLAS never discloses its AI nature externally. Recorded as a legal exposure in R12; the approval gate is the control.
A10: 5 | B10: ATLAS never delegates work back to the Principal. A rewrite pass removes any task-shaped request to the Principal; only decisions and approvals may be asked.
A11: 6 | B11: Register differs between Principal and external recipients (6.4).
A12: 7 | B12: Cross-domain requests must trigger their task-force preset (8.3).
A13: 8 | B13: Money never moves without the Principal. Two-factor prompts are never automated.
A14: 9 | B14: *v0.4.0 (S-50; D-56 options (a) and (b), approved by the Principal on 2026-10-16 in the returned action register):* routed engines use only lossless accelerations: the default expert count, speculative decoding with exact verification, and prefix caching. An approximate switch (a per-box router bias, a bounded sliding-window replay in the decoder, sparse prefill) is allowed only inside the V4.1 trial, each scored against the same file without it; vendor speed settings that change results, such as running fewer experts, never.
A15: 10 | B15: *v0.4.0 (S-13):* every engine is admitted under Section 1's arsenal rules: no LLM seat under about 70B total parameters, each engine alone with the whole engine budget, quality before speed, and the least-quantised rung that fits, with its measured quality cost stated.
A17: Approval tiers
A18: Tier | B18: Examples | C18: Behaviour
A19: Routine | B19: Meeting scheduling, confirmations, acknowledgements | C19: Pre-approved categories, sent automatically, logged for review
A20: Standard | B20: Replies with substance, requests, negotiations, content updates, DNS changes; configuration proposals from Domain 20 (retention, window, maintenance; S53), submitted by a hemisphere lead in the Principal register | C20: Drafted, held until the Principal approves. For a configuration proposal the approval records the decision and the Principal applies the change as root (16.3 item 6); ATLAS applies nothing
A21: Sensitive | B21: Legal, financial, medical, estate, security, any payment, anything under a sensitive-tier task force | C21: Drafted, held, flagged with the director's reasoning; strong cross-check applied automatically
A23: Never without the Principal (proposed, D8)
A24: # | B24: Action
A25: 1 | B25: Move money, initiate a payment, or change a payment method.
A26: 2 | B26: Sign, accept, or bind to a contract or terms.
A27: 3 | B27: Send external correspondence above the routine tier.
A28: 4 | B28: Change DNS, domain, or Cloudflare security settings.
A29: 5 | B29: Delete, move, or modify vault contents or backups.
A30: 6 | B30: Modify its own code, configuration, approval tiers, router rules, or the allowlist. Domain 20 proposes; the Principal approves.
A31: 7 | B31: Enable continuous vision or audio capture.
A32: 8 | B32: Install software or pull models from outside the allowlist.
A33: 9 | B33: Share any Principal data with a third party not already connected under Section 13.
A34: 10 | B34: Create new external identities, accounts, or mailboxes.

Sheet Ref Day 1
A1: Ref Day 1
A2: Section 17. Four phases; each ends with a printed pass/fail gate. Phases 3 and 4 run detached and resumable. v0.4.0: Phase 3 pulls the four Day 1 LLM repositories (about 448 GB), adds step 2b (V25, the output parity of the re-pin) and step 2c (the quality record, to-do kld-run), and proves single residency in step 3 (V21). S56 (2026-10-17): V10 gates on the decode floors at 8k, the prefill floors and the placement checks, and the pull is about 2.5 hours at the 400 Mbps planning figure.
A4: Expected durations
A5: Phase | B5: Time
A6: 1 | B6: 30 to 60 minutes including reboot
A7: 2 | B7: 30 to 60 minutes
A8: 3 | B8: Download-bound: ~2.5 hours at the 400 Mbps planning figure for ~448 GB (S56, B-27; about 30 minutes at the 2,000 Mbps line rate with parallel downloads, ATLAS_PULL_JOBS above 1; v0.4.0 planned ~10 hours at 100 Mbps over Wi-Fi, v0.3.5 ~15 hours for ~690 GB); plus the load, parity and quality tests, longer than v0.3.5's ~30 minutes now that each large seat takes about a minute to load and decodes at 7 to 14 tok/s (INFERRED; Phase 3 records the times)
A9: 4 | B9: Download and build-bound: several hours; can run overnight
A11: Phase steps
A12: Phase | B12: Step
A13: Phase 1 | B13: 1. Pre-flight, using only what a bare host has (one exception since v0.3.4, below): confirm Ubuntu Server 26.04.1, kernel 7.0, both NVMe drives present, fTPM enabled (V2), and the GPU present and identified from lspci and /sys/class/drm. The rocminfo confirmation of gfx1151 belongs to the Phase 4 container self-test (V11), because ROCm is never installed on the host (3.4). *v0.3.4: the one package step 1 fetches is systemd's TPM2 library set (libtss2-rc0t64, which the server image lacks, and esys/mu/tcti-device when a minimized install lacks those too), from the Ubuntu archive before the proxy and firewall exist; exactly one TPM is required, since tpm2-device=auto refuses two (S42). Every package install through the scripts' installer and every package-list update first waits, up to 15 minutes, for apt-daily/unattended-upgrades to finish; the remaining apt calls wait on the dpkg lock for 5 minutes. S56 (B-27, 2026-10-17): step 1 also notes the LAN interface, its driver, PCI ids and MAC, and what must point at that MAC (the cable on the 10 GbE port not marked DASH, the DHCP reservation, the UDP 51820 forward, Wi-Fi off the LAN subnet); it warns, never stops, on a Wi-Fi LAN interface, on the controller the driver treats as the DASH part, and on a second interface with an address on the LAN subnet (phase1/01-preflight.sh phase1_lan_link_note).*
A14: Phase 1 | B14: 2. LUKS2 on the data volume, TPM2 enrolment, recovery key printed once for off-node storage (D3).
A15: Phase 1 | B15: 3. Mount layout per Section 3.5; swap off; tmpfs for /tmp, capped at 4 GiB by a tmp.mount drop-in from the next boot (*S55, 2026-10-17;* it was 16 GiB).
A16: Phase 1 | B16: 4. System update; kernel parameters (V3); firewall baseline; SSH hardening; Cockpit. *v0.3.4: tpm2-tools is installed before the update and every initramfs is rebuilt with TPM2 support before the reboot (S32); time sync is proven through the closed firewall (S35). v0.3.5: before the update the node is held on the GA 7.0 kernel line; HWE metapackages over the same 7.0 image are swapped for linux-generic after a clean apt simulation, anything else (an OEM kernel, an image outside 7.0, a kernel metapackage held with apt-mark) becomes the to-do kernel-line (S45). v0.3.5, option (c) of 2026-10-10 (S48): kdump is switched off without removing the package (debconf answer false and USE_KDUMP=0, kdump-tools.service disabled and masked, a loaded crash kernel unloaded), and /etc/default/grub.d/zzz-atlas-crash.cfg removes every crashkernel= and panic= from the kernel line and appends panic=10; after update-grub the step stops if grub.cfg still carries crashkernel= or its first kernel line (the default entry) does not carry exactly one panic=10. v0.3.5, 2026-10-10 (S49): the same drop-in also removes every kho= and appends kho=off after panic=10, the step stops unless that first kernel line carries exactly one kho= word and it is kho=off, and its log records the kexec handover scratch the running kernel holds (on the first run that boot still carries the crash-kernel reservation, which adds about 8.5 GiB to the scratch, S49). v0.3.5, 2026-10-11 (S50): last before the reboot, the step finds the hardware watchdog without starting it: it loads sp5100_tco by name, since Ubuntu blacklists every watchdog module, and does not take a zero exit status as proof (only /sys/class/watchdog counts, where a device named exactly SP5100 TCO timer and bound to the sp5100-tco driver must appear); otherwise it unloads the module, tries wdat_wdt only when ACPI has a WDAT table, and with neither chooses softdog soft_panic=1 for the next boot (not loaded now) and raises the to-do watchdog, which a later run that finds a hardware watchdog closes. It never opens /dev/watchdog*. It then writes /etc/systemd/system/atlas-watchdog-driver.service (a plain modprobe of the chosen driver before sysinit.target at every boot), enabled without reloading systemd, and /etc/systemd/system.conf.d/90-atlas-watchdog.conf (RuntimeWatchdogSec=2min, RebootWatchdogSec=10min), both rewritten whole on every run, and logs what it found (the SMBus controller's PCI ids, whether ACPI has a WDAT table, and the device's state, timeout and boot status, or the driver's kernel lines when it made no device). systemd arms the watchdog from the reboot on. A missing hardware watchdog never stops the step; a unit that cannot be enabled does.*
A17: Phase 1 | B17: 5. Reboot. Post-reboot: vulkaninfo shows the Radeon 8065S, and the GTT pool read from /sys/class/drm matches the kernel parameters (V3, first half). The llama-cli --list-devices check (llama.cpp's Vulkan backend lists the GPU as Vulkan0 with at least 160000 MiB, about 156 GiB, of device memory, or the largest Day 1 seat's projected footprint if that is larger (v0.4.0, D-36 option (c)); the figure is recorded and is not the engine budget) moves to the Phase 2 gate, since llama.cpp is installed in Phase 2 (V3, second half). *v0.3.5: V3a also proves the crash settings of S48: no crashkernel= on the booted command line and no crash-kernel memory reserved, exactly one panic=10, kernel.panic 10 and kernel.panic_on_oops 0. Since S49 it also fails unless the booted command line carries exactly one kho= word, the literal kho=off, and on any CMA memory: kexec handover scratch still set aside (the zone cma pages of /proc/zoneinfo less CmaTotal, which never counts the scratch) or a named CMA area (CmaTotal above 0). Three read-only records follow: the kernel line (the to-do kernel-line closes once it is GA 7.0, and is raised again with the state after the reboot otherwise, S45), what the unused NPU shows (PCI revision, driver, /dev/accel; 3.7 W-NPU), and whether a kernel panic's log can be kept across the restart (the pstore backend, systemd-pstore.service, archived records and kdump's state; S48), which warns but never stops. v0.3.5, 2026-10-11 (S50): right after V3a, V24 proves that systemd has armed the watchdog step 4 installed, with both timeouts in effect, pings it and is the only holder of the device; a hardware watchdog passes, the softdog fallback is recorded deferred (to-do watchdog), and anything else, no watchdog device at all included, is a fail that stops the step as V3a does. Last, step 5 raises the to-do w-drill, the crash and watchdog tests the live ATLAS runs later with the Principal present (3.7 W-DRILL).*
A18: Phase 1 | B18: 5b. XFCE and xrdp installed, bound to LAN and WireGuard only; Google Chrome in the desktop session (v0.3.3); one RDP connection tested from the Principal's Windows PC (V19; no connection within 10 minutes is deferred with a to-do, not failed).
A19: Phase 1 | B19: 6. Docker with GPU device passthrough; service account in render and video.
A20: Phase 1 | B20: 7. WG-Easy, Cloudflare dynamic DNS with the relocated scoped token (R7), ntfy.
A21: Phase 1 | B21: 8. Gate: table of V2, V3 first half, V5, V19 and V24 results. Phase 2 does not start on a red row. V1 is recorded as informational only; since S56 it records the cable's driver and link speed and warns below 2,500 Mb/s (B-27). *v0.3.5 (S50): V24 is required; its deferred row (the softdog fallback, to-do watchdog) never blocks, like every deferred row.*
A22: Phase 2 | B22: 1. llama-server, Vulkan build. *v0.4.0 (S-01, S-02, S-37; D-01 option (c), approved by the Principal on 2026-10-16 in the returned action register):* built from the pinned build tag b11474 (3.4), with llama-perplexity among the installed binaries; beside it, v0.4.1's llama-perplexity alone, from a git worktree into /opt/atlas/llama-parity, for the Phase 3 parity test V25 only. Up to 20 engine slots (ports 8101 to 8120); the Day 1 set is seven units (S-33). The optional ROCm container for tuned prefill is phased after Day 1 (3.4, D-52 option (b)).
A23: Phase 2 | B23: 2. Redis, Celery workers (cpu, gpu queues), orchestrator scaffold with the Engine Arbiter, router, approval queue, task ledger. *v0.4.0 (D-32 option (a)):* ATLAS_ARBITER_MAX_RESIDENT=1 is seeded once into orchestrator.env, so a value the Principal sets survives a re-run (4.2 rule 3). *S55 (2026-10-17):* the Celery cpu worker's concurrency is min(8, nproc − 2), at least 1 (CELERY_CPU_CONCURRENCY in orchestrator.env), and the units carry the out-of-memory order (OOMScoreAdjust 500 on the Celery cpu worker, -500 on the orchestrator and on llama-server@).
... A47: Phase 4 | B47: 6. Gate: per-engine table: built, loaded, sample output produced, footprint, pass/fail/deferred.
A49: Phase 3 test plan: every test in the action register (v0.4.0)
A50: Test | B50: Settles | C50: Day 1 | D50: How and when
A51: T-01: the GTT pool and Vulkan device memory on kernel 7.0 | B51: D-36; every rung above about 149 GiB | C51: Day 1 scripted | D51: V3a (Phase 1 step 5) and V3b (Phase 2 gate), with V3b's floor raised to the largest Day 1 seat with its context memory (D-36 (c)); the measured heap decides every rung above about 149 GiB (B-31)
A52: T-02: output parity between the two pins | B52: D-01; the -fa setting; GLM's --kv-unified coherence (D-48) | C52: Day 1 scripted, in part; the rest after Day 1 | D52: Phase 3 step 2b (V25) on gpt-oss-120b, DeepSeek-V4-Flash-0731 and the router. GLM-5.3-Flash cannot load on the old pin; the phased engines are compared at their own pull (Qwen3-Coder-Next no longer among them, D-19 (c), S56)
A53: T-03: the KLD run against a reference | B53: D-02, D-11, D-16, D-19, D-28, D-29 | C53: Day 1 scripted (the record); after Day 1 (the reference run, the coding set and the D-16 gate) | D53: Phase 3 step 2c records each seat's perplexity and task score and raises kld-run; the reference files are not pulled on Day 1 (step 2c). *S56:* D-19 (c) adds 20 to 30 of the Principal's own coding tasks, run on GLM-5.3-Flash UD-IQ4_XS and DeepSeek-V4-Flash-0731 UD-Q8_K_XL at each seat's real slot profile and reasoning setting, recording pass rate and wall-clock per task; the result decides which seat codes (the tasks are a to-do, Section 22). D-16 adds the q8_0 cache gate of the phased Intern-S1 and Baichuan-M3 at their pull: llama-perplexity --kl-divergence at -c 4096 -b 512 on a medical and scientific corpus, and a long-context A/B test through llama-server at 1 × 16,384, f16 against q8_0; q8_0 is accepted at a mean KLD of about 0.005 or less, the same top token about 98% of the time or more, and no more than about 1 in 50 long answers changed
A54: T-04: GLM-5.3-Flash on Vulkan at the pin | B54: D-02's conditions; D-48; GLM's cache type (D-29) | C54: Day 1 scripted, in part; the rest after Day 1 | D54: Phase 3 step 2 loads it with flash attention on and an f16 cache, proves both KV lines (V4), measures decode and prefill at 512 and 8k, and records its V22 row. Whether its hyper-connection operation runs on the GPU, multi-slot coherence under --kv-unified and decode at 32k and 128k follow after Day 1, with D-48
A55: T-05: every Day 1 engine against the Arbiter's projections | B55: D-10, D-29, D-31, D-33, D-48 | C55: Day 1 scripted | D55: Phase 3 steps 2 and 4: V4, V10 beside the projections, and the kv-estimates and cache-ram records
A56: T-06: DeepSeek-V4-Flash-0731 on mainline Vulkan | B56: D-11, D-29, D-33, D-47, D-61 | C56: Day 1 scripted, in part; the rest after Day 1 | D56: Phase 3 step 2: UD-Q8_K_XL on the f16-first ladder, its V22 row, and V10 judged at 8k with DSpark off against the 4 tok/s floor, beside the 6.8 to 7.2 tok/s projection and the review line (4.8 tok/s, 70% of 6.8; S56, D-47). UD-Q4_K_XL is pulled only if the relief order of 4.1 reaches it, or if Q8 decodes below 4 with clean placement lines. After Day 1: decode at 8k, 16k and 32k beside the floor and the review line, for the Principal's choice between the two rungs, and DSpark at both rungs as a record, at temperatures 0, 0.15, 0.6 and 1.0 (15.5); production DSpark only at a lower rung (D-61)
A57: T-07: Qwen3.8-Flash-Next decode | B57: Its role as challenger and third opinion; D-28 | C57: After Day 1 | D57: At its post-Day-1 pull (5.1)
A58: T-08: the ggml-org Qwen3.8-Flash-Next Q8_0 KLD | B58: D-28 | C58: After Day 1 | D58: Folded into T-03, before any Flash-Next pull
A59: T-09 and T-10 | B59: D-07, D-08, D-09, D-58 | C59: After Day 1 | D59: With the items they settle (Section 19)
A60: T-11: Baichuan-M3-235B load and a HealthBench subset | B60: D-15, D-16 | C60: After Day 1 | D60: At its post-Day-1 pull, on the i1-Q5_K_S file (S56, D-16): load at 1 × 16,384 with q8_0 first and copy the logged compute buffer into engines.json; check that both KV lines read q8_0, the rotation lines read n_rot_k = 128 and n_rot_v = 64, and LLAMA_ATTN_ROT_DISABLE is unset; then grant 32,768 (40,960 if at least 0.5 GiB is left), after T-03's q8_0 gate
A61: T-12: Nemotron 3 Super with a prompt of 20K tokens or more | B61: D-13; llama.cpp #20732 | C61: After Day 1 | D61: At its post-Day-1 pull; Phase 3's alive check after the 8k prefill stays on every engine
... A79: T-33: an R9700 in a USB4 dock | B79: D-62 (b) | C79: Not scheduled | D79: Only if D-62 becomes (b) (W-DGPU, 3.7)
A80: Day 1 scripted: a Day 1 step runs and records it. Day 1 manual: done by hand during Day 1, with the Principal. After Day 1: with its to-do; most wait on a phased engine or on the Principal's own material.

Sheet Ref Hardware
A1: Ref Hardware
A2: Sections 2, 3.7 and 4.1. The machine v0.2 is built for, what is deliberately left out of its platform, and what its 192 GB actually buys (v0.4.0: one LLM seat at a time, about 156 GiB for it).
A4: GMKtec EVO-X5 Pro, Gorgon Halo platform
A5: Component | B5: Specification | C5: Design consequence
A6: CPU | B6: AMD Ryzen AI Max+ PRO 495, 16 Zen 5 cores, 32 threads, up to 5.2 GHz, 64 MB cache | C6: Ample for orchestrator, Celery CPU workers, vector DB, browser automation, CPU-only tools (Radiance, EnergyPlus, KiCad, Docling) and, since v0.4.0, the Qwen3 4B embedder and reranker (D-14 (e), 4.1)
A7: GPU | B7: Radeon 8065S, 40 CUs, RDNA 3.5, ROCm target gfx1151, confirmed by the Principal | C7: Runs all inference except the CPU retrieval pair (v0.4.0, 4.1). Same identifier as the previous machine, so every community ROCm, Vulkan and llama.cpp finding carries over unchanged
A8: NPU | B8: XDNA 2, up to 55 TOPS | C8: Not used. Zero design dependency (re-checked 2026-10-09, watch-list W-NPU in 3.7). The 26.04 kernel already ships the NPU driver (amdxdna) and its firmware, so the NPU may show up as /dev/accel/accel0; that is harmless, no container is given it, and step 5 records what the node shows. Linux NPU software now exists (FastFlowLM, maintained by AMD, with an Ubuntu 26.04 package), so v0.3.4's "Windows-first" no longer holds, but it does not fit ATLAS today (3.7)
A9: Memory | B9: 192 GB LPDDR5X-8533, soldered | C9: 273 GB/s. Decode speed = bandwidth ÷ active weight bytes. Not upgradeable
A10: GPU-addressable memory | B10: All of MemTotal on Linux via GTT once Day 1 has switched off kexec handover (kho=off, S49; with it on, Ubuntu's 7.0 kernel keeps about 13 GiB of MemTotal where GPU pages cannot go), about 187 to 188 GiB expected once Day 1 has removed the 4.25 GiB that kdump-tools reserves for a crash kernel (S48), of which about 156 GiB is free for engines once the GPU resident set (the router), the CPU retrieval pair and the 16 GiB host reserve are subtracted (4.1; v0.3.5 said about 164 GiB, with the bge pair on the iGPU; v0.3.4 said ~180 GB and ~170 GB) | C10: VERIFY V3. The reason to buy this machine, and what makes the two 147 to 151 GiB Day 1 seats possible
A11: Power | B11: 45–120 W configurable TDP | C11: Principal is adding external cooling (R10)
A12: Expansion | B12: USB4 ports with external GPU dock support; a third M.2 slot unused | C12: A CUDA-locked tool (NVIDIA Modulus/PhysicsNeMo) would need an NVIDIA card via the dock
A13: Network | B13: Wired 10 GbE, by the Principal's choice of 2026-10-17 (S56, B-27): a cable from the 10 GbE port not marked DASH (the one away from DC IN) to a 2.5 GbE router port, decided before Phase 1, with Wi-Fi off the LAN subnet. A 2,000 Mbps Internet line. Until 2026-10-17 the node was to run on Wi-Fi only | C13: The cable is LAN_IFACE from Phase 1, so the DHCP reservation and the UDP 51820 forward move to that port's MAC. Both ports are Realtek RTL8127 parts, carried by kernel 7.0's r8169 driver (R9; VERIFIED). V1 is informational, not a gate, and records the link speed. The single-stream pull, not the line, sets the download time (15.4)
A14: Storage 1 | B14: 8 TB NVMe, PCIe 4.0 x4 | C14: /srv/atlas: models, engines, agent data, vector stores, vault. The growing side
A15: Storage 2 | B15: 4 TB NVMe, PCIe 4.0 x4 | C15: Operating system, logs, cold storage archives, restic backups. Both drives are now the same speed, so capacity decides the split, not bandwidth
A17: Platform watch-list: considered, not adopted, and the guided tests for later (3.7, reviewed 2026-10-09; W-DRILL added 2026-10-11; W-DGPU, W-PLACEMENT, W-MEMGUARD, W-MANIFEST and W-SESSIONLOG added 2026-10-16)
A18: Item | B18: What it is | C18: Why not now | D18: What would change the answer
A19: W-NPU: the XDNA 2 NPU (reviewed 2026-10-09) | B19: The NPU inside the PRO 495. The Linux 7.4 patch ("accel/amdxdna: Add support for AIE2 revision 9", posted 2026-09-29) adds two lines that give it the name "NPU Gorgon Halo"; the driver binds by PCI identity (1022:17f0 at PCI revision 0x10, 0x11 or 0x20), not by this name table, so the patch changes no binding: a matching NPU binds under a generic name without it. That this chip matches is INFERRED (one user report of 1022:17f0 on a 7.2.8 kernel; no primary source for its revision), which is why step 5 records it. Kernel 7.0 has no name table at all, so the patch cannot apply to it. The in-tree amdxdna driver and the NPU firmware already ship in 26.04 (linux-modules-7.0.0-*-generic, linux-firmware-amd-misc). The only Linux NPU runtime is FastFlowLM (AMD/ROCm since v1.0.0, 2026-08-11; v1.0.7 has an Ubuntu 26.04 package whose XRT libraries are in universe); Lemonade reaches the NPU only through it | C19: Nothing ATLAS runs gains from it. No NPU build of the retrieval pair (bge-m3 and bge-reranker-v2-m3 at the 2026-10-09 review; Qwen3-Embedding-4B and Qwen3-Reranker-4B, on the CPU, since v0.4.0); the router model exists only in FastFlowLM's own 4-bit format and community figures put the NPU several times slower than the iGPU; the NPU shares the same 192 GB and the same bandwidth, so moving work to it frees nothing. FastFlowLM does not list this chip, runs closed-source NPU kernels under licence terms that contradict each other (README "free for any use", TERMS.md a USD 10M revenue threshold), loads one model per process and downloads models from Hugging Face, and the community container known to work needs seccomp=unconfined, unlimited memlock and a world-writable /dev/accel/accel0, where ATLAS's service containers drop their capabilities and keep the default seccomp profile (the one exception is Phase 4: if V11 shows on this node that the GPU self-test fails under the default profile and passes without it, Phase 4's GPU test containers run with seccomp=unconfined, recorded and warned). Getting Linux 7.4 code would mean leaving the GA kernel (3.3, S45) for a name | D19: FastFlowLM (or Lemonade) lists Gorgon Halo / Ryzen AI Max 400 and Ubuntu 26.04 as supported; its licence is settled in writing; an NPU build of a model ATLAS uses appears; a like-for-like speech-to-text measurement on Strix Halo or Gorgon Halo beats the CPU path on latency or energy without accuracy loss (Whisper is the only plausible candidate); a runtime that works under ATLAS's container hardening with models installed offline. Separately: a Gorgon Halo NPU fix in the 26.04 GA kernel by SRU (Launchpad bug 2169534, title seen only), or amdxdna errors in the step-5 record, which the normal SRU flow handles (blacklisting amdxdna is the fallback if it ever misbehaves)
A20: W-PERFOPT: AMD IOMMU "PerfOpt" for integrated GPUs (reviewed 2026-10-09) | B20: A Linux 7.4 change that lets the iGPU bypass IOMMU translation when it is in identity mode (amdgpu.iommu_perfopt=0 turns it off) | C20: Not in the 7.0 kernel. Reported gains disagree (18 to 23% in one report, a typical 2 to 4% on Strix Halo in another), and it switches off the IOMMU's containment of GPU memory access (ATS, PRI, PASID and SVA disabled) on a node that enables the IOMMU (3.2); its merge was not confirmed from a primary source | D20: It reaches the 26.04 GA kernel by SRU, or independent llama.cpp Vulkan benchmarks on Strix or Gorgon Halo show at least 10% with the DMA trade-off reviewed; or ATLAS deliberately changes kernel line (W-KERNEL)
A21: W-KERNEL: newer kernel lines (reviewed 2026-10-09) | B21: The 26.04 HWE kernels: the 26.10 kernel (7.3) is expected with the 26.04.2 point release (INFERRED; milestone 2027-02-18, possibly in -updates a month earlier); 26.04.3 the 27.04 kernel, the first stock Ubuntu kernel built on 7.4 code, around August 2027 by precedent; the line settles on the 28.04 kernel at 26.04.5 (about August or September 2028). The OEM kernels (linux-oem-26.04, -26.04a, -26.04b) are still 7.0-based with a shorter life | C21: The GA line stays on 7.0, the kernel the Section 3.3 parameters were validated on, with standard support to May 2031. The HWE line moves to a new kernel series about every six months until 2028, each a re-validation of V3a, V11 and V22 on an unattended node. Day 1 holds the node on GA (S45) | D21: A V-check or a driver feature that only a newer kernel provides, decided by the Principal as a deliberate change of line; then V3a, V11, V22, W-NPU and W-PERFOPT are re-tested together
A22: W-DRILL: guided crash and watchdog tests, led by the live ATLAS with the Principal present (added 2026-10-11 at the Principal's request) | B22: Day 1 arms the crash restart (panic=10, S48) and the hardware watchdog (S50) but never proves that they work on this board. In a session the Principal has agreed to, ATLAS explains each test and its risk in plain words, waits for the Principal's go-ahead before each one, runs it, and records the result. (1) Crash restart: with all work written to disk (sync), a test panic (echo c > /proc/sysrq-trigger). This proves that panic=10 restarts the node, that the TPM then unlocks both disks unattended, and whether a panic record reaches /var/lib/systemd/pstore (step 5 recorded the pstore backend). (2) Watchdog reset: ATLAS stops systemd's pings and lets the timer expire, about two minutes. This proves that this board's FCH timer really resets the node, again with the unattended unlock, and reads the reset cause on the next boot (the device's bootstatus, the kernel log). (3) Timer survival: after one of those resets, the Principal holds the next boot at the GRUB menu for over two minutes. A second reset means the timer outlives the board's reset, and loading the driver in the initramfs (S50) becomes a decision for the Principal. (4) Suspend: either a short suspend with the timer armed, to see whether it resets the node, or the Principal's choice to mask the sleep targets instead. Each UNKNOWN in S48 and S50 that a test settles is written back to this document as VERIFIED, with the date. Phase 1 step 5 puts the tests on the to-do list the live ATLAS works from (w-drill), and raises them again whenever step 5 runs after the live ATLAS has closed them | C22: Day 1 never triggers a panic or a reset: its phases run largely unattended, and a test that goes wrong (a failed unlock, a restart loop) needs the Principal at the console with the LUKS recovery keys (D3). The tests also need the live ATLAS and its records, which exist only once Day 1 is complete. A deliberate panic or reset is never ATLAS's own decision: it runs only in a session the Principal has agreed to and attends | D22: Day 1 complete (the Phase 4 gate passed) and the live ATLAS running: ATLAS then proposes the first session, for an idle node (no engine loaded, no task running, the night's AEGIS backup done), with the Principal at the console and the recovery keys at hand. ATLAS proposes the tests again after a BIOS or firmware update, a change of kernel line (W-KERNEL), a TPM re-seal, or any change to the S48 or S50 settings, since each can change the restart or unlock path
A23: W-DGPU: a discrete GPU (added 2026-10-16; D-62 option (a), and D-63 option (a) for a second machine) | B23: A Radeon AI PRO R9700 (32 GB) in a USB4 v2 dock with a supply of 750 W or more, as a second device with its own memory pool. Its kernel parameters (thunderbolt.host_reset=false, amdgpu.runpm=0) and its power and noise limits would then join Sections 2, 3.3, 4.1 and 4.2 (S-55). A second machine, the Lucebox Zero 495 appliance, is not adopted either: it duplicates this node's processor, and its software checks for updates daily | C23: Lucebox's own engine measured large gains with the card for DeepSeek V4.1 and Qwen3.8-Flash-Next but almost none for the 0731 checkpoint ATLAS runs, and those are not the node's mainline Vulkan figures (UNVERIFIED here). The card costs about USD 1,800 before an unpriced dock and supply, never idles down with amdgpu.runpm=0, and brings a 300 W blower near 3,000 RPM | D23: The DeepSeek V4.1 trial (T-30, phased after Day 1) shows V4.1 or Qwen3.8-Flash-Next worth accelerating, preferably once a 32 GB card in a USB4 dock has been published working; the Principal then supplies a budget ceiling, the tolerance for the blower's noise and a second power brick, and whether external hardware is acceptable
A24: W-PLACEMENT: usage-ranked expert placement (added 2026-10-16; D-64 (a), B-62) | B24: The most-called experts of a MoE engine sit in the fastest memory, ranked by a routing profile measured on the node. llama.cpp's -ot tensor overrides are its manual form | C24: The node has one memory pool, so there is nothing to rank between | D24: W-DGPU is adopted: this is then the design to follow for the card's 32 GB
A25: W-MEMGUARD: Lucebox Manage's memory guard (added 2026-10-16; D-64 (a), B-63) | B25: A guard that stops a program filling memory before the machine can freeze | C25: Partly covered already: the Arbiter's hard pre-flight against a budget that keeps a fixed 16 GiB host reserve (4.1, 4.3) is the same idea, and a second guard would duplicate it | D25: The next baseline revision compares it with the Arbiter, rather than adding a second guard now
A26: W-MANIFEST: signed release manifests that expire (added 2026-10-16; D-64 (a), B-64) | B26: Lucebox signs its releases with Ed25519, and a manifest expires after 120 days | C26: Phase 4 and the llama.cpp builds pin exact versions and build once, with no expiry; the idea implies no updater and no outbound check, but nothing on Day 1 needs it | D26: A decision to re-attest the node's own pinned images on a schedule, as a cheap discipline with no updater and no outbound check
A27: W-SESSIONLOG: retrieval from local agent session logs (added 2026-10-16; D-64 (a), B-65) | B27: Lucebox's "Learning" without the marketing: relevant past work retrieved from local agent session logs into the prompt; retrieval, not training (its LoRA adapters are "Coming soon") | C27: The Vector Cortex and the graph layer (10.1, 10.2) index memory and documents, not session logs, and nothing on Day 1 needs them | D27: The live ATLAS has session logs worth retrieving: they then become a candidate source for the existing retrieval stack, not a new one
A28: Raised by the report 'Linux 7.4 to support the NPU on Ryzen AI Max 400 Gorgon Halo' (2026-09-30): a device-name patch with nothing to adopt. Day 1 records the NPU and the kernel line in Phase 1 step 5 and holds the GA 7.0 kernel line in step 4 (S45). W-DRILL (2026-10-11, at the Principal's request) is not a change left out: it defers the crash and watchdog tests of S48 and S50 to the live ATLAS, which proposes them once Day 1 is complete and runs each only with the Principal present and agreeing. The five items of 2026-10-16 come from the Lucebox review (D-62 (a), D-63 (a), D-64 (a), approved by the Principal): none is adopted and none changes Day 1.
A30: Memory budget
A31: Consumer | B31: Budget | C31: Notes
A32: Ubuntu Server, XFCE, Docker, Cockpit | B32: 4 GB | C32: XFCE adds roughly 0.5 GB over the headless figure in v0.1
A33: Open WebUI, ChromaDB, graph store | B33: 3 GB | C33: v0.4.0: the embedding model has its own row below (D-14 (e)); v0.3.5 counted it here, at 4 GB for the row
A34: Kokoro, Whisper Large-v3-Turbo, PyAnnote | B34: 3 GB | C34: Always loaded. v0.4.0 (C-06): the diarisation pipeline is pyannote speaker-diarization-community-1, replacing 3.1, which V6 probes only as a diagnostic when community-1 is refused (14.1); nothing falls back to it
A35: Orchestrator, Celery workers, Redis, Sentinel, ntfy, WG-Easy | B35: 1–2 GB
A36: CPU-side subtotal | B36: ~12 GB | C36: Inside the Arbiter's fixed 16 GiB host reserve, with transient CPU work and kernel overhead (S44, S48); the host-side consumers the reserve covers are bounded since S55 (below the table)
A37: Eleanor's resident router model, Qwen3.5-4B Q8_0, on the iGPU | B37: ~5.5 GiB | C37: Always loaded. The whole GPU resident set since v0.4.0: a 4.48 GB file (4.17 GiB), about 0.53 GiB of q8_0 KV at 4 × 8k and its compute buffers (INFERRED until the Arbiter measures the set at startup). Classification only: Eleanor's own persona work runs on GLM-5.3-Flash (P-10)
A38: Qwen3-Embedding-4B and Qwen3-Reranker-4B Q8_0, on the CPU | B38: ~9.6 GiB | C38: Always loaded (D-14 (e), D-45 (a), C-02, C-03), replacing the bge pair. Two 4.28 GB files (2 × 3.99 GiB), each with about 0.30 GiB of q8_0 KV at 4,096 tokens and a 0.5 GiB compute allowance: 9.57 GiB projected (INFERRED). They run with --device none, so the GPU memory counter never shows them; the Arbiter charges each unit its weights' bytes in full (they stay file-backed pages the kernel may drop and re-read, so VmRSS can show less than the file) plus its measured anonymous memory (RssAnon + RssShmem of the unit's main process: the KV cache and compute buffers), never below this projection, which stands in while a unit cannot be measured: the host resident set. The host-reserve warning (S44) looks past only that anonymous share, since clean file pages count as available; atlas-admin arbiter status applies the same rule. T-15 measures their real host footprint and their throughput on the CPU against the iGPU (to-do)
A39: Withheld from engines | B39: ~31 GiB | C39: The 16 GiB reserve, the GPU resident set (~5.5) and the host resident set (~9.6). v0.3.5 withheld about 22 to 24 GiB: the reserve and a GPU set of 6 to 8 GiB with the bge pair on the iGPU
A40: Usable for engines | B40: ~156 GiB (expected) | C40: The memory pool minus what is withheld above (v0.3.5 said ~164 GiB; v0.3.4 said ~180 GB minus ~17 GB, ~170 GB). The Arbiter computes it in GiB as the smaller of the GTT total and MemTotal (kernel 7.0.0-38 reports the requested 192 GiB, more than the node has; S47), minus the GPU resident set it measures (the router alone since v0.4.0, about 5.5 GiB), minus the host resident set (the CPU retrieval pair, about 9.6 GiB, D-14 (e)), minus a fixed 16 GiB reserve for the CPU-side rows above (about 12 GB) plus transient CPU work and kernel overhead, which the GPU memory counter never sees (v0.3.5, S44, S48). MemTotal is the real limit, every page of it able to hold GTT memory, because Phase 1 step 4 also puts kho=off on the kernel line (S49): with kexec handover on, as Ubuntu's 7.0 kernel has it by default, about 12 to 14 GiB of MemTotal (about 13 expected, INFERRED) would be CMA scratch that GTT pages can never use, so the pool would overstate what engines can get by that much and the largest seats would likely fail for want of memory in Phase 3 although the Arbiter granted them; V3a fails while any of it is set aside, and kho=off leaves MemTotal itself unchanged. MemTotal is expected near 187 to 188 GiB once Phase 1 step 4 has removed the 4.25 GiB crash-kernel reservation that kdump-tools puts on the kernel line (192 GiB less the UMA carve-out, 512 MiB at the BIOS minimum of 3.2, the kernel's page map of about 3 GiB and about 0.5 GiB of firmware and kernel; an estimate until V3a records the real figure, S48). The budget is then (187 to 188) − 5.5 − 9.6 − 16 = about 155.9 to 156.9 GiB, about 156 GiB expected (INFERRED). The largest Day 1 seat, GLM-5.3-Flash at 155.05 GiB projected, fits while MemTotal is at least 155.05 + 16 + 5.5 + 9.57 = about 186.1 GiB, which leaves 0.9 to 1.9 GiB to spare; DeepSeek-V4-Flash-0731 at 153.64 GiB needs about 184.7 GiB and leaves 2.3 to 3.3 GiB (table below). With the reservation still in place MemTotal would be about 183 to 184 GiB, below both thresholds (183.5 GiB refuses both seats), so V3a fails on any reserved crash-kernel memory. Every figure in the table below is measured against this budget, not against the raw 192 GB. VERIFY V3 on first boot before anything depends on it
A41: v0.4.0 (D-14 (e), D-31, D-32, approved by the Principal on 2026-10-16): the router is the whole GPU resident set (about 5.5 GiB); the Qwen3 embedder and reranker run on the CPU and the Engine Arbiter charges them as a host resident set of their own (about 9.6 GiB projected; once running, their weights in full plus their measured anonymous memory, never below the projection); every engine is budgeted from the exact bytes of its files, and one LLM seat runs alone in what is left, about 156 GiB expected. The Arbiter budgets from min(GTT total, MemTotal) and keeps the 16 GiB host reserve for what the GPU memory counter never sees (v0.3.5, S44, S48, S49): the CPU-side rows (about 12 GB) plus transient CPU work and kernel overhead. The fit needs MemTotal near its expected 187 to 188 GiB, which holds only because Phase 1 step 4 removes the 4.25 GiB that kdump-tools reserves for a crash kernel (S48) and puts kho=off on the kernel line (S49), V3a proving both; with the reservation in place neither Day 1 seat fits. ATLAS_ARBITER_HEADROOM_GIB in orchestrator.env changes the reserve and ATLAS_ARBITER_MAX_RESIDENT the seat limit (default 1). Each chat llama-server's host-RAM prompt cache and its context checkpoints sit outside the budget; since S55 (approved by the Principal on 2026-10-17) every engine has an explicit --cache-ram (4096 MiB for chat and vision, 1024 for the router, 0 for the CPU pair, so at most 5 GiB for the router and one seat where the 8 GiB default allowed 16), /tmp is capped at 4 GiB, the Celery cpu worker runs at most 8 children, Kokoro, speaches and Docling are capped, and the out-of-memory killer takes background work first. Phase 3 measures the caches and raises the to-do cache-ram (S52), which asks whether to change a cap.
A43: What each Day 1 seat takes, run alone (4.1, v0.4.0)
A44: Seat, run alone | B44: Projected footprint | C44: Verdict
A45: GLM-5.3-Flash UD-IQ4_XS with its glm5v mmproj (157.95 GB = 147.10 GiB of files), 8 × 32k, f16 KV | B45: 155.05 GiB: weights 147.10, KV 4.81, recurrent state 1.14, compute buffers 2.0 | C45: Fits, with 0.9 to 1.9 GiB to spare: the thinnest margin of the set. It is refused if the GPU resident set exceeds about 6.4 GiB at a MemTotal of 187 GiB, or if MemTotal is below about 186.1 GiB. Relief, in order: Phase 3's measured footprint replaces the projection (4.2 rule 1); fewer GLM slots (D-48, 4.3); a q8_0 cache if T-04 allows it (2.25 GiB less); a smaller reserve once host use has been measured. The to-do kv-estimates carries the measured figures for the Principal's decision
A46: DeepSeek-V4-Flash-0731 UD-Q8_K_XL (161.87 GB = 150.75 GiB), 1 × 131,072, f16 KV | B46: 153.64 GiB: weights 150.75, KV 0.84, per-slot state 0.04, compute buffers 2.0 (the q8_0 rung: 153.24) | C46: Fits, with 2.3 to 3.3 GiB to spare. Before D-31 the 161.87 GB file was read as 161.87 GiB and refused. The register's "about 13 GiB" of room (D-11) assumed the bge pair on the iGPU; with the CPU pair resident the room is this. Should Phase 3 find it short (T-06), the relief order is: stop the reranker, which has no Day 1 caller (about 4.8 GiB); cut the context; fall back to UD-Q4_K_XL (155.10 GB = 144.44 GiB, D-11 (b)). *S56 (T-06):* a decode below the 4 tok/s floor with clean placement lines also brings in UD-Q4_K_XL (5.1, 9.1). Its native 1,048,576-token window does not fit (6.72 GiB of f16 KV)
A47: gpt-oss-120b F16-trunk GGUF, native MXFP4 experts (65.37 GB = 60.88 GiB), 8 × 32k, q8_0 KV | B47: 68.29 GiB: weights 60.88, KV 4.78, sliding-window cache 0.63, compute buffers 2.0 | C47: Fits, with about 88 GiB to spare that stays unused: it runs alone like every seat (4.2 rule 3). The fast utility and the fallback floor every seat can use (D-12, D-40)
A48: v0.3.5's two-engine pairings (142 GB and 126 GB) and the everyday text-and-vision pair | B48: — | C48: Withdrawn (D-32 (a), S-22): one LLM seat is resident at a time, and vision runs on the GLM unit itself (D-20 (a)). Nemotron 3 Super, Qwen3.5-122B, Qwen2.5-VL-72B and Meditron leave the Day 1 roster (D-13, D-21)
A49: One LLM seat is resident at a time (D-32 (a); C30 on sheet 2 supersedes C26); exactly one generation runs, everywhere, Celery jobs included. Every figure is the Arbiter's own projection at the profile engines.json renders, INFERRED until Phase 3 measures it (to-dos kv-estimates and cache-ram). GLM-5.3-Flash has the thinnest margin, 0.9 to 1.9 GiB; its relief order is in its row. The gpt-oss-120b-abliterated entry is unchanged by this revision.
