Workbook

Sheet Summary
A1: A.T.L.A.S. Action Register
A2: Every open action and recommendation from the research of 13 to 15 October 2026 (the roster refresh, the specialist LLM arsenal and the Lucebox study) and the items still open in the baseline v0.3.5, for the Principal's response. Nothing in the repository has been changed; the structure is amended only after this workbook is returned.
A4: How to use this workbook
A5: 1. Each sheet lists items with the recommendation in the blue column. The yellow cells are yours: Your response (dropdown), Your choice or alternative, and Your comments. Do not edit the other cells.
A6: 2. Your response: Approve (take the recommendation as written), Approve with changes (write the change in the next cell), Reject, Defer (decide later), Need more info (say what you need). Sheet 6 also offers Done.
A7: 3. Work sheet 1 (Decisions) first. Sheets 2 to 4 follow from it, and sheet 5 lists the document, script and workbook amendments that each approved decision would trigger, citing the decision IDs it depends on.
A8: 4. Sheet 7 lists the measurements on the node that settle the open quality questions; approving a test adds it to the Phase 3 test plan.
A9: 5. Speeds and quality figures are projections or full-precision results until the node measures them. Sources are the reports and notes under reports/ and research_notes/ in the repository.
A10: 6. The progress table below updates as you answer. Return the workbook when done; each approved structure change is then made, checked and committed.
A12: Example of a completed row (illustration only, not an item)
A13: ID | B13: D-00
A14: Item | B14: Move the llama.cpp pin to a newer release
A15: Recommendation | B15: Move to v0.6.0 with an output-parity test
A16: Your response | B16: Approve with changes
A17: Your choice or alternative | B17: v0.6.0, not b11474
A18: Your comments | B18: Run the parity test on gpt-oss-120b before the other engines
A20: Progress
A21: Sheet | B21: Items | C21: Approve | D21: Approve with changes | E21: Reject | F21: Defer | G21: Need more info | H21: Done | I21: Answered | J21: Outstanding
A22: 1 Decisions | B22: =COUNTA('1 Decisions'!$A$5:$A$68) -> 64 | C22: =COUNTIF('1 Decisions'!$J$5:$J$68,"Approve") -> 0 | D22: =COUNTIF('1 Decisions'!$J$5:$J$68,"Approve with changes") -> 0 | E22: =COUNTIF('1 Decisions'!$J$5:$J$68,"Reject") -> 0 | F22: =COUNTIF('1 Decisions'!$J$5:$J$68,"Defer") -> 0 | G22: =COUNTIF('1 Decisions'!$J$5:$J$68,"Need more info") -> 0 | H22: =COUNTIF('1 Decisions'!$J$5:$J$68,"Done") -> 0 | I22: =COUNTA('1 Decisions'!$J$5:$J$68) -> 0 | J22: =B22-I22 -> 64
A23: 2 Named models | B23: =COUNTA('2 Named models'!$A$5:$A$16) -> 12 | C23: =COUNTIF('2 Named models'!$I$5:$I$16,"Approve") -> 0 | D23: =COUNTIF('2 Named models'!$I$5:$I$16,"Approve with changes") -> 0 | E23: =COUNTIF('2 Named models'!$I$5:$I$16,"Reject") -> 0 | F23: =COUNTIF('2 Named models'!$I$5:$I$16,"Defer") -> 0 | G23: =COUNTIF('2 Named models'!$I$5:$I$16,"Need more info") -> 0 | H23: =COUNTIF('2 Named models'!$I$5:$I$16,"Done") -> 0 | I23: =COUNTA('2 Named models'!$I$5:$I$16) -> 0 | J23: =B23-I23 -> 12
A24: 3 Persona allocation | B24: =COUNTA('3 Persona allocation'!$A$5:$A$22) -> 18 | C24: =COUNTIF('3 Persona allocation'!$K$5:$K$22,"Approve") -> 0 | D24: =COUNTIF('3 Persona allocation'!$K$5:$K$22,"Approve with changes") -> 0 | E24: =COUNTIF('3 Persona allocation'!$K$5:$K$22,"Reject") -> 0 | F24: =COUNTIF('3 Persona allocation'!$K$5:$K$22,"Defer") -> 0 | G24: =COUNTIF('3 Persona allocation'!$K$5:$K$22,"Need more info") -> 0 | H24: =COUNTIF('3 Persona allocation'!$K$5:$K$22,"Done") -> 0 | I24: =COUNTA('3 Persona allocation'!$K$5:$K$22) -> 0 | J24: =B24-I24 -> 18
A25: 4 Companions | B25: =COUNTA('4 Companions'!$A$5:$A$16) -> 12 | C25: =COUNTIF('4 Companions'!$I$5:$I$16,"Approve") -> 0 | D25: =COUNTIF('4 Companions'!$I$5:$I$16,"Approve with changes") -> 0 | E25: =COUNTIF('4 Companions'!$I$5:$I$16,"Reject") -> 0 | F25: =COUNTIF('4 Companions'!$I$5:$I$16,"Defer") -> 0 | G25: =COUNTIF('4 Companions'!$I$5:$I$16,"Need more info") -> 0 | H25: =COUNTIF('4 Companions'!$I$5:$I$16,"Done") -> 0 | I25: =COUNTA('4 Companions'!$I$5:$I$16) -> 0 | J25: =B25-I25 -> 12
A26: 5 Structure changes | B26: =COUNTA('5 Structure changes'!$A$5:$A$64) -> 60 | C26: =COUNTIF('5 Structure changes'!$H$5:$H$64,"Approve") -> 0 | D26: =COUNTIF('5 Structure changes'!$H$5:$H$64,"Approve with changes") -> 0 | E26: =COUNTIF('5 Structure changes'!$H$5:$H$64,"Reject") -> 0 | F26: =COUNTIF('5 Structure changes'!$H$5:$H$64,"Defer") -> 0 | G26: =COUNTIF('5 Structure changes'!$H$5:$H$64,"Need more info") -> 0 | H26: =COUNTIF('5 Structure changes'!$H$5:$H$64,"Done") -> 0 | I26: =COUNTA('5 Structure changes'!$H$5:$H$64) -> 0 | J26: =B26-I26 -> 60
A27: 6 Baseline open items | B27: =COUNTA('6 Baseline open items'!$A$5:$A$84) -> 80 | C27: =COUNTIF('6 Baseline open items'!$H$5:$H$84,"Approve") -> 0 | D27: =COUNTIF('6 Baseline open items'!$H$5:$H$84,"Approve with changes") -> 0 | E27: =COUNTIF('6 Baseline open items'!$H$5:$H$84,"Reject") -> 0 | F27: =COUNTIF('6 Baseline open items'!$H$5:$H$84,"Defer") -> 0 | G27: =COUNTIF('6 Baseline open items'!$H$5:$H$84,"Need more info") -> 0 | H27: =COUNTIF('6 Baseline open items'!$H$5:$H$84,"Done") -> 0 | I27: =COUNTA('6 Baseline open items'!$H$5:$H$84) -> 0 | J27: =B27-I27 -> 80
A28: 7 Node tests | B28: =COUNTA('7 Node tests'!$A$5:$A$37) -> 33 | C28: =COUNTIF('7 Node tests'!$F$5:$F$37,"Approve") -> 0 | D28: =COUNTIF('7 Node tests'!$F$5:$F$37,"Approve with changes") -> 0 | E28: =COUNTIF('7 Node tests'!$F$5:$F$37,"Reject") -> 0 | F28: =COUNTIF('7 Node tests'!$F$5:$F$37,"Defer") -> 0 | G28: =COUNTIF('7 Node tests'!$F$5:$F$37,"Need more info") -> 0 | H28: =COUNTIF('7 Node tests'!$F$5:$F$37,"Done") -> 0 | I28: =COUNTA('7 Node tests'!$F$5:$F$37) -> 0 | J28: =B28-I28 -> 33
A29: Total | B29: =SUM(B22:B28) -> 279 | C29: =SUM(C22:C28) -> 0 | D29: =SUM(D22:D28) -> 0 | E29: =SUM(E22:E28) -> 0 | F29: =SUM(F22:F28) -> 0 | G29: =SUM(G22:G28) -> 0 | H29: =SUM(H22:H28) -> 0 | I29: =SUM(I22:I28) -> 0 | J29: =SUM(J22:J28) -> 279
A31: Sources (in the repository)
A32: reports/ATLAS specialist LLM arsenal.md (2026-10-15) and research_notes/ATLAS specialist LLM arsenal/
A33: reports/Lucebox engine and memory hierarchy.md (2026-10-15) and research_notes/Lucebox engine and memory hierarchy/
A34: reports/ATLAS LLM roster refresh 2026.md (2026-10-13, addendum 2026-10-14) and research_notes/ATLAS LLM roster refresh 2026/
A35: docs/ATLAS_FRAMEWORK_REVIEW.md v0.3.5 and docs/ATLAS_BUILD_BASELINE.xlsx (the baseline and its workbook)

Sheet 1 Decisions
A1: Decisions
A2: Decisions the Principal must make before the structure is amended. Work this sheet first: sheets 2 to 5 depend on it.
A4: ID | B4: Area | C4: Decision required | D4: Options | E4: Recommendation | F4: Why (evidence) | G4: Priority | H4: Depends on | I4: Source | J4: Your response | K4: Your choice or alternative | L4: Your comments
A5: D-01 | B5: llama.cpp pin | C5: Move the node's llama.cpp off v0.4.1 (commit b29c606, build tag b10964, 2026-09-14), and to which build? | D5: (a) keep v0.4.1: GLM-5.3-Flash, EmbeddingGemma 2 and K2-Horizon cannot load, Flash-Next runs an incomplete Vulkan path; (b) v0.6.0 (2026-10-05): GLM (#27773), Flash-Next MTP (#29761) and hyper-connection ops (#28988), Nemotron MTP (#29018), MiMo (#29257), rerank batch fix (#28876), Vulkan fixes; (c) b11474 (2026-10-07): (b) plus EmbeddingGemma 2, K2-Horizon and GLM MTP (#29928); (d) newest b11643 (2026-10-15). | E5: (c) b11474, or (b) v0.6.0 if EmbeddingGemma 2 (b11452), K2-Horizon (b11454) and GLM MTP (b11474) are not needed. Only the arsenal report recommends a re-pin (b11474 or v0.6.0); the roster research lists what a post-pin build would add but recommends no re-pin. Adopt only after the output-parity test T-02; b11330 is the floor for Flash-Next. It changes every engine's behaviour, so it needs explicit approval. | F5: GLM-5.3-Flash, the arsenal's main engine, needs glm5-next (b11279 / v0.6.0), and under the new rules most strong candidates and several speed and retrieval fixes are post-pin. Vulkan correctness fixes after the pin include #28956 (wrong KV rows without flash attention) and FA fixes #29591 / #29988. No build yet has a llama-server TTS endpoint (PR #26603). | G5: Before any change | H5: T-02 | I5: Arsenal report Inputs L97; Arsenal CR G1 (L40-69). Roster report Addendum L126; Roster gap_closure L363, L415-L425.
A6: D-02 | B6: Top seats: precision versus quality | C6: Which engine leads the top seats: GLM-5.3-Flash at a lossy 4-bit rung, or DeepSeek-V4-Flash-0731 at a lossless rung? | D6: (a) GLM-5.3-Flash UD-IQ4_XS 156.82 GB / 146.05 GiB (KLD 0.117, 88.2% top-1) for its board lead; (b) DeepSeek-V4-Flash-0731 UD-Q8_K_XL 161.87 GB / 150.75 GiB (bit-exact) and accept the lower index score; (c) decide per seat after the node KLD run. | E6: (c): run the KLD test T-03 first; meanwhile professional-knowledge and long-context seats default to GLM, and reasoning and Apex seats to the lossless V4-Flash. | F6: GLM leads in-envelope (AA 41.8 vs 34.3; LegalBench 83.93%, Finance Agent v2 57.85%, MedScribe 88.94%, AA-LCR 80.0), but every board score is full precision, and hard reasoning amplifies quantisation loss 3-10x (a 3.5-bit GLM lost 1.4 MMLU-Pro and 4.9 maths points). The roster research rejected GLM as 3-bit only (UD-Q3_K_XL 147.54 GB); the arsenal research found the IQ4_XS rung and governs LLM seats. | G6: Before any change | H6: D-01 (GLM cannot load at v0.4.1); T-03 | I6: Arsenal report Inputs L96, quantisation rule L72. Roster report L35, L56, L86.
A7: D-03 | B7: Licence: Qwen3.8-Flash-Next | C7: Accept the Qwen Community License 1.0 for Qwen3.8-Flash-Next? | D7: (a) accept; (b) reject and drop Flash-Next (runner-up for Ren and Victor, Deep Think third opinion). | E7: (a) accept: internal use is exempt. | F7: Flash-Next is AA 39.8 (second of the twelve) and its UD-Q6_K_XL (169.17 GB / 157.55 GiB) is KLD 0.0271 against 0.0266 for its own Q8_0. Both research rounds read the licence. | G7: Before any change | I7: Arsenal report Inputs L98, verdict row 7 (L48). Roster report Addendum L130.
A8: D-04 | B8: Licence: Nemotron 3 Super | C8: Accept the NVIDIA Nemotron Open Model License for Nemotron 3 Super? | D8: (a) accept; (b) reject and drop Nemotron 3 Super (long-context utility, long-document runner-up). | E8: (a) accept. | F8: Licence text (2025-12-15): commercial use and derivatives allowed, no claim on outputs, no safety or acceptable-use clause; redistribution needs the licence and an NVIDIA notice; terminates on patent or copyright litigation. engines.json L90 still marks it unverified. It also makes an abliterated Nemotron licence-compatible for private use. | G8: Before any change | I8: Arsenal report Inputs L98; Arsenal CR G5 (L134-141). Roster gap_closure L403-L413.
A9: D-05 | B9: Licence: OpenMDW-1.1 | C9: Accept OpenMDW-1.1 for Nemotron 3 Diarization and, if chosen, the Nemotron-3-Embed-8B embedder? | D9: (a) accept; (b) reject: keep pyannote (community-1) for diarisation and a Qwen3 embedder. | E9: (a) accept. | F9: Nemotron 3 Diarization is the best open diariser on the only same-harness comparison (OpenBench average DER 0.19 vs pyannote community-1 0.28); Nemotron-3-Embed-8B leads RTEB (75.45). | G9: Before any change | I9: Arsenal report Inputs L98, verdict row 12 (L53).
A10: D-06 | B10: Uncensored: Mistral Large 2 Uncensored | C10: Reject the named Ollama build gdisney/mistral-large-uncensored? | D10: (a) reject; (b) reject it but admit the weight-edited XORTRON (2411 Heretic) Q8_0 130.28 GB / 121.33 GiB at about 1.7 tok/s; (c) admit the named Q4_0 build 69.08 GB / 64.34 GiB. | E10: (a) reject; (b) only if the Principal wants the Mistral lineage and accepts about 1.7 tok/s. | F10: The artefact is stock Mistral-Large-2407 at legacy Q4_0 plus a system prompt that instructs misinformation, under the research and non-commercial MRL licence; stock 2411 already scores UGI W/10 7.5 with no prompt. Mistral Large 3 (Apache 2.0) fits only at 1 bit (UD-TQ1_0 157.03 GiB). | G10: Before any change | I10: Arsenal report Inputs L98, L100, verdict row 6 (L47); Arsenal CR G6 (L143-151).
A11: D-07 | B11: Uncensored: Valerie's default engine | C11: Which uncensored engine is Valerie's default for cyber and AEGIS work (Alaric shares it)? | D11: (a) MiMo-V2.6-Flash uncensored (dealignai RL-UNCENSORED, AliceThirty MXFP4 168.42 GB / 156.85 GiB, MIT, about 18 tok/s); (b) gpt-oss-120b Derestricted Q8_0 124.30 GB / 115.76 GiB (Apache 2.0, about 37-39 tok/s projected); (c) keep the current huihui/noctrex gpt-oss file (the roster research's choice). | E11: (a) MiMo uncensored, after the re-pin and the load test T-09; (b) is the fallback. | F11: Its base leads Vals CyberBench among open models (75.36%), and it is the only large 2026 uncensored build with published retention (MMLU 83.41% vs base 83.56%; HarmBench compliance 99.69%, thinking off). It fits with about 7 GiB spare only if companions do not cut the ~164 GiB budget (D-14). Contradiction: the roster research says MiMo needs a pin after 2026-09-22 (#29257); the arsenal review (C6) found the mimo2 runtime already in v0.4.1 and only the converter later, so loading at the pin is plausible but untested. | G11: Before any change | H11: D-01; T-09; T-10 | I11: Arsenal report Inputs L99, uncensored L82; Arsenal CR G4 (L123-128), C6 (L235). Roster report L38; Roster gap_closure L378, L463.
A12: D-08 | B12: Uncensored: explicit-override seat | C12: Which build serves the explicit-override uncensored seat behind Ren's and Arthur's uncensored prefixes? | D12: (a) ArliAI gpt-oss-120b Derestricted Q8_0 124.30 GB / 115.76 GiB; (b) Derestricted MXFP4_MOE (gghfez) 63.39 GB / 59.03 GiB; (c) keep the current huihui v2 / noctrex MXFP4_MOE file; (d) abliterated Qwen3.5-122B-A10B Q8_0 129.87 GB / 120.95 GiB (mradermacher or wangzhang v2; the roster research's pick). | E12: (a) Derestricted Q8_0; (d) only as a second option after a node refusal and KLD check (T-10). | F12: Derestricted raises UGI NatInt above base (35.70 vs 33.68) where the huihui abliteration fell to 16.72; Apache 2.0; a Q8_0 of the edited BF16 keeps the edited experts near BF16, while re-quantising to MXFP4 adds fresh error. The 122B builds have no refusal or quality data (Heretic and huihui cost KLD about 0.06 on Qwen3.5-27B), and the arsenal governs LLM seats. | G12: Before any change | H12: D-21 (Qwen3.5-122B kept or not); T-10 | I12: Arsenal report Inputs L99, uncensored L82; Arsenal CR G4 (L118-122). Roster report L80, L110, Addendum L140; Roster gap_closure L392.
A13: D-09 | B13: Uncensored: retire the current abliterated file | C13: Retire the node's current abliterated engine (huihui v2 -> noctrex MXFP4_MOE, key gpt-oss-120b-abliterated, 63.39 GB / 59.03 GiB)? | D13: (a) retire it and remove it from the Phase 3 pull; (b) keep it only until a replacement passes a node test (the roster research's choice); (c) keep it as a standing fallback. | E13: (a) retire it; (b) would pull 63 GB only to benchmark a file the arsenal does not use. | F13: No provenance card and no refusal, KL or benchmark data, and huihui's source repositories now return HTTP 401. The Heretic alternatives are worse than Derestricted (kldzj v2 KL 0.53 with 22/100 refusals; v1 0.92). | G13: Before any change | H13: D-07; D-08 | I13: Arsenal report Inputs L99, uncensored L82, verdict row 10 (L51). Roster report L80, L108, Addendum L140; Roster gap_closure L349, L393, L455.
A14: D-10 | B14: Persona and agent allocation map | C14: Adopt the per-persona allocation (sheet 3) as the new engine map? | D14: (a) adopt as given: GLM-5.3-Flash for Ren, Gideon, Silas, Helena, Victor, Minerva (primary), vision and long documents; V4-Flash for Arthur and the Apex; MiMo uncensored for Valerie and Alaric; Qwen3.5-4B for Eleanor; (b) adopt with seat changes the Principal names; (c) defer until the node tests. | E14: (a), with GLM's seats provisional until the KLD run T-03. | F14: GLM is the measured leader wherever a professional board exists, and under sequential operation every seat gets the full ~164 GiB, so co-residency no longer justifies a smaller engine for Ren; the cost is the 4-bit rung and the re-pin. It replaces gpt-oss-120b (Corporate) and Nemotron (Estate) as defaults (D-12, D-13). | G14: Before any change | H14: D-01; D-02 | I14: Arsenal report allocation L13-34. Roster report core seats L66-L67.
A15: D-11 | B15: Apex / TF_OMEGA engine and rung | C15: Keep DeepSeek-V4-Flash-0731 as the Apex / TF_OMEGA engine and move it from UD-Q4_K_XL to the lossless UD-Q8_K_XL? | D15: (a) UD-Q8_K_XL 161.87 GB / 150.75 GiB, bit-exact on all 1,328 tensors (unsloth/DeepSeek-V4-Flash-0731-GGUF); (b) keep UD-Q4_K_XL 155.10 GB / 144.44 GiB (KLD 0.0102, 96.28% same top token, about 11 tok/s); (c) GLM-5.3-Flash UD-IQ4_XS (AA 41.8, lossy) if the KLD run favours it; (d) K2-Horizon-375B IQ3_XXS 150.81 GiB (AA 31, needs b11454). | E15: (a) until the KLD run decides, with the fit confirmed by the Phase 3 KV measurement T-06. The arsenal, roster and Lucebox reports agree. | F15: Bit-exact, HLE 38.6, GPQA 90.8; the dsv4 cache is about 6,880 B/token, so UD-Q8_K_XL leaves about 13 GiB of ~164 GiB, not the 2 GiB Section 5.1 states (it read 161.9 GB as GiB and used the Arbiter's 327,680 B/token). No UD-Q6_K_XL exists, and unsloth/DeepSeek-V4-Flash-GGUF holds the preview, not 0731. Decode about 7 tok/s on mainline Vulkan (a floor; in-pin kernels unmeasured). | G15: Before any change | H15: D-02; T-03; T-06 | I15: Arsenal report TF_OMEGA row L28, what changed L88; Arsenal CR C1 (L230). Roster report L68, L86, Addendum L128, L136. Lucebox report Inputs row 1 (L392).
A16: D-12 | B16: gpt-oss-120b role | C16: Confirm dropping gpt-oss-120b as the Corporate default (Ren, Helena, Victor, Gideon, Minerva) and demote it to a fast utility, drafting and Sentinel-escalation engine? | D16: (a) demote; (b) keep it as the default resident engine (Section 6.3; the roster research's recommendation); (c) promote Qwen3.5-122B-A10B Q8_0 to the default (the roster's no-download fallback). | E16: (a) demote, and take the seat engines from D-10. | F16: AA 11.6 makes it a speed engine, not a quality seat; its 63.39 GB (59.03 GiB) earned the default only under co-residency, which the run-alone directive removes. It stays lossless at native MXFP4 and the fastest engine: 57-60 tok/s projected by the arsenal, 53.8-55.6 measured on 128 GB boxes (roster). | G16: Before any change | H16: D-10 | I16: Arsenal report directives L7, verdict row 9 (L50), what changed L88. Roster report L66, L82, Addendum L134.
A17: D-13 | B17: Nemotron 3 Super role | C17: Confirm dropping Nemotron 3 Super Q8_0 as the Estate default (Arthur, Silas, Alaric) and keep it as a long-context utility? | D17: (a) keep it as the Estate default (the roster research's recommendation); (b) Arthur to DeepSeek-V4-Flash-0731 UD-Q8_K_XL, Nemotron kept as long-context utility and long-document runner-up; (c) keep it as default for Silas and Alaric only. | E17: (b). | F17: AA 12.8 against 34.3 for V4-Flash, its card discloses an HLE/GPQA contamination risk, and it has no MTP at the pin (#29018). It earns a place by a 1M-token context at tiny KV (about 44 GiB spare) and calibrated refusals (RefusalBench 0.4% benign refused, 89.3% of should-refuse refused). Its Q8_0 is 128.47 GB / 119.65 GiB, not 120-123 GB. | G17: Before any change | H17: D-10; T-12 | I17: Roster report L67, L84; Roster gap_closure L380, L418, L451. Arsenal report verdict row 8 (L49).
A18: D-14 | B18: Companion residency versus engine budget | C18: Where do the upgraded retrieval companions live, given that every GiB resident on the iGPU comes off every engine's budget? | D18: (a) Qwen3-Embedding-8B + Qwen3-Reranker-8B resident (7.49 + 7.49 GiB; budget about 150 GiB); (b) the 4B pair resident (about +6.7 GiB; budget about 157 GiB); (c) 8B embedder + 4B reranker (about +10.2 GiB); (d) load the retrieval pair on demand; (e) run it on the CPU; (f) keep bge-m3 + bge-reranker-v2-m3 (1.3 GiB) until the engine set is fixed. | E18: Choose companions and LLM rungs together. If MiMo stays Valerie's default (D-07) and Flash-Next stays at UD-Q6_K_XL, take (d) or (e); otherwise (b), the 4B pair the roster research named only as its alternative (its first pick, like the arsenal's, is the 8B pair (a)), with Flash-Next at UD-Q5_K_XL (D-28). Neither report sizes this fully; T-15 measures it. | F18: The Arbiter budgets pool minus the measured GPU resident set (6-8 GiB today) minus 16 GiB. At about 150 GiB, V4-Flash UD-Q8_K_XL (150.75), the 5-bit 235B-class rungs (150.76-150.84), Flash-Next UD-Q6_K_XL (157.55) and MiMo (156.85) stop fitting; at about 157 GiB Flash-Next and MiMo still do not. The 4B pair keeps most of the gain (MTEB multilingual 69.45 vs 70.58; MMTEB-R 72.74 vs 72.94; bge pair 59.56 / 58.36). A resident OCR model adds about 1.3-1.5 GiB. | G18: Before any change | H18: D-07; T-15 | I18: Arsenal CR G9 (L194-204); Arsenal report companions L84. Roster report L75, L100; Roster gap_closure L73-L75.
A19: D-15 | B19: Medical cross-check | C19: Replace Meditron-70B with Baichuan-M3-235B as Minerva's cross-check, and drop MedGemma-27B as the fallback? | D19: (a) Baichuan-M3 (mradermacher Q5_K_S 161.88 GB / 150.76 GiB, or official baichuan-inc Q4_K_M 143.78 GB / 133.91 GiB; Apache 2.0; 8-13 tok/s projected); (b) Apertus-70B-MeditronFO Q8_0 69.87 GiB (dense, about 3 tok/s); (c) keep Meditron-70B (about 74 GB, 4K context, about 3 tok/s); (d) MedGemma-27B Q8_0 28.71 GB (under the 70B floor). | E19: (a), with the rung set by D-16; drop (d). GLM stays Minerva's primary. | F19: Meditron is a 2023 Llama-2-70B continued pre-train with no instruction tuning (52.9% on an independent 2026 neurology exam, lowest of the 70B models); Apertus-MeditronFO averages 53.77. Baichuan-M3 has an official GGUF and vendor HealthBench 65.1 / Hard 44.4 (gpt-oss-120b 57.6 / 30.0) but no independent score, so T-11 checks it. | G19: Before any change | H19: D-16; T-11 | I19: Arsenal report Minerva row L23, what changed L88; Arsenal CR section 5 (L262). Roster report L71, L96, Addendum L132, L140; Roster gap_closure L390, L431.
A20: D-16 | B20: Context targets: medical and science seats | C20: What context must the medical cross-check (Baichuan-M3) and the science seat (Intern-S1) support? | D20: (a) Q5_K_S (Baichuan 150.76 GiB, Intern-S1 150.84 GiB): about 23K context after a 9 GiB allowance; (b) Q4_K_M (Baichuan official 133.91 GiB, Intern-S1 132.86 GiB) for longer context. | E20: State a target context per seat: Q5_K_S if about 20-23K tokens is enough, Q4_K_M otherwise. | F20: These Qwen3-235B-shaped engines carry about 188 KiB/token of f16 KV (192,512 B); 5-bit is near reference (+0.63-0.75% PPL), while 4-bit costs 3.7-5.0 points on AIME and GPQA. GLM, Flash-Next, Nemotron and V4-Flash reach their native windows. | G20: Before any change | H20: D-14 | I20: Arsenal report Inputs L102, quantisation table L69. Roster gap_closure L390.
A21: D-17 | B21: Science seat | C21: Add Intern-S1 as the science engine for domains 15, 35 and 36 (Minerva; Valerie with Minerva)? | D21: (a) add Intern-S1 (bartowski Q5_K_S 161.96 GB / 150.84 GiB) as an override engine; (b) leave science on GLM-5.3-Flash. | E21: (a). | F21: Vendor ChemBench 83.4, MatBench 75.0, ProteinLMBench 63.1 (no independent board); Apache 2.0; qwen3moe at the pin; 10-13 tok/s projected. It carries the Qwen3-235B lineage forward; Intern-S2-397B fits only at 2 bits. | G21: Before any change | H21: D-16 | I21: Arsenal report science row L31, what changed L88; Arsenal CR G7 (L153-166).
A22: D-18 | B22: Finance seat | C22: Add Ling-3.0-flash-Fin as Silas's finance-tuned, lossless second engine? | D22: (a) add Ling-3.0-flash-Fin Q8_0 135.63 GB / 126.32 GiB as Silas's override or second opinion; (b) GLM-5.3-Flash only. | E22: (a), with GLM kept as Silas's primary. | F22: Finance Agent v2 54.93% against GLM's 57.85%, but lossless Q8_0 inside the pin at 22.6-30.2 tok/s projected (corrected for C7; no gfx1151 measurement); MIT. LegalBench 68.74% and AA 23 make it a finance engine, not a general CFO engine. | G22: Before any change | I22: Arsenal report Silas row L20, what changed L88; verification_other_large_specialists rows 3-6.
A23: D-19 | B23: Coder seat | C23: Add a dedicated coder seat with Qwen3-Coder-Next, at which rung, and confirm dropping Qwen3.8-27B? | D23: (a) Qwen3-Coder-Next Q8_0 84.81 GB / 78.99 GiB (37-44 tok/s projected); (b) BF16 159.46 GB / 148.51 GiB (unquantised, 256K context, about 9 tok/s projected on Vulkan); (c) no dedicated seat, GLM-5.3-Flash covers coding; (d) Qwen3.8-27B Q8_0 29.05 GB co-resident (the roster research's pick, now under the 70B floor). | E23: Drop (d). (a) if a dedicated seat is wanted; (b) only if unquantised weights are worth a fourfold speed loss; otherwise (c). | F23: Coder-Next is just above the floor (79.7B total, 3B active) and inside the pin; vendor SWE-bench Verified 70.6-71.3 and Aider polyglot 66.2, but AA 9.24, and GLM beats it on SWE-bench (92%, Vals). Fixed-harness runs put open models 15-20 points below vendor tables. Its Apache 2.0 rests on the card (LICENSE file missing). The arsenal table lists BF16, its verdict calls Q8_0 practical. | G23: Before any change | I23: Arsenal report coder row L32, verdict row 4 (L45), quantisation table L67. Roster report L70, L90, Addendum L128, L134; Roster gap_closure L61-L63, L412.
A24: D-20 | B24: Vision engine | C24: Which engine becomes the single vision engine now that it need not pair, and is the co-resident light vision tier dropped? | D24: (a) GLM-5.3-Flash + glm5v mmproj (UD-IQ4_XS + 0.65 GB; needs the re-pin); (b) Qwen3-VL-235B Q5_K_S 161.88 GB / 150.76 GiB + 1.16 GB mmproj (at the pin); (c) Flash-Next UD-Q6_K_XL + 0.62 GB mmproj; (d) Qwen3.5-122B-A10B Q8_0 + mmproj-BF16 (the roster's at-pin pick); (e) keep Qwen2.5-VL-72B Q8_0 79 GB; (f) a 27-31B co-resident light tier (Qwen3.8-27B or Gemma 4 31B, under the 70B floor). | E24: (a) after the re-pin, (b) if the pin stays at v0.4.1; drop (e) and (f). A small OCR companion (C-04) transcribes scanned documents. | F24: GLM is LMArena vision #23 (top open) and Vals MMMU 86.01%, and on its own unit vision costs no swap while GLM is resident; Qwen3-VL-235B is OmniDocBench 89.78; Qwen2.5-VL-72B is MMMU 70.2 at about 3 tok/s. The light tier existed only to pair with gpt-oss (Qwen3.8-27B 29.05 GB, Gemma 4 31B 32.64 GB; MMMU-Pro 76.3 / 73.4). | G24: Before any change | H24: D-01; T-17 | I24: Arsenal report vision row L29, what changed L88; Arsenal CR G3 (L93-104). Roster report L72, L88, L98, Addendum L134; Roster gap_closure L430, L444.
A25: D-21 | B25: Engines leaving the core set | C25: Retire Qwen2.5-VL-72B, Meditron-70B and Qwen3.5-122B-A10B from the roster and the Phase 3 pull? | D25: (a) retire all three: vision to D-20, cross-check to Baichuan-M3, long documents to GLM (Nemotron Q8_0 runner-up); (b) keep Qwen3.5-122B-A10B Q8_0 MTP build (132.55 GB / 123.45 GiB) + mmproj as an at-pin long-document and vision fallback until GLM runs on an approved pin (the roster research's pick); (c) keep any of them on disk as a fallback. | E25: (a). | F25: None is in the arsenal's ten-engine set, and their seats are reassigned (GLM AA-LCR 80.0, MRCR 128K 62.9). Qwen3.5-122B scores AA 16 against GLM's 41.8, and the arsenal covers the at-pin case with Qwen3-VL-235B (vision) and Nemotron (1M context). Retiring the 72B (79 GB) and Meditron (74 GB) also removes the gpt-oss + vision pairing. The arsenal report does not name Qwen3.5-122B; its retirement is inferred from the allocation. | G25: Before any change | H25: D-10; D-15; D-20 | I25: Arsenal report allocation L29-30, sequential L78, what changed L88. Roster report L69, L71, L72, L88, L96, L98; Roster gap_closure L374, L384, L430. FRAMEWORK_REVIEW 19 D10, D12.
A26: D-22 | B26: Deep Think engine pair | C26: Replace the gpt-oss-120b generator and Nemotron adversary with a two-family GLM-5.3-Flash + DeepSeek-V4-Flash-0731 pair, Flash-Next as third opinion? | D26: (a) GLM and V4-Flash (Ren's and Arthur's engines), Flash-Next third opinion; (b) any two families among GLM, V4-Flash, MiMo and Flash-Next; (c) keep the baseline pair. | E26: (a). | F26: Diversity comes free under sequential operation: two architectures and two training recipes for only swap latency (about 50-85 s per swap). AA HLE 39.9 / 38.6 and GPQA 91.2 / 90.8. | G26: Before any change | H26: D-10 | I26: Arsenal report Deep Think row L27, allocation points L34.
A27: D-23 | B27: Default resident engine and batching | C27: Batch queued work by engine and keep the most-used engine (GLM-5.3-Flash) resident by default? | D27: (a) adopt: route a hemisphere's or persona's queued work to the resident engine before swapping, GLM resident by default; (b) keep gpt-oss-120b resident by default (Section 6.3). | E27: (a). | F27: A resident 145-160 GiB engine leaves only about 10-25 GiB of page cache, so switching between two large engines is a full cold read (25-70 s; 50-85 s per swap realistic); fast engines (gpt-oss-120b 63.39 GB / 59.03 GiB, Nemotron 3 Super Q8_0 128.47 GB / 119.65 GiB) recover page cache. | G27: Before any change | H27: D-10; T-14 | I27: Arsenal report sequential L76-78.
A28: D-24 | B28: Slow dense engines and 3-bit rungs | C28: Exclude dense 70-123B engines and 3-bit-only engines from the primary arsenal? | D28: (a) exclude both classes; (b) admit a dense uncensored Mistral (XORTRON Q8_0) only on explicit request; (c) admit 3-bit engines (Llama 4 Maverick, Qwen3.5-397B UD-IQ3_XXS, K2-Horizon-375B IQ3_XXS, GLM-4.x). | E28: (a); (b) only if the Principal wants that lineage and accepts about 1.7 tok/s. | F28: Dense Mistral Large / XORTRON, Mistral Medium 3.5, Devstral 2 and Kimi-Dev decode at about 1.7-3.3 tok/s; 3-bit rungs sit in the risky band (KLD about 0.03-0.18, about 5 maths points lost). Intern-S2-397B fits only at 2 bits, Mistral Large 3 only at 1 bit, and Mistral Small 4 runs its experts on the CPU at the pin (0.82 tok/s). | G28: Before any change | I28: Arsenal report Inputs L100; Arsenal CR G6, G7 (L143-166). Roster report L37, L41, L52; Roster gap_closure L375, L379.
A29: D-25 | B29: Baseline revision type | C29: Is the arsenal change recorded as a new baseline version that reopens closed decisions D4, D10 and D12 and supersedes C23, C25 and C26, or as Section 23 S-rows only? | D29: (a) v0.4.0 with new D-rows from D16, new C-rows from C28 and one S54 row for the script corrections; (b) v0.3.6 with S-rows only. | E29: (a). | F29: Section 23 defines S-rows as corrections of literals that reopen no decision, while the arsenal replaces the D4 retrieval models, the D10 vision engine, the D12 Meditron inclusion and the C23, C25 and C26 resolutions. The header still reads 'Closed build baseline'. | G29: Before any change | I29: FRAMEWORK_REVIEW L11, L1142, C23-C26 L996-L999, D4-D12 L1011-L1019.
A30: D-26 | B30: Day 1 scope of the change | C30: Does the amended structure go into Day 1, or does Day 1 run on the v0.3.5 roster and migrate afterwards? | D30: (a) amend everything before Day 1; (b) run Day 1 on v0.3.5 and migrate after; (c) amend the pin, roster, residency rule, Arbiter units and Phase 3 list before Day 1, and phase the specialist seats, slot save/restore, swap batching, the speech and image companions and the V4.1 trial after Day 1. | E30: (c). | F30: Nothing has been executed. v0.3.5 would pull about 690 GB (about 15 h at 100 Mbps), of which Qwen2.5-VL-72B (79 GB), Meditron-70B (74 GB) and the abliterated file (63 GB) are to be retired, and V21 would prove a pair production no longer runs; the orchestrator features are not needed to bring the node up. | G30: Before any change | H30: D-25 | I30: FRAMEWORK_REVIEW 17 Phase 3 step 1 (L945), 21 V21 (L1085); Arsenal report Inputs.
A31: D-27 | B31: Workbook builder in the repository | C31: Commit the builder that produces docs/ATLAS_BUILD_BASELINE.xlsx to the repository before the amendment? | D31: (a) commit it beside scripts/day1/tools/fill-workbook.py; (b) keep it outside the repository. | E31: (a). | F31: The builder exists only in a session scratchpad (r54/build.py); every baseline change since v0.3.4 rebuilt the workbook from it, and this change touches at least eleven of its fifteen sheets. | G31: Before any change | H31: D-25 | I31: scratchpad r54/build.py L207-L245; docs/ATLAS_BUILD_BASELINE.xlsx (15 sheets).
A32: D-28 | B32: Qwen3.8-Flash-Next file | C32: Which Qwen3.8-Flash-Next file is pulled? | D32: (a) unsloth UD-Q6_K_XL 169.17 GB / 157.55 GiB (KLD 0.0271), about 6.5 GiB left for KV; (b) ggml-org Q8_0 162.62 GB / 151.46 GiB: its header is already read (per_layer_token_embd, the n-gram table, at Q4_0 = 28.80 GB; every other matrix Q8_0), so only its KLD is unmeasured (T-08); (c) unsloth UD-Q5_K_XL 158.29 GB / 147.42 GiB, more room for context and companions; (d) do not adopt it. The unsloth Q8_0 (188.23 GB / 175.30 GiB) does not fit. | E32: (a), unless T-08 shows the ggml-org Q8_0 is near-lossless; (c) if D-14 or a long context leaves no room for (a). | F32: UD-Q6_K_XL matches its own Q8_0 (KLD 0.0271 vs 0.0266); the roster research had found no in-budget file meeting the precision rule. AA 39.8, GPQA 92.3, Terminal-Bench 2.1 86.1. MTP (#29761) and the Vulkan hyper-connection ops (#28988) are post-pin: measured only at UD-IQ4_XS on 128 GB Ryzen AI Max+ 395 boxes: 26.9-27.2 tok/s without MTP (the roster infers v0.4.1 gets this) and 41.3 with MTP on PR #28243 fork builds; nothing is measured at UD-Q6_K_XL (23-29 tok/s projected). | G32: Before Day 1 | H32: D-01; D-03; D-14; T-08 | I32: Arsenal report verdict row 7 (L48). Roster report Addendum L126, L128, L130, L136; Roster gap_closure L373, L374, L396.
A33: D-29 | B33: KV cache precision for every seat | C33: Which KV cache type does each seat run under the less-quantisation rule, including the Apex ladder? | D33: (a) f16 where the cache is cheap (GLM 19,712 B/token, V4-Flash about 6,880 B/token), q8_0 elsewhere, q4_0 nowhere; the Apex ladder keeps the highest-precision rung that fits its target context (f16, else q8_0); (b) keep today's split: q4_0 for gpt-oss-120b and its abliterated twin, an Apex ladder descending to a q4_0 target; (c) q8_0 everywhere. | E33: (a), approved before Day 1 with GLM's KV type provisional until T-04. | F33: q8_0 K and V is task-lossless (mean KLD 0.0018, at most 4 of 500 ARC answers changed); q4_0 on K collapsed Qwen2.5-7B from 92.0% to 24.2% on ARC, and gpt-oss-20b fell from 37.9% to 21.7% on AIME25 with a q4_0 cache even with Hadamard rotation, which MLA models such as V4 do not get (#21038). GLM at 8 x 32K in f16 needs about 4.8 GiB; GLM on Vulkan may need -fa off, which rules out a quantised cache for it. q4_0 was chosen only for co-residency headroom. | G33: Before Day 1 | H33: D-01; D-11; T-04; T-05 | I33: Roster report L21, L68, Addendum L136. Arsenal report what changed L88; Arsenal CR G2. FRAMEWORK_REVIEW 4.3 L264-L270, App B L1244; engines.json L25, L57, L147-L148.
A34: D-30 | B34: Reasoning mode per seat | C34: Which thinking or reasoning-effort setting does each LLM seat run (MiMo uncensored, GLM-5.3-Flash, DeepSeek-V4-Flash, Flash-Next, gpt-oss-120b), given that the research's quality and refusal figures depend on it? | D34: (a) each engine's vendor default, recorded in engines.json with its sampling; (b) a fixed setting per seat chosen after the refusal and KLD tests; (c) chosen per task tier by the router. | E34: Derived, no source recommends a setting: (b), recorded with the vendor sampling in each engines.json entry (S-19). Measure MiMo uncensored with thinking off and on in T-10 before fixing Valerie's mode. | F34: MiMo uncensored complies 99.69% with thinking off but 90.94% with thinking on; the stock DeepSeek-V4 UGI figure is with reasoning off; gpt-oss-120b's GPQA 80.1 is at high effort; Qwen3-Coder-Next is non-thinking only. S-19 names vendor sampling but no row decides the mode. | G34: Before Day 1 | H34: D-10; T-10 | I34: Arsenal report uncensored L82; Arsenal CR G4 (L113, L124), section 2 (L28). Roster report L82.
A35: D-31 | B35: Arbiter footprint units | C35: Should the Arbiter budget each engine from its exact file size in GiB instead of reading the decimal GB figure as GiB? | D35: (a) exact bytes from the Hugging Face tree (already read into MANIFEST.json at pull time) converted to GiB; (b) keep reading footprint_gb as GiB; (c) a hand-typed footprint_gib field per engine. | E35: (a). | F35: config.py reads footprint_gb as GiB, a deliberate 7.4% over-estimate: harmless at 63-130 GB files, binding at 150-158 GiB (about 11 GiB at 150 GiB, more than the cache margin of the large seats). MiMo (168.42 GB) and Flash-Next UD-Q6_K_XL (169.17 GB) would be projected at 168-169 GiB and refused against ~164 GiB, and V4-Flash UD-Q8_K_XL (161.87 GB) would keep about 2 GiB where it has about 13. | G35: Before Day 1 | H35: D-10 | I35: config.py L322-L331; FRAMEWORK_REVIEW 5.1 L317. Roster report L86; Roster baseline notes L149. Arsenal report allocation table.
A36: D-32 | B36: Residency under sequential operation | C36: Does the Arbiter allow exactly one LLM seat resident at a time, or keep two-engine residency where a pair happens to fit? | D36: (a) one weight-bearing LLM seat resident, the always-resident companions excluded; (b) keep MAX_RESIDENT = 2 for pairs that fit (for example gpt-oss-120b at 59 GiB beside Qwen3-Coder-Next Q8_0 at 79 GiB) and run the 300B-class seats exclusive. | E36: (a), with the residency limit made a setting so (b) can return without a code change. | F36: The directive is that every engine runs alone with the whole ~164 GiB. Every primary seat is 146-157 GiB, so a pair could form only between the two smaller utility engines, and keeping C26 would keep a V21 test and co-resident profile code for a case the map barely uses. | G36: Before Day 1 | H36: D-10 | I36: arbiter.py L11, L123, L916-L940; FRAMEWORK_REVIEW 4.2 rule 3 L252, C26 L999.
A37: D-33 | B37: Phase 3 decode gate | C37: How does V10 judge decode speed for engines whose bands are only projections, and which engine failures may defer without blocking the Phase 3 gate? | D37: (a) keep the fail below each band's lower bound, with bands re-based on the research projections; (b) gate on load, KV proof, generation and memory release, record decode against the projection, and fail only below a per-seat floor the Principal sets; (c) (b) plus a deferrable V22-style row for every post-pin architecture (GLM glm5-next, MiMo, Flash-Next). | E37: (c), with the per-seat floors set alongside the deep-tier floor (D-47). | F37: No candidate has a decode figure on the PRO 495 at any pin (GLM 12-14 projected from 17.4 at 3.84 bpw; V4-Flash UD-Q8_K_XL about 7 as a floor; Intern-S1 10-13; Baichuan-M3 8-13). The Apex band of 25-32 tok/s has no measurement behind it (only 2-3-bit runs exist, all on 128 GB Ryzen AI Max+ 395 boxes, none on the PRO 495: UD-IQ2_XXS 12.6-13.3 on stock Vulkan and 18.9 on a fork; UD-IQ3_XXS 11.9 on mainline b10488 and 18.4 on a fork), so a quality-first file would fail V10 on speed alone. R19 lets only the Apex (V22) defer today. | G37: Before Day 1 | H37: D-01; D-47 | I37: phase3-models.sh L33, L755; loadtest.py L238-L242; FRAMEWORK_REVIEW V10 L1074, V22 L1086, R19 L1039. Roster report L54; Roster gap_closure L354. Arsenal baseline item (gate policy).
A38: D-34 | B38: Licences: the rest | C38: Accept and record the remaining licences the research verified, now or with each engine? | D38: (a) accept all now and record them in Section 16.5 and engines.json; (b) accept each with its engine as it is approved. | E38: (b). Items: DeepSeek V4-Flash MIT; MiMo MIT; Ling-3.0-flash-Fin MIT; Derestricted gpt-oss Apache 2.0; Baichuan-M3 and Intern-S1 Apache 2.0; Qwen3-Coder-Next Apache 2.0 on its card only (LICENSE file missing); pyannote community-1 CC-BY-4.0 (gated); HiDream-I1's Llama 3.1 text encoder. Flash-Next, Nemotron and OpenMDW are D-03 to D-05; the MRL rejection is D-06. | F38: Verified on 2026-10-14 and 2026-10-15, while engines.json still marks Nemotron and DeepSeek unverified; MedGemma's HAI-DEF gate falls away if MedGemma is dropped (D-15). | G38: Before Day 1 | H38: D-03; D-04; D-05; D-06 | I38: Roster report Addendum L130; Roster gap_closure L403-L413. Arsenal report Inputs L98, verdict table.
A39: D-35 | B39: Licences: engines and companions not listed in D-34 | C39: Accept and record the licences of the engines and companions the register recommends but D-34 does not name, including the main engine GLM-5.3-Flash? | D39: (a) fold them into D-34 and accept each with its engine as it is approved; (b) accept all now and record them in 16.5 and engines.json. | E39: (a). Items: GLM-5.3-Flash MIT (the arsenal's main engine); Qwen3-Embedding-8B/4B and Qwen3-Reranker-8B/4B Apache 2.0; Qwen3-VL-235B Apache 2.0 (vision runner-up); OCR candidates TeleOCR, OvisOCR2 and PaddleOCR-VL-1.6 Apache 2.0, GLM-OCR MIT; Qwen3-ASR-1.7B and Qwen3-TTS Apache 2.0; Chatterbox Turbo and Multilingual V3 MIT; Z-Image-Turbo and Qwen-Image-2512 Apache 2.0; EmbeddingGemma 2 Apache 2.0 if kept (D-60). | F39: D-34 lists DeepSeek, MiMo, Ling, Derestricted, Baichuan-M3, Intern-S1, Coder-Next, pyannote community-1 and HiDream only, so the licence of the engine that carries most seats, and every new companion, has no acceptance row; S-27 and S-45 record licences only for what a decision accepts. | G39: Before Day 1 | H39: D-34 | I39: Arsenal report Inputs L98 (GLM, DeepSeek, MiMo MIT), verdict row 11 (L52). Arsenal CR section 2 (L35, EG2 Apache 2.0), G8 (L184-L188). Roster report Addendum L130.
A40: D-36 | B40: Kernel GTT line | C40: Keep the GTT and TTM kernel line as written for 192 GB, or change it before Day 1? | D40: (a) keep amdgpu.gttsize=196608 ttm.pages_limit=50331648 and let V3 and V3b validate it; (b) adopt the one published 192 GB profile, ttm.pages_limit=46137344 (176 GiB); (c) keep (a) and raise the V3b floor from 160000 MiB to the largest approved engine plus its KV. | E40: (c). | F40: No community source has qualified a 192 GB GTT profile, and AMD's footnote caps graphics memory at 160 GB (149.01 GiB). The Lucebox report, which governs hardware, finds the node's line already covers its 192 GB profile (amdgpu.gttsize=180224, about 146.5 GiB of experts in GTT). The largest candidates are 146-158 GiB files, so a Vulkan heap below about 165 GiB would shut them out. | G40: Before Day 1 | H40: T-01 | I40: Roster report L114, Addendum L138; Roster gap_closure L359, L467; FRAMEWORK_REVIEW 3.3 L123-L135. Lucebox report tier table L186, L331.
A41: D-37 | B41: Specialist seats: how they are reached | C41: Are the new specialist engines (science, finance, coder, medical cross-check) bound to directors and task forces, or to domains, and do they get Principal prefixes? | D41: (a) director override lists plus task-force presets (an engine field in task-forces.json), keeping 8.4's rule that a domain never spawns a model; (b) a domain card carries an engine and loading the card switches the engine; (c) (a) plus explicit prefixes such as [SCIENCE], [CODER] and [FIN]. | E41: (a), adding a prefix only for a seat the Principal wants to call directly. | F41: Domains are knowledge injected into the director's prompt (8.4), and every extra engine is now a 50-85 s swap plus re-prefill, so binding engines to cards could turn one three-card dispatch into three swaps. Persona files already carry default_engine and override_engines, and task-forces.json already carries an engine field for TF_OMEGA. | G41: Before Day 1 | H41: D-17; D-18; D-19; D-15 | I41: FRAMEWORK_REVIEW 8.4 L527-L535, 8.5 L539-L553; config/personas/*.md L7-L11; config/task-forces.json L358.
... A50: D-46 | B50: Apex trial: DeepSeek V4.1 Flash | C50: What role should DeepSeek V4.1 Flash (552B) have on the node? | D50: (a) leave it out; (b) evaluation-only trial outside the routed roster; (c) replace V4-Flash-0731 as the Apex engine. | E50: (b): keep 0731 as Apex (D-11) and promote V4.1 only if it beats 0731 on 30-50 private Deep Think and TF_OMEGA-style tasks scored blind by the Principal or a director (T-30). The Principal supplies approval and the task set. | F50: At full precision V4.1 leads 0731 on AA 39.46 to 34.33, mostly in agentic terminal work, but every V4.1 file that fits ~164 GiB is 2-3 bits (antirez Q2: KL 0.260, top-1 78.3%; Lucebox ROCMFP2S: KL 0.266, 77.7%), while 0731 UD-Q8_K_XL is bit-exact. The Lucebox report governs V4.1: mainline llama.cpp cannot run it (PR #28696 open) and its Q2_K needs 186.17 GiB resident, superseding the roster's Q2_K figure (a 264.52 GB / 246.35 GiB file; its body said 'even the lowest rung is 80 GiB over the budget'); 186.17 GiB is resident weights, excluding the 188.83 GiB of Engram tables read from disk. | G50: Before Day 1 | H50: T-06 (the Apex rung follows the 0731 KV measurement) | I50: Lucebox report Inputs row 1 (L392), quantisation L333-L349. Roster report L9, Addendum L128; Roster gap_closure L383, L465.
A51: D-47 | B51: Deep tier speed floor and sampling | C51: What minimum decode speed is acceptable for the deep tier, and which sampling settings should the V4.1 trial measure? | D51: (a) accept whatever V4.1 delivers; (b) set a minimum decode rate before the trial. Sampling: greedy only, or greedy and the node's temperature 1.0. | E51: (b): set a floor before the trial so its result is decisive (for example, whether 14 tok/s is usable for the longest tasks), and measure both sampling settings. The same floor sets the per-seat floors of D-33. | F51: The node samples DeepSeek at temperature 1.0, which changes draft acceptance and speed, and Lucebox's figures are greedy-only. V4.1 runs at about 14-16 tok/s on this APU; the arsenal projects 0731 at about 7 (UD-Q8_K_XL) and 11 (UD-Q4_K_XL) tok/s on mainline Vulkan; the directive puts quality first. | G51: Before Day 1 | I51: Lucebox report Inputs row 8 (L399), Risks L374, path 0 L355; engines.json L170.
A52: D-48 | B52: Slot and context profile per engine | C52: How do engines that now run alone lay out slots and context, in particular GLM-5.3-Flash, which needs --kv-unified for more than one sequence? | D52: (a) keep 8 x 32K slots without --kv-unified everywhere (not supported for GLM, #27773); (b) per-engine profile from the measured KV, with GLM on --kv-unified, 8 slots sharing one pool and the S52 window guard rewritten for a pooled window; (c) as (b) but GLM on --parallel 1 with one large context (for example 131072) and slot save/restore for other conversations; (d) --kv-unified everywhere. | E52: (b) if the parity test shows coherent output under --kv-unified, otherwise (c); set each engine after the Phase 3 kv-estimates measurement. | F52: Each slot is a hard 32K request limit, so long native windows go unused. GLM carries about seven seats, so a single slot would re-prefill each persona's stable prefix at every switch; its cache is small (19,712 B/token f16, about 0.6 GiB per 32K), so pooling is cheap. GLM slowed to about 6 tok/s by 128K context in review. | G52: Phase 3 (node test) | H52: D-01; D-02; T-02; T-04; T-05 | I52: Roster report L56, L88; FRAMEWORK_REVIEW 4.3 L275, L277; engines.py L30-L57. Arsenal report allocation table.
A53: D-49 | B53: Test sets for seats with no benchmark | C53: Will the Principal supply test sets for Australian law, HR, aviation, logistics, AEC, SCADA, game design, growth marketing, customer success and physical security / OSINT? | D53: (a) supply them; (b) accept the general leader (GLM) on those seats unproven. | E53: (a). | F53: No board, no Australian-law evaluation and no specialist above the floor exist for Victor, Alaric and those domains, and LMArena has no category for them; their quality can only be settled on the Principal's own work (T-27). | G53: After Day 1 | I53: Arsenal report allocation points L34, gaps L90; Arsenal CR G10 (L206-218). Arsenal CR section 1 (L13) for customer success and growth marketing.
A54: D-50 | B54: Phase 4 engines beside a 150 GiB seat | C54: How do image, video and other Phase 4 engines run when the resident LLM seat leaves no room beside it? | D54: (a) a Phase 4 load evicts the resident seat, which reloads afterwards, with Phase 4 work batched through the Celery gpu queue; (b) run the default seat at a smaller rung to keep 20-40 GB free; (c) Phase 4 work only in scheduled idle windows. | E54: (a). | F54: FLUX.1-dev needs 12-24 GB and Wan2.2 20-40 GB, while GLM-5.3-Flash leaves about 18 GiB of the budget for its own cache; (b) contradicts the less-quantisation rule, and each eviction costs a 50-85 s reload plus re-prefill unless the slot was saved. | G54: After Day 1 | H54: D-32; D-44 | I54: FRAMEWORK_REVIEW 15.2 L796-L797, 4.2 rule 2 L251; arbiter.py L45-L58.
A55: D-51 | B55: V4.1 trial engine and file | C55: Which engine and file should the V4.1 trial use? | D55: (a) DwarfStar with antirez Q2 (365.71 GB file, 151.76 GiB resident), the only path measured on this APU, 14-16.5 tok/s; (b) the Lucebox engine with Geometric ds41-lucebox-final (366.13 GB, 152.15 GiB resident), best internal bench 164 of 177 but never run on one device; (c) wait for llama.cpp PR #28696. | E55: (a) first, then (b) only if (a) shows promise; do not wait for (c), which has no AMD kernels and a cap near 16K context. The Principal accepts about 14-16 tok/s on a 2-bit file. | F55: Framework measured DwarfStar with antirez Q2 on a 192 GB PRO 495 at 14.0/13.8/13.8 tok/s and 16.3-16.5 with DSpark (prefill 350/337/300 at 0/32K/64K); both Lucebox V4.1 profiles assume an R9700 (projected 12-16 tok/s alone). Lucebox's ROCMFP2S file (167.58 GiB resident) and llama.cpp's Q2_K (186.17 GiB) and Q3_K_M (244.62 GiB) do not fit. | G55: After Day 1 | H55: D-46; D-52; D-47 | I55: Lucebox report Inputs row 2 (L393), L329, paths A-D L356-L359.
A56: D-52 | B56: GPU compute stack for an LLM engine | C56: May an LLM engine run on ROCm on the node? | D56: (a) no, Vulkan only; (b) yes, inside a container following the Phase 4 pattern; (c) ROCm installed on the host. | E56: (b), extending the Phase 4 container rule to one LLM engine: inbox amdgpu driver only, no DKMS, locked memory for that container alone, pinned image digest and source commit. | F56: Every route to V4.1 leaves the node's Vulkan llama.cpp: the Lucebox engine builds only for CUDA or HIP, and DwarfStar's measured run used kyuz0's ROCm 10.0 container for gfx1151. Section 3.4 already keeps ROCm off the host, and AMD does not recommend amdgpu-dkms on gfx1151 APUs after page-fault reports (ROCm #6186). | G56: After Day 1 | H56: D-46; T-29 | I56: Lucebox report Inputs row 3 (L394), L329-L331, L374; FRAMEWORK_REVIEW 3.4.
A57: D-53 | B57: Outbound allowlist for the trial | C57: Which build-time sources may be admitted for the trial engines, and for how long? | D57: (a) none; (b) GitHub (antirez/ds4, Luce-Org/lucebox), Docker Hub (kyuz0 images) and AMD's ROCm repository, during builds only. | E57: (b), build-time only and logged, with run time offline; Hugging Face pulls are already allowed. Lucebox's appliance updater, cloud fallback, crash reporting, Tailscale and Connect are never installed. | F57: Section 12.5 names only package mirrors during builds and Hugging Face during model pulls, and 16.3 item 8 forbids installing software from outside the allowlist without the Principal. allowlist.txt already admits github.com, registry-1.docker.io and stable.repo.amd.com, so the approval is mainly for the new sources. | G57: After Day 1 | H57: D-51; D-52 | I57: Lucebox report Inputs row 4 (L395), Risks L372; allowlist.txt L51-L84.
A58: D-54 | B58: Model drive for the trial files | C58: May the 8 TB model drive hold the V4.1 trial files? | D58: (a) one file of about 366 GB at a time; (b) both the antirez and Geometric files, about 732 GB. | E58: (a), one file at a time. | F58: The Lucebox report measures room against the baseline's under-900 GB; with the arsenal's about 1.9 TB (D-41) plus one 366 GB trial file the drive holds about 2.3 TB of 8 TB (computed here). Streaming experts only reads the drive, and SMART's written-data counter counts host writes only, so wear is not a concern. | G58: After Day 1 | H58: D-51; D-41 | I58: Lucebox report Inputs row 5 (L396), Risks L374; FRAMEWORK_REVIEW 15.4.
A59: D-55 | B59: Governance: zero-cloud | C59: Which Lucebox software, if any, may ever run on the node? | D59: (a) none; (b) the Apache 2.0 engine (luce_server) only, built from a pinned commit inside the trial container, with pflash_upstream_base unset and the cluster socket unused; (c) the appliance stack (updater, Manage, Connect, Tailscale, crash Report). | E59: (b) only if the trial reaches its second stage (D-51 (b)); never (c). | F59: A search of the engine source at commit 6f2b179 found no telemetry, licence check or vendor endpoint; its only outbound code is the multi-box cluster socket and an upstream proxy that runs only when pflash_upstream_base is set. The appliance has a daily update check, an undefined cloud fallback, a crash-log Report button, Tailscale and Connect, all of which break Section 1's zero-cloud rule. | G59: After Day 1 | H59: D-51 | I59: Lucebox report L368-L370; Lucebox CR section 4 G1 (L127).
A60: D-56 | B60: Governance: result fidelity | C60: Which speed-for-fidelity switches may an engine on the node use? | D60: (a) lossless only: default expert count, speculative decoding with exact verification, prefix caching; (b) also approximate switches after a scored comparison on the trial set (per-box router bias, decoder SWA bounded replay, sparse prefill); (c) any vendor speed setting, including top-4 experts and PFlash. | E60: (a) as the standing rule for routed engines, (b) only inside the V4.1 trial with each switch scored against the same file without it, never (c). Derived from the report's precision-first reading, not a numbered input. | F60: Lucebox's 54 tok/s V4 Flash headline used four of six experts, which on the adaptive 0731 file cut exact-copy fidelity from 95.0% to 60.0% with degenerate output, and PFlash is labelled lossy. Every V4.1 run uses a router bias fitted to the box, so 'bit-identical' compares speculative and plain decode under the same biased routing, not DeepSeek's reference. | G60: After Day 1 | H60: D-51 | I60: Lucebox report L128, L209, L217, L313; Lucebox CR section 4 G2 (L135-139), section 7 item 2 (L240).
A61: D-57 | B61: Governance: container privilege | C61: May the trial LLM container hold unlimited locked memory, and run as root if the engine requires it? | D61: (a) no; (b) yes, for that one container only, through its own memlock limit and non-root where the engine allows; (c) host-wide. | E61: (b), as part of D-52, with compute-wave save/restore left on. | F61: Lucebox's profiles need locked memory (root or ulimit -l unlimited) and break if compute-wave save/restore is off; with the default 8 MiB lock limit the iGPU host tier stays empty and experts stream from the SSD. The node's llama-server units already run with LimitMEMLOCK=infinity. | G61: After Day 1 | H61: D-52; D-51 | I61: Lucebox report L207, Risks L374; systemd/llama-server@.service L57.
A62: D-58 | B62: Uncensored: large 2026 abliterations | C62: Admit the huihui abliterations of GLM-5.3-Flash, Qwen3.8-Flash-Next and DeepSeek-V4-Flash, or a Nemotron 3 Super Heretic, into the arsenal? | D62: (a) not now; (b) admit after a node refusal and capability test (T-10); (c) as (b) for Nemotron 3 Super Heretic Q8_0 only (uploader-reported KL 0.1081 / 28 refusals v1, 0.2127 / 11 v2; March GGUFs may lack the MTP tensors). | E62: (a) not now: none is evidence-backed. | F62: None publishes refusal or quality figures, and the huihui builds ablate only non-expert layers (GLM layers 15-35; the DeepSeek build is a 4-bit proof of concept; the Flash-Next files are unsloth's base rungs); none has a UGI row. Abliterating a fully uncensored large MoE costs about 8 NatInt points, and every abliterated output still passes the same approval gate. | G62: Optional | H62: D-04 (for a Nemotron build) | I62: Arsenal report uncensored L82; Arsenal CR G4 (L129-132), open gap 3. Roster report L110; Roster gap_closure L361, L391, L399, L400.
A63: D-59 | B63: gpt-oss-120b file | C63: Keep the ggml-org MXFP4 file (Q8_0 trunk) or move to the F16-trunk GGUF? | D63: (a) MXFP4 / Q8_0-trunk 63.39 GB / 59.03 GiB (current); (b) F16-trunk 65.37 GB / 60.88 GiB, the highest-precision GGUF. | E63: (b), as the arsenal's disk set lists it; the experts stay native MXFP4 either way. | F63: Only about 2% of parameters change precision and no independent measurement compares the two files; the rule for native-MXFP4 models is to keep native tensors unchanged and the rest at high precision. | G63: Optional | H63: D-12 | I63: Arsenal report quantisation L59, L66, sequential L78; verification_named_120b_class_and_uncensored L91.
A64: D-60 | B64: EmbeddingGemma 2 | C64: Keep EmbeddingGemma 2 at all? | D64: (a) adopt as an optional code and multimodal side index after a re-pin to b11452 or later (b11474 covers it; v0.6.0 does not); (b) drop it. | E64: (a) or (b) at the Principal's preference; the primary retrieval pair is the Qwen3 embedder and reranker either way. | F64: MTEB multilingual 61.36 (+0.21 over EG1), English -1.21, 9-13 points below the 8B-27B leaders; its value is one shared space for text, image, video and audio plus code retrieval (+9.92). | G64: Optional | H64: D-01 | I64: Arsenal report Inputs L103, verdict row 11 (L52).
A65: D-61 | B65: Speculative-decoding drafters | C65: Use MTP or DSpark drafters with the large engines? | D65: (a) native MTP for Flash-Next (+2.8 GB), GLM (b11474) and Nemotron (v0.5.0 and later) after the re-pin; (b) DSpark for V4-Flash (+10.9 GB), which beside UD-Q8_K_XL totals 160.90 GiB and leaves 3.1 GiB; (c) separate draft models such as EAGLE3; (d) none. | E65: Keep the drafter files in the disk set; use only native MTP heads or DSpark, never separate draft models; decide per engine after the re-pin and node speed tests, measuring draft acceptance at temperature 1.0; DSpark with V4-Flash only at a lower rung. Record single-stream speculative decoding on the watch-list. | F65: Drafters trade memory for speed, and speed is secondary. Measured effects differ by engine: native MTP gave 1.4-1.6x on MoE engines; EAGLE3 cut gpt-oss-120b from 51.7 to 27.7 tok/s; DSpark slowed 0731 on stock Vulkan (mainline b10488 11.94 to 7.7 tok/s at UD-IQ3_XXS; 12.3 to 11.7 at UD-IQ2_XXS) but lifted a tuned fork from 18.9 to 28.9 at UD-IQ2_XXS and stock ROCm 10.0 llama.cpp from 13.3 to 20.9, while Framework measured V4.1 under DwarfStar at 14 -> 16.3-16.5 tok/s with it (Lucebox). 0731 ships no MTP head; concurrent serving rejects the drafter, so sequential use suits it. | G65: Optional | H65: D-01; D-11; T-05; T-31 | I65: Arsenal report L78, L97; Arsenal CR G1. Roster report L52, L56, Addendum L126; Roster gap_closure L435. Lucebox report L223, L374, L378.
A66: D-62 | B66: Hardware: discrete GPU | C66: Should the node gain a discrete GPU (Radeon AI PRO R9700, 32 GB)? | D66: (a) none now; (b) USB4 v2 dock with the card and a supply of 750 W or more; (c) M.2 riser, moving a four-lane drive to the x1 slot. | E66: (a) for now; revisit (b) only if the trial shows V4.1 or Flash-Next worth accelerating, preferably after someone publishes a 32 GB card in a USB4 dock; avoid (c). The Principal supplies a budget ceiling, tolerance for a 300 W blower near 3,000 RPM and a second power brick, and whether external hardware is acceptable. | F66: Lucebox measured V4.1 with the card at 48.7 tok/s on code and 31-33 at 2K-31K (Gen3 x4, greedy) against 14-16.5 without, and Flash-Next from 40 to 75 tok/s, while the card barely helps V4 Flash 0731 (36-42 with, 39-42 without). Those are Lucebox-engine figures, not the node's mainline Vulkan (0731 about 7-11 tok/s projected, D-11). The card alone is about $1,800 (Lucebox comparator), plus an unpriced USB4 v2 dock and a supply of 750 W or more; with amdgpu.runpm=0 the card never idles down. | G66: Optional | H66: D-46; T-30 | I66: Lucebox report Inputs row 6 (L397), L317-L325; Lucebox CR section 7 items 1, 4 (L237-L242).
A67: D-63 | B67: Hardware: second machine | C67: Should the Principal buy a Lucebox Zero 495 appliance as a second machine? | D67: (a) no; (b) yes, run air-gapped with the appliance software removed. | E67: (a); consider (b) only if the Principal wants a second box regardless. | F67: It duplicates the node's Ryzen AI MAX+ PRO 495 and adds an R9700 on a PCIe 4.0 x4 riser; its software has a daily update check and an undefined cloud fallback, and no third party has reproduced its figures. 192 GB units ship in February 2027 at $8,499 before Engine Pro ($199 per month per machine). | G67: Optional | I67: Lucebox report Inputs row 7 (L398), L75-L106.
A68: D-64 | B68: Watch-list: Lucebox ideas | C68: Record Lucebox's no-hardware ideas on the baseline watch-list? | D68: (a) record them at the next baseline revision (memory guard; expiring signed manifests; retrieval from local agent session logs; usage-ranked expert placement for any future card; single-stream speculative decoding); (b) do not record. | E68: (a), with no repository change beyond the watch-list rows; each idea is a baseline row (B-63, B-64, B-65, B-62, B-34). | F68: None needs Lucebox software or new hardware: the memory guard mirrors the Arbiter's 16 GiB host reserve, 120-day manifest expiry is a cheap discipline for pinned images, session-log retrieval fits the existing retrieval stack, usage-ranked placement is the design for any future card, and speculative decoding suits Ren and Arthur running one after the other. | G68: Optional | I68: Lucebox report Inputs row 9 (L400), L378.

Sheet 2 Named models
A1: Named models
A2: The twelve models and engines the Principal named, with the recommended verdict. Accept the verdict or state a change.
A4: ID | B4: Named model | C4: Recommended verdict | D4: Rung that fits alone | E4: Size (GB / GiB) | F4: Role in the arsenal | G4: Reason and evidence | H4: Source | I4: Your response | J4: Your choice or alternative | K4: Your comments
A5: N-01 | B5: DeepSeek-V4-Flash | C5: Include | D5: UD-Q8_K_XL (bit-exact), unsloth/DeepSeek-V4-Flash-0731-GGUF | E5: 161.87 GB / 150.75 GiB | F5: Apex / TF_OMEGA, Arthur, Deep Think adversary; reasoning and long context | G5: The only named engine with a lossless fitting rung (bit-identical to the official weights on all 1,328 tensors; KLD about 0, 100% top-1), inside the pin, MIT; AA 34.3, CritPt 16.6 lead, HLE 38.6, GPQA 90.8; the dsv4 KV (about 6,880 B/token) lets a 1M context fit. 0731 ships no MTP head (DSpark only). V4.1-Flash (552B) is a different model, governed by the Lucebox report as an evaluation-only trial (D-46); every fitting V4.1 file is 2-3 bit (KL about 0.26). huihui's abliterated 0731 is excluded (experts not ablated, 4-bit only). | H5: Arsenal report verdict row 1 (L42); verification_named_heavyweight_moe row 4. Roster report L68, L86, L110, Addendum L126-L136. Lucebox report Inputs rows 1-2 (L392-393).
A6: N-02 | B6: Qwen3-235B-A22B | C6: Exclude | D6: Q5_K_S (about 5.5 bpw), or Q4_K_M for long context | E6: 161.88 GB / 150.76 GiB | F6: None; its post-trains Intern-S1 (science) and Baichuan-M3 (medical) take seats | G6: Superseded: a 2025 model at AA 12.7, far below the 2026 leaders, and its 188 KiB/token KV caps the 5-bit rung near 23K context after buffers. | H6: Arsenal report verdict row 2 (L43); verification_named_heavyweight_moe row 13.
A7: N-03 | B7: GLM-5.3-Flash 320B | C7: Include with conditions | D7: UD-IQ4_XS (KLD 0.117, 88.2% top-1, lossy) | E7: 156.82 GB / 146.05 GiB | F7: General quality lead: Ren, Gideon, Silas, Helena, Victor, Minerva primary; vision (glm5v); long documents; Deep Think generator | G7: Conditions: re-pin to b11279 / v0.6.0 or later (D-01) and the KLD run (T-03). AA 41.8, top in-envelope; MIT; leads most legal, finance, medical, agentic and long-context boards but fits only at about 4 bits. KV 19,712 B/token f16 with the DSA indexer, about 469K context after a 9 GiB allowance. The roster research rejected it as 3-bit only (UD-Q3_K_XL 147.54 GB) with a Vulkan CPU fallback for its hyper-connection op and --kv-unified needed; those cautions become T-04. | H7: Arsenal report verdict row 3 (L44); Arsenal CR G1, G2. Roster report L35, L56, L86; Roster gap_closure L385.
A8: N-04 | B8: Qwen3-Coder-Next | C8: Include with conditions | D8: Q8_0 (practical); BF16 also fits | E8: Q8_0 84.81 GB / 78.99 GiB; BF16 159.46 GB / 148.51 GiB | F8: Dedicated coder, only if the Principal wants one (D-19) | G8: Just above the 70B floor (79.7B total, 3B active), inside the pin; the only named engine whose full BF16 fits with 256K context, but BF16 decode is kernel-limited (about 9 tok/s projected on Vulkan) against 37-44 projected at Q8_0; neither rung has a gfx1151 llama.cpp measurement. Vendor SWE-bench Verified 70.6-71.3, Aider 66.2; AA 9.24; GLM beats it on SWE-bench (Vals). Apache 2.0 rests on the card (LICENSE file missing). | H8: Arsenal report verdict row 4 (L45); verification_quantization_value row 19. Roster report L70, L90; Roster gap_closure L61-L63, L412.
A9: N-05 | B9: Llama 4 Maverick | C9: Exclude | D9: 2-3 bit only: UD-Q2_K_XL or i1-IQ3_XS | E9: UD-Q2_K_XL 152.66 GB / 142.17 GiB; i1-IQ3_XS 163.35 GB / 152.13 GiB | F9: None | G9: No KLD at any fitting rung and near the bottom of every current board (AA 9.3; LMArena #260 of 415); only 2-3 bit rungs fit, which the less-quantisation rule rejects (D-24). Vision works at the pin, but the model is out-classed. | H9: Arsenal report verdict row 5 (L46); verification_named_heavyweight_moe row 17.
A10: N-06 | B10: Mistral Large 2 Uncensored | C10: Exclude | D10: Q4_0 (the named Ollama build) | E10: 69.08 GB / 64.34 GiB | F10: None (D-06) | G10: gdisney/mistral-large-uncensored is stock Mistral-Large-2407 at legacy Q4_0 plus a system prompt instructing misinformation, under the research and non-commercial MRL licence. The weight-edited alternative is XORTRON (2411 Heretic) Q8_0 130.28 GB / 121.33 GiB, a dense 123B at about 1.7 tok/s. | H10: Arsenal report verdict row 6 (L47); verification_named_120b_class_and_uncensored L52.
A11: N-07 | B11: Qwen3.8 Flash-Next | C11: Include | D11: UD-Q6_K_XL (KLD 0.0271, matches its own Q8_0) | E11: 169.17 GB / 157.55 GiB | F11: Corporate challenger; runner-up for Ren and Victor; science QA; coding; vision; Deep Think third opinion | G11: Re-pin advised (b11330 or later): it loads at the pin, but its Vulkan hyper-connection ops (#28988), MTP (#29761) and the #29751 attention fix are later (measured only at UD-IQ4_XS on 128 GB Ryzen AI Max+ 395 boxes: 26.9-27.2 tok/s without MTP (the roster infers v0.4.1 gets this) and 41.3 with MTP on PR #28243 fork builds; nothing is measured at UD-Q6_K_XL (23-29 tok/s projected)). AA 39.8 (second of the twelve), GPQA 92.3, Terminal-Bench 2.1 86.1 (top open); Qwen Community 1.0, internal use exempt (D-03). About 6.5 GiB left, so companion growth can push it to UD-Q5_K_XL (D-28). Its huihui v2 (unsloth-recipe UD-Q6_K_XL 157.55 GiB, experts not ablated) and cygnal Heretic2 (IQ4_XS) abliterations are excluded: neither publishes refusal or quality data. | H11: Arsenal report verdict row 7 (L48); verification_named_heavyweight_moe row 19. Roster report L66, L82, L110, Addendum L126-L136; Roster gap_closure L373-L374, L400.
A12: N-08 | B12: Nemotron 3 Super Q8 | C12: Include | D12: Q8_0 (release precision), 4 shards | E12: 128.47 GB / 119.65 GiB | F12: Long-context utility; long-document runner-up; Estate option, no longer Arthur's default (D-13) | G12: Fits with about 44 GiB spare and a 1M-token context at tiny KV, inside the pin, but AA 12.8 and its card discloses an HLE/GPQA contamination risk; no MTP at the pin. The Vulkan fault near 20K-token prompts (#20732) was closed with no fix (T-12). Licence read (D-04); an optional Heretic build exists (D-58). | H12: Arsenal report verdict row 8 (L49); verification_quantization_value L28. Roster report L67, L84; Roster gap_closure L380, L418, L437.
A13: N-09 | B13: gpt-oss-120b | C13: Include | D13: MXFP4 (release precision); F16-trunk is the highest-precision GGUF (D-59) | E13: MXFP4 63.39 GB / 59.03 GiB; F16-trunk 65.37 GB / 60.88 GiB | F13: Fast utility, drafting, Sentinel escalation; fallback floor for every seat (D-40) | G13: Native MXFP4 experts make it lossless at release precision, and it is the fastest engine: 57-60 tok/s projected by the arsenal, 53.8-55.6 measured on 128 GB boxes (roster). AA 11.6 makes it a speed engine, not a quality seat, now that co-residency no longer rewards its size (D-12). | H13: Arsenal report verdict row 9 (L50); verification_quantization_value row 22. Roster report L66, L82, Addendum L128, L134.
A14: N-10 | B14: gpt-oss-120b Abliterated | C14: Include with conditions | D14: ArliAI Derestricted Q8_0 (or Derestricted MXFP4_MOE) | E14: Q8_0 124.30 GB / 115.76 GiB; MXFP4_MOE 63.39 GB / 59.03 GiB | F14: Explicit-override uncensored seat for Ren and Arthur; Valerie fallback | G14: Condition: the Derestricted build, not the node's current file. The current huihui v2 -> noctrex MXFP4_MOE has no provenance card or data and huihui's repos return 401 (retire, D-09); kldzj Heretic v2 measures KL 0.53 with 22/100 refusals. Derestricted is the best measured variant (UGI NatInt 35.70 vs base 33.68), Apache 2.0, and its Q8_0 keeps the edited experts near BF16. | H14: Arsenal report verdict row 10 (L51); Arsenal CR G4 (L118-122). Roster report L80, L108; Roster gap_closure L349, L393, L455.
A15: N-11 | B15: EmbeddingGemma 2 | C15: Include with conditions | D15: Q8_0 or BF16 | E15: Q8_0 0.31 GB / 0.29 GiB; BF16 0.56 GB / 0.52 GiB | F15: Optional multimodal and code side index, not the primary embedder (D-60) | G15: Condition: side index only, after a re-pin to b11452 or later (b11474 covers it, v0.6.0 does not). MTEB multilingual 61.36 (+0.21 over EG1), English -1.21, 9-13 points below the 8B-27B leaders; its value is one shared space for text, image, video and audio plus code retrieval (+9.92). | H15: Arsenal report verdict row 11 (L52); verification_named_companion_engines rows 4-6.
A16: N-12 | B16: Nemotron 3 Diarization | C16: Include | D16: Official Q8_0 GGUF (NeMo-Speech.cpp format, not llama.cpp) | E16: 0.11 GB / 0.10 GiB | F16: Primary diariser (C-06) | G16: Best open result on the only same-harness comparison (OpenBench average DER 0.19 vs pyannote community-1 0.28; 0.206 vs 0.300 without the contaminated VoxConverse set); OpenMDW-1.1 (D-05); tiny memory; runs on the node's ggml/Vulkan stack. Handles up to eight speakers; community-1 stays the fallback beyond that. | H16: Arsenal report verdict row 12 (L53); verification_named_companion_engines rows 18, 23. Roster report L77, L102.

Sheet 3 Persona allocation
A1: Persona allocation
A2: Recommended engine for each persona and agent, each running alone at the least-quantised rung that fits. Projections until the node measures them.
A4: ID | B4: Persona or agent | C4: Discipline | D4: Recommended engine | E4: Rung | F4: Size (GB / GiB) | G4: Decode (basis) | H4: Strongest evidence | I4: Runner-up | J4: Source | K4: Your response | L4: Your choice or alternative | M4: Your comments
A5: P-01 | B5: Ren (Corporate lead) | C5: General, negotiation, geopolitics | D5: GLM-5.3-Flash (unsloth UD-IQ4_XS) (provisional: UD-IQ4_XS is lossy, KLD 0.117; pending the node KLD run T-03, D-02) | E5: UD-IQ4_XS | F5: 156.82 GB / 146.05 GiB | G5: 12-14 tok/s projected (17.4 measured on a PRO 495 at 3.84 bpw, Vulkan, post-pin build) | H5: AA 41.8, top in-envelope; LMArena #29 overall. KV 19,712 B/token f16, about 469K context after a 9 GiB allowance. Replaces gpt-oss-120b as Corporate default (D-12). | I5: Qwen3.8-Flash-Next UD-Q6_K_XL | J5: Arsenal report allocation L17. Roster report L66, L82.
A6: P-02 | B6: Arthur (Estate lead) | C6: General, estate, academia | D6: DeepSeek-V4-Flash-0731 (unsloth UD-Q8_K_XL) | E6: UD-Q8_K_XL | F6: 161.87 GB / 150.75 GiB | G6: About 7 tok/s on mainline Vulkan (floor; in-pin kernels unmeasured); about 11 at UD-Q4_K_XL | H6: Bit-exact, KLD about 0; AA 34.3; CritPt 16.6 lead. KV about 6,880 B/token f16, so a 1M context fits. Replaces Nemotron 3 Super as Estate default (D-13). | I6: GLM-5.3-Flash (diversity against Ren); Nemotron 3 Super Q8_0 (former default) | J6: Arsenal report allocation L18. Roster report L67, L84.
A7: P-03 | B7: Gideon (law, strata, HR) | C7: Legal, compliance | D7: GLM-5.3-Flash (provisional: UD-IQ4_XS is lossy, KLD 0.117; pending the node KLD run T-03, D-02) | E7: UD-IQ4_XS | F7: 156.82 GB / 146.05 GiB | G7: 12-14 tok/s projected | H7: LegalBench 83.93% (top open model that fits); Legal Research 45.19%. US-centric boards only; no Australian-law or HR evaluation exists (D-49). GLM Legal (86.23%) is API-only, on the watch-list. | I7: DeepSeek-V4-Flash-0731 (LegalBench 77.71%) | J7: Arsenal report allocation L19. Roster report L94.
A8: P-04 | B8: Silas (CFO, audit, fraud) | C8: Finance, tax | D8: GLM-5.3-Flash (provisional: UD-IQ4_XS is lossy, KLD 0.117; pending the node KLD run T-03, D-02) | E8: UD-IQ4_XS | F8: 156.82 GB / 146.05 GiB | G8: 12-14 tok/s projected | H8: Finance Agent v2 57.85% (top open); TaxEval 75.59%. | I8: Ling-3.0-flash-Fin Q8_0 135.63 GB / 126.32 GiB (finance-tuned, lossless; FAB v2 54.93%; D-18) | J8: Arsenal report allocation L20.
A9: P-05 | B9: Valerie (infra, DevOps, cyber; uncensored default) | C9: Cybersecurity, AEGIS | D9: MiMo-V2.6-Flash uncensored (dealignai RL-UNCENSORED, AliceThirty MXFP4) | E9: MXFP4 | F9: 168.42 GB / 156.85 GiB | G9: About 18 tok/s (stock MiMo MXFP4 measured 18.3 on a PRO 495, ROCm) | H9: Vals CyberBench 75.36% (top open); MMLU -0.14 pp against base. Fits with about 7 GiB spare. The roster research put it after the pin; the arsenal review (C6) finds the mimo2 runtime in v0.4.1, so loading at the pin is untested (T-09). | I9: gpt-oss-120b Derestricted Q8_0 (D-07 (b)) | J9: Arsenal report allocation L21; Arsenal CR C6. Roster report L38; Roster gap_closure L378.
A10: P-06 | B10: Helena (comms, PR, crisis, creative) | C10: Communications, creative | D10: GLM-5.3-Flash (provisional: UD-IQ4_XS is lossy, KLD 0.117; pending the node KLD run T-03, D-02) | E10: UD-IQ4_XS | F10: 156.82 GB / 146.05 GiB | G10: 12-14 tok/s projected | H10: LMArena creative #45 (top open); entertainment #38. No EQ-Bench result exists for GLM. | I10: DeepSeek-V4-Flash-0731 (EQ-Bench Creative Writing 1441.1; the stronger 1559.1 belongs to the April preview checkpoint, not 0731) | J10: Arsenal report allocation L22.
A11: P-07 | B11: Minerva (health, longevity) | C11: Medicine; cross-check | D11: GLM-5.3-Flash primary (provisional: UD-IQ4_XS is lossy, KLD 0.117; pending the node KLD run T-03, D-02) + Baichuan-M3-235B cross-check | E11: UD-IQ4_XS / Q5_K_S (or official Q4_K_M) | F11: 146.05 GiB; Baichuan Q5_K_S 161.88 GB / 150.76 GiB or Q4_K_M 143.78 GB / 133.91 GiB | G11: GLM 12-14 tok/s; Baichuan-M3 8-13 tok/s (projections; no gfx1151 measurement) | H11: GLM MedScribe 88.94%, MLCR 51.1 (top open); Baichuan-M3 HealthBench 65.1 / Hard 44.4 (vendor, no independent index). Baichuan's 188 KiB/token KV caps context near 23K at Q5 (D-16). Replaces Meditron-70B (D-15). | I11: Intern-S1 (science subdomains); MedGemma-27B dropped under the 70B floor | J11: Arsenal report allocation L23. Roster report L71, L96, Addendum L132, L140.
A12: P-08 | B12: Victor (aviation, transport, concierge) | C12: No domain board | D12: GLM-5.3-Flash (provisional: UD-IQ4_XS is lossy, KLD 0.117; pending the node KLD run T-03, D-02) | E12: UD-IQ4_XS | F12: 156.82 GB / 146.05 GiB | G12: 12-14 tok/s projected | H12: General leaders only (tau-Banking 47.2, GDPval-AA, AutomationBench 60.4); quality can be settled only on the Principal's own test sets (D-49). | I12: Qwen3.8-Flash-Next | J12: Arsenal report allocation L24.
A13: P-09 | B13: Alaric (OSINT, protection, Sentinel) | C13: Physical security, OSINT | D13: MiMo-V2.6-Flash uncensored (shared with Valerie) | E13: MXFP4 | F13: 168.42 GB / 156.85 GiB | G13: About 18 tok/s (stock MiMo MXFP4 measured, PRO 495, ROCm) | H13: No OSINT or physical-security board; cyber lead plus generalist strength. | I13: GLM-5.3-Flash | J13: Arsenal report allocation L25.
A14: P-10 | B14: Eleanor (router, dispatch, logistics) | C14: Classification, routing, LightRAG extraction | D14: Qwen3.5-4B (resident companion) | E14: Q8_0 | F14: 4.5 GB / 4.19 GiB | G14: Fast; always resident, thinking off (no measured figure) | H14: A companion, outside the no-small-models rule; the only 4B-class model with a 2026 date and llama.cpp text and vision; Qwen 3.8 shipped no small model (G8). | I14: Gemma 4 E4B; Granite 4.1 8B (no measured routing advantage) | J14: Arsenal report allocation L26. Roster report L74, L100.
A15: P-11 | B15: Deep Think generator / adversary | C15: Cross-model reasoning | D15: GLM-5.3-Flash + DeepSeek-V4-Flash-0731 (two families) | E15: UD-IQ4_XS / UD-Q8_K_XL | F15: 146.05 GiB; 150.75 GiB | G15: As each engine, run in turn at about 50-85 s per swap plus re-prefill | H15: AA HLE 39.9 / 38.6; GPQA 91.2 / 90.8 (D-22). | I15: Qwen3.8-Flash-Next (third opinion) | J15: Arsenal report allocation L27.
A16: P-12 | B16: TF_OMEGA / Apex | C16: Deepest synthesis | D16: DeepSeek-V4-Flash-0731 UD-Q8_K_XL, until the node KLD run decides | E16: UD-Q8_K_XL | F16: 161.87 GB / 150.75 GiB | G16: About 7 tok/s on mainline Vulkan (floor); about 11 at UD-Q4_K_XL; measured only at 2-3 bits on 128 GB Ryzen AI Max+ 395 boxes: UD-IQ2_XXS 12.6-13.3 on stock Vulkan and 18.9 on a fork; UD-IQ3_XXS 11.9 on mainline b10488 and 18.4 on a fork | H16: Bit-exact, KLD about 0 (UD-Q4_K_XL 0.0102); HLE 38.6, GPQA 90.8; a 1M context fits (D-11). | I16: GLM-5.3-Flash UD-IQ4_XS (AA 41.8, lossy); K2-Horizon-375B IQ3_XXS (AA 31); V4.1 Flash as an evaluation-only trial (D-46); Qwen3.5-397B 3-bit dropped | J16: Arsenal report allocation L28. Roster report L68, L86, Addendum L136. Lucebox report Inputs row 1.
... A22: P-18 | B22: Fast utility (drafting, Sentinel escalation) | C22: Drafting, triage, escalation | D22: gpt-oss-120b | E22: MXFP4 (F16-trunk GGUF per D-59) | F22: 63.39 GB / 59.03 GiB (F16-trunk 65.37 GB / 60.88 GiB) | G22: 57-60 tok/s projected; 53.8-55.6 measured on 128 GB boxes | H22: AA 11.6; lossless at native MXFP4; loads at the current pin, so it is also every seat's fallback floor (D-12, D-40). | I22: Nemotron 3 Super Q8_0 (13.6-15.8 tok/s projected) | J22: Arsenal report verdict row 9 (L50), directives L7. Roster report L66, L82.

Sheet 4 Companions
A1: Companions
A2: Companion engines (router, retrieval, OCR, speech, diarisation, voice, image). Small models are allowed here; the no-small-models rule covers LLM seats only.
A4: ID | B4: Role | C4: Current engine | D4: Recommendation | E4: Alternatives | F4: Why (evidence) | G4: Depends on | H4: Source | I4: Your response | J4: Your choice or alternative | K4: Your comments
A5: C-01 | B5: Router (Eleanor) | C5: Qwen3.5-4B Q8_0, 4.5 GB, always resident (port 8108) | D5: Keep. | E5: Gemma 4 E4B; Granite 4.1 8B | F5: No newer sub-10B model exists in the family, and the router is a classifier, not an LLM seat, so the no-small-models rule does not apply. | H5: Arsenal report companions L84; Arsenal CR G8 (L191). Roster report L74, L100.
A6: C-02 | B6: Embeddings (primary) | C6: bge-m3 Q8_0, 0.7 GB, 1024-dim, always resident (port 8109; MTEB multilingual 59.56) | D6: Qwen3-Embedding-8B Q8_0 (8.05 GB / 7.49 GiB; MTEB multilingual 70.58), or the 4B (4.28 GB / 3.99 GiB; 69.45) if D-14 picks the 4B pair; serve with --embedding --pooling last -ub 8192, truncate to the 1024-dim schema and re-normalise; re-index per D-45. | E6: Nemotron-3-Embed-8B (RTEB 75.45, OpenMDW-1.1, sliceable to 1024); Qwen3-Embedding-0.6B (64.33); keep bge-m3. Harrier-27B (74.3) is not faithful at any pin (the gemma-embedding loader forces bidirectional attention). | F6: An 8-bit embedder costs only about 0.2-0.6 points, and bge-m3 is about 11 points behind. Qwen's official GGUF carries pooling LAST and works with the pinned llama-server. Every resident GiB comes off the single engine's budget. | G6: D-14; D-05 (if Nemotron-3-Embed); T-15 | H6: Arsenal report companions L84; verification_named_companion_engines rows 12-16. Roster report L75, L100, Addendum L132; Roster gap_closure L73-L74.
A7: C-03 | B7: Reranker | C7: bge-reranker-v2-m3 Q8_0, 0.7 GB, always resident (port 8110; MMTEB-R 58.36) | D7: Qwen3-Reranker-8B (MMTEB-R 72.94; Q8_0 8.05 GB / 7.49 GiB) or 4B (72.74; 4.28 GB) per D-14, on /v1/rerank with --reranking and -ub sized to the longest query plus document. Confirm the rank head (pooling RANK, cls.output.weight) before use, or convert locally with the pinned converter. | E7: ggml-org Qwen3-Reranker-0.6B Q8_0, the only official reranker GGUF (66.36); keep bge-reranker-v2-m3. | F7: A 14.6-point MMTEB-R gain. Contradiction: the arsenal reads the Voodisss 8B Q8_0 as correctly converted; the roster research did not inspect its headers and found the mradermacher 8B lacks the rank head, so T-15 checks it. The batch-splitting fix (#28876) is post-pin: at v0.4.1 an over-long pair is rejected. | G7: D-14; D-01; T-15 | H7: Arsenal report companions L84; verification_named_companion_engines row 16; Arsenal CR G1. Roster report L75, L100, Addendum L132; Roster gap_closure L75, L361, L432.
A8: C-04 | B8: OCR and scanned documents | C8: No OCR model: Docling on the CPU, Florence-2-large in Phase 4, Qwen2.5-VL-72B as vision engine | D8: A resident sub-2 GB OCR model beside the text engine, chosen by a node test on the Principal's documents (T-19): OvisOCR2 0.853B (OmniDocBench 96.47) or PaddleOCR-VL-1.6 0.96B (96.34, Apache 2.0 per the HF API read 2026-10-15; the roster could not read it), both at the pin. | E8: TeleOCR 1.415B (96.91, Apache 2.0); GLM-OCR 0.9B (95.22 on v1.6; ggml-org Q8_0 0.95 GB + 0.48 GB mmproj, MIT, -hf ggml-org/GLM-OCR-GGUF); MinerU2.5-Pro (95.75); dots.ocr. | F8: On scanned-document transcription a small OCR model beats every 70B+ engine (Qwen3-VL-235B 89.78). Resident, it takes about 1.3-1.5 GiB from every engine's budget; no benchmark covers handwriting or drawings. | G8: D-14; T-19 | H8: Arsenal report companions L84; Arsenal CR G8 (L182-190). Roster report L73, L100, Addendum L132; Roster gap_closure L77, L413.
A9: C-05 | B9: Speech-to-text | C9: faster-whisper large-v3-turbo, CPU int8, via speaches 0.8.3-cpu (port 8881); Open ASR average WER 8.39 (#48) | D9: Run a WER test on the Principal's audio (T-20) and switch only on its result, keeping Whisper as the fallback. Candidates: Qwen3-ASR-1.7B (WER 5.75; ggml-org Q8_0 2.17 GB + 0.36 GB mmproj on llama-server /v1/audio/transcriptions, at the pin) and Phi-4-multimodal 6B (5.02, MIT). | E9: granite-speech-3.3 8B / 2B (5.26 / 5.36); parakeet-tdt-0.6b-v3 (6.51); faster-whisper on the GPU via the CTranslate2 4.7 ROCm wheel (11.5x realtime on gfx1151). | F9: A roughly 3-point WER gap under the quality-first directive. Qwen3-ASR beats Whisper-large-v3 on every English set Qwen lists (Tedlium 4.50 vs 6.84), Apache 2.0, 52 languages. The arsenal notes its Transformers path needs 5.13.0 or later; the roster found the GGUF runs on the pinned llama-server. | G9: D-26 (phasing); T-20 | H9: Arsenal report companions L84; Arsenal CR G8 (L169-181). Roster report L76, L102, Addendum L132; Roster gap_closure L78, L434.
A10: C-06 | B10: Speaker diarisation | C10: pyannote speaker-diarization-3.1 (pyannote.audio 4.0.7) in a CPU venv; community-1 as the scripted fallback (05-voice.sh L156, L162) | D10: Adopt Nemotron 3 Diarization (official Q8_0, 0.11 GB) via NeMo-Speech.cpp as the primary diariser; switch pyannote from 3.1 to community-1 now, as the interim default and the fallback for more than eight speakers. | E10: pyannote community-1 alone (OpenBench DER 0.28); DiariZen (CC BY-NC); Sortformer (four-speaker cap); pyannoteAI precision (cloud, forbidden). | F10: OpenBench average DER 0.19 vs 0.28 on the same harness at tiny memory; community-1 beats 3.1 by 1-4 DER points on 11 of 12 sets (AMI-SDM 19.9 vs 22.7). NeMo-Speech.cpp is a separate runtime with no gfx1151 speed figure yet. | G10: D-05; T-21 | H10: Arsenal report companions L84, verdict row 12 (L53); Arsenal CR C17 (L246). Roster report L77, L102; Roster gap_closure L100.
A11: C-07 | B11: EmbeddingGemma 2 side index | C11: None | D11: Optional code and multimodal side index after the re-pin, or drop it (D-60); not the primary embedder. | E11: None needed; the primary pair is unchanged either way. | F11: MTEB multilingual 61.36 (+0.21 over EG1), English -1.21, code +9.92; one shared space for text, image, video and audio; Q8_0 0.31 GB / 0.29 GiB. | G11: D-60; D-01 (b11452 or later) | H11: Arsenal report companions L84, Inputs L103.
A12: C-08 | B12: Text-to-speech, default | C12: Kokoro-82M via kokoro-fastapi-cpu v0.9.0 (port 8880) | D12: Keep. | E12: CosyVoice3 (Apache 2.0) | F12: About 1063 Elo on the AA open-weights TTS arena; about 20x realtime on ROCm gfx1151 after the MIOPEN_FIND_MODE=2 warm-up fix. The arsenal research did not re-evaluate TTS. | H12: Roster report L78, L102. Arsenal report gaps L90; Arsenal CR G8 (L192), open gap 6.
A13: C-09 | B13: Text-to-speech, character and cloning tier | C13: Chatterbox 0.1.7 on the CPU, own venv, through the Arbiter | D13: Move to Chatterbox Turbo 350M (repo 4.04 GB) for English and Multilingual V3 0.5B (3.21 GB, 23 languages), both MIT, after a test on the ROCm 10.0 image (T-23); keep 0.1.7 until then. | E13: Chatterbox Nano 110M (CPU); Higgs v3 and Fish S2-Pro (non-commercial) | F13: Turbo's one-step decoder cuts compute; no gfx1151 run exists anywhere, and the documented continuation quirk must be re-tested. | G13: D-26 (phasing); T-23 | H13: Roster report L78, L102; Roster gap_closure L98-L99.
A14: C-10 | B14: Text-to-speech, Qwen3-TTS test | C14: Watch-list: test after the core build (Section 14.1) | D14: Test Qwen3-TTS-12Hz-1.7B-Base (ggml-org Q8_0 1.85 GB + 0.45 GB mmproj) through llama-tts on the pinned Vulkan build after Day 1, beside Kokoro and Chatterbox in the V7 listening set (T-22). | E14: 0.6B GGUFs exist only for separate runtimes (qwentts.cpp) | F14: Apache 2.0, three-second cloning, Seed-TTS WER 1.24 (English); support and the Vulkan GET_ROWS fix (#28253) are in the pin, but it is CLI-only until the server endpoint (PR #26603) merges. A speech companion, so the no-small-LLM rule does not apply. | G14: D-26 (phasing); T-22 | H14: Roster report L78, L102; Roster gap_closure L79, L398, L433. FRAMEWORK_REVIEW 14.1 L737.
A15: C-11 | B15: Image generation | C15: FLUX.1-dev (Phase 4 green; non-commercial licence accepted by the Principal) | D15: Keep FLUX.1-dev; add Z-Image-Turbo (6B, Apache 2.0) as a permissive fast tier; evaluate Qwen-Image-2512 (Apache 2.0). | E15: FLUX.2-dev 32B (non-commercial, 24B text encoder); HiDream-I1 (transformer MIT, Llama 3.1 text encoder); FLUX.2-klein-4B (Apache 2.0); Qwen-Image-2.1 (non-commercial, watch-list) | F15: Z-Image-Turbo was the top open text-to-image model on AA (2025-12-08); its repository is 32.90 GB with an F32 transformer (about 12.31 GB in BF16). Qwen-Image-2512 (57.70 GB) measured 74-79 s per image with the 4-step LoRA on Strix Halo; no FLUX or Z-Image timing on gfx1151 exists. | G15: D-26 (phasing); D-50; T-25 | H15: Roster report L79, L104; Roster gap_closure L96-L97, L408.
A16: C-12 | B16: Medical imaging | C16: Rad-DINO (Phase 4, research use per its card) | D16: Keep Rad-DINO; add MedGemma 1.5 4B (Q8_0 4.13 GB + 0.85 GB mmproj) only if the Principal classes it as an imaging companion rather than an LLM seat and accepts its HAI-DEF terms. | E16: Rad-DINO alone | F16: The roster research proposed it beside Rad-DINO for chest X-ray, dermatology, ophthalmology and histopathology; as a 4B multimodal LLM it falls under the no-small-models rule unless treated as a companion. | G16: D-15 | H16: Roster report L96; Roster gap_closure L72.

Sheet 5 Structure changes
A1: Structure changes
A2: The amendments to the baseline document, scripts and workbook that would follow once the decisions they depend on are approved. Approve here to authorise the edit.
A4: ID | B4: Area | C4: Amendment | D4: Targets (files and sections) | E4: Depends on | F4: Effort | G4: Source | H4: Your response | I4: Your choice or alternative | J4: Your comments
A5: S-01 | B5: llama.cpp re-pin | C5: Move the pin from v0.4.1 (b29c606) to the approved build (v0.6.0 or b11474; GLM needs b11279 or later), add llama-perplexity to the built binaries, update every min_llama_cpp_tag and the research line, and re-verify every source fact marked VERIFIED: reserved flags, context shift off on six of eight engines, TRACE KV lines at --verbosity 4, HTTP 400 on an over-long prompt, the --fit log the load test parses. | D5: scripts/day1/phase2/01-llama.sh L27-L30; phase2/engine-env.py RESERVED_FLAGS; config/engines.json _meta research L16 and min_llama_cpp_tag; phase3/loadtest.py FIT_END_RE, parse_memory_lines; FRAMEWORK_REVIEW 3.4 L143, 4.3 L273, 5.2, 17 Phase 2 step 1 L928, 23, App B L1244, App D; scripts/day1/README.md UNVERIFIED list | E5: D-01 | F5: Large | G5: Structure review (re-pin); Arsenal structure (pin); Arsenal report Inputs L97; Arsenal CR G1.
A6: S-02 | B6: Pin parity test | C6: Add a required output-parity step: build the old pin beside the new one and compare outputs on engines both load (gpt-oss-120b, Nemotron, DeepSeek-V4-Flash, Qwen3.8-Flash-Next, the router and any other at-pin seat) with llama-perplexity --kl-divergence and a deterministic task set, -fa on and off, recorded as a new V25. | D6: scripts/day1/phase2/01-llama.sh (second build directory); phase3-models.sh (new step); phase3/loadtest.py (new subcommand); FRAMEWORK_REVIEW 17 Phase 3, 21 (new V25); scripts/day1/COVERAGE.md; tools/fill-workbook.py | E6: D-01; T-02 | F6: Medium | G6: Structure review (parity test); Arsenal report closing gaps.
A7: S-03 | B7: Quality (KLD) measurement step | C7: Add a Phase 3 record step that scores each candidate file against a reference with llama-perplexity --kl-divergence on Wikitext-2 plus a domain corpus and counts changed answers on a small deterministic set, raising a to-do like S52's kv-estimates. GLM's Q8_0 reference is 317 GiB, so its check is a task delta against published full-precision scores. | D7: scripts/day1/phase3/loadtest.py (new record); phase3-models.sh (new step and to-do); FRAMEWORK_REVIEW 17 Phase 3, 21 | E7: D-02; T-03 | F7: Medium | G7: Structure review (KLD step); Arsenal structure (KLD tooling); Arsenal report L72, L107; Roster report verification protocol.
A8: S-04 | B8: Diarisation | C8: Make Nemotron 3 Diarization the primary diariser (official Q8_0, 0.10 GiB, NeMo-Speech.cpp on the node's ggml and Vulkan stack) and pyannote community-1 the fallback for more than eight speakers; add a pinned NeMo-Speech.cpp build step, rewrite V6 (passes only on pyannote 3.1) and the gated-model checklist item. | D8: scripts/day1/phase2/05-voice.sh L18-L35, L156-L162, L834 and a new build step; verify/v06-pyannote.sh; FRAMEWORK_REVIEW 4.1 L228, 14.1 L739, 21 V6 L1070, 22 L1112; workbook Ref Voice | E8: D-05; C-06; T-21 | F8: Large | G8: Structure review (diarisation); Arsenal structure (diarisation); Roster structure (diarisation).
A9: S-05 | B9: Uncensored marker and R13 | C9: Replace the name-suffix test endswith('-abliterated') with an engines.json field (uncensored: true) read by the router's tier floor and the cross-check exclusion, so MiMo uncensored and Derestricted keep R13 (never below standard tier); remove the gpt-oss-120b-abliterated entry (noctrex repo), add the approved uncensored entries and re-point the ren-abliterated and arthur-abliterated routes. | D9: orchestrator/src/atlas/router.py L913-L944; approval.py L343-L412; personas.py L161; config/engines.json L51-L79; config/router-rules.json L31, L33; config/personas/valerie.md L8, ren.md, arthur.md; FRAMEWORK_REVIEW 5.1 L308, 6.1, 6.2, S1 L1146, R13 L1052 | E9: D-07; D-08; D-09 | F9: Medium | G9: Structure review (uncensored marker); Arsenal structure (uncensored engines); Roster structure (abliterated engines).
A10: S-06 | B10: Hemisphere, Sentinel and locale text | C10: Rewrite the remaining engine mentions: 9.3's escalation (resident engine first; gpt-oss-120b only when resident, never forcing a swap), Section 1's locale line (multilingual carried by Qwen3.5 and Kokoro) and 10.2's 'escalating to a large engine' for graph indexing. | D10: FRAMEWORK_REVIEW 9.3 L590, 1 L62, 10.2 L640 | E10: D-10; D-12 | F10: Small | G10: Structure review (hemisphere text).
A11: S-07 | B11: Nemotron long-prompt check | C11: If Nemotron stays as the long-context utility, add a prompt of 20K tokens or more with a health check to Phase 3 (today's test uses 8K) and update its known_issue. | D11: scripts/day1/phase3/loadtest.py; config/engines.json nemotron-3-super known_issue | E11: D-13; T-12 | F11: Small | G11: Arsenal structure (Nemotron long prompt); Arsenal CR G11 (L220-224).
A12: S-08 | B12: OCR companion | C12: Add a resident OCR llama-server unit for the approved model (C-04) and route scanned pages from Docling ingestion to it; decide whether Florence-2 keeps detection and captioning only. | D12: config/engines.json (new resident entry and port); phase2/04-memory.sh (resident keys L128, docling path); orchestrator/src/atlas/memory.py (ingestion); config/phase4-engines.json florence-2 L123-L149; FRAMEWORK_REVIEW 4.1 resident rows, 5.3, 10.1 L636, 15.1, 15.2 L799, 17 Phase 2 step 4 L931; workbook Ref Multimodal | E12: D-14; C-04; T-19 | F12: Medium | G12: Structure review (OCR); Arsenal structure (OCR companion); Roster structure (OCR service).
A13: S-09 | B13: New seats | C13: Add engines.json entries, Arbiter classes and persona or task-force bindings for the approved seats: Intern-S1 Q5_K_S 150.84 GiB (or Q4_K_M 132.86 GiB), Ling-3.0-flash-Fin Q8_0 126.32 GiB, Baichuan-M3 Q5_K_S 150.76 GiB or official Q4_K_M 133.91 GiB (KV about 188 KiB/token, context per the Principal's target), Qwen3-Coder-Next Q8_0 78.99 GiB or BF16 148.51 GiB, MiMo uncensored MXFP4 156.85 GiB and gpt-oss Derestricted Q8_0 115.76 GiB; point Minerva's cross-check plan and the strong cross-check route at Baichuan-M3. | D13: config/engines.json (new entries); config/personas/silas.md, valerie.md, minerva.md; config/task-forces.json; config/router-rules.json (strong cross-check route); orchestrator/src/atlas/approval.py DEFAULT_CROSS_CHECK_PLAN L350; FRAMEWORK_REVIEW 4.3, 5.1, 6.2 L384, 9.2 L581, 15.2 L811, 15.4, 16.5 | E13: D-07; D-08; D-15; D-16; D-17; D-18; D-19 | F13: Large | G13: Structure review (new seats); Roster structure (medical cross-check).
A14: S-10 | B14: Vision engine, C25 and D10 | C14: Remove Qwen2.5-VL-72B from every engine map and rewrite C25 ('One engine: Qwen2.5-VL-72B at Q8_0') and D10 for the chosen engine: GLM-5.3-Flash with the glm5v mmproj (0.65 GB) on the default engine's own unit, or Qwen3-VL-235B Q5_K_S plus mmproj as a separate ~150 GiB swap. State that the OCR companion transcribes and does not reason, so C25 stays 'one vision engine'. | D14: FRAMEWORK_REVIEW C25 L998, D10 L1017, 0 item 7 L41, 5.1 L321, 6.2 L380, L384, 14.4 L768, 15.2 L798, App B L1240; config/engines.json L178-L209; config/personas/valerie.md L10, minerva.md L11; phase3-models.sh L18-L24, L131; workbook Ref Engines, Ref Multimodal | E14: D-01; D-20 | F14: Medium | G14: Structure review (vision engine); Roster structure (vision engine).
A15: S-11 | B15: Retired engines | C15: Remove Qwen2.5-VL-72B (79 GB), Meditron-70B (74 GB, 4K context), the current abliterated file and Qwen3.5-122B-A10B from engines.json, the Arbiter's KV table, the Meditron join path (join_into and Phase 3's +74 GB transient copy) and the 15.2 rows; mark D12 reopened. If D-21 keeps Qwen3.5-122B instead, pull its MTP build and mmproj and render --mmproj and --spec-type draft-mtp. | D15: config/engines.json L51-L79, L109-L139, L178-L238; arbiter.py L151-L153; approval.py L350; phase3-models.sh L635 and step 01; FRAMEWORK_REVIEW 5.1 L319-L321, 15.2 L798, L811, D12 L1019 | E15: D-09; D-15; D-21 | F15: Medium | G15: Structure review (retired engines); Roster structure (medical cross-check, Qwen3.5-122B).
A16: S-12 | B16: Swap cost and work grouping (5.4, 6.3) | C16: Restate 5.4 and 4.2 rule 4 (15-45 s per swap) as about 50-85 s per large swap through LUKS plus re-prefill (V4-Flash about 4.4 min at 32K, up to 13 min at 64K), make GLM-5.3-Flash the default resident engine in 6.3, and change the Arbiter's FIFO queue to engine-affinity ordering with a starvation bound, preferring to evict fast engines that recover page cache. | D16: FRAMEWORK_REVIEW 4.2 rule 4, 5.4 L342-L352, 6.3 L391-L393, 9.1, 17 durations; orchestrator/src/atlas/arbiter.py acquire_generation L1100-L1106 and eviction choice; Celery gpu queue routing in atlas/tasks; tests/test_arbiter.py | E16: D-23; T-14 | F16: Large | G16: Structure review (swap and grouping); Arsenal structure (work grouping; swap figures); Arsenal CR C19.
... A64: S-60 | B64: Script companions and tests | C64: Update README.md, COVERAGE.md, CONVENTIONS.md section 8 and config/README.md for the new keys, steps and V-rows, and the orchestrator tests and fixtures that pin today's keys (test_arbiter, test_config, test_router, test_approval, test_engine_env, test_context_window, test_phase3_loadtest); 50 files under scripts/day1 name a current engine key. | D64: scripts/day1/README.md, COVERAGE.md, CONVENTIONS.md, config/README.md; orchestrator/tests/*.py and tests/fixtures/config/ | E64: D-25; every approved D-row | F64: Large | G64: Structure review (script companions; grep of current engine keys).

Sheet 6 Baseline open items
A1: Baseline open items
A2: Items open in the baseline v0.3.5 and the Day 1 build before this research: prompt-time inputs, to-dos, phased items, watch-list entries and document fixes.
A4: ID | B4: Area | C4: Open item | D4: Recommendation | E4: Current status | F4: Priority | G4: Source | H4: Your response | I4: Your choice or alternative | J4: Your comments
A5: B-01 | B5: Apex Q8 arithmetic (Section 5.1) | C5: Section 5.1 says UD-Q8_K_XL would leave about 2 GiB for KV (Q4 about 9) and logs Q8 as a post-Day-1 experiment; it reads the 161.9 GB file as GiB. | D5: Correct it: UD-Q8_K_XL is 150.75 GiB and UD-Q4_K_XL 144.44 GiB, leaving about 13 and 19.5 GiB of ~164 GiB before compute buffers; the dsv4 cache is about 6,880 B/token (0.24 GiB at 32K). Adopt Q8 per D-11. | E5: Wrong as written (FRAMEWORK_REVIEW L317); v0.3.5 adopts UD-Q4_K_XL 155 GB. Valid whatever D-11 decides. | F5: Before any change | G5: Arsenal CR C1 (L230); Arsenal report what changed L88. Roster report L86, Addendum L136.
A6: B-02 | B6: Two-engine pair and vision profile (S52) | C6: Rule 3 allows two resident engines; the vision engine's standing 2 x 32K profile (KV 10.6 GiB) pairs it with gpt-oss (about 142 GB, 157.69 GiB charged), tested by Phase 3 step 3 and V21; 8 x 32K only by override (overrides.json coresident=false, KV 42.5 GiB). | D6: Retire or re-base the pair, its profile and V21 with D-20 and D-32; keep a two-resident limit only for small loads. | E6: Built and tested in the Day 1 scripts (S52); superseded in purpose by the run-alone directive. | F6: Before any change | G6: Arsenal report what changed L88; FRAMEWORK_REVIEW 4.1, 4.3, 21 V21 (L1085), 23 S52 (L1197). Roster baseline notes L146, L151, L153.
A7: B-03 | B7: Arbiter KV projections (to-do kv-estimates) | C7: The Arbiter's per-token KV figures are UNVERIFIED: DeepSeek 327,680 B (about 10 GiB at 32K), Nemotron 77,102 B, Qwen3.5 115,653 B; the S52 to-do kv-estimates compares them with Phase 3's measured context memory. | D7: Replace DeepSeek's figure with about 6,880 B/token from the pinned llama-kv-cache-dsv4.cpp now, add the new engines' figures, and adopt the Phase 3 measurements for every kept engine before any long context: a registered footprint lasts only until the orchestrator restarts, after which the estimates govern every load and eviction. | E7: Open to-do kv-estimates (S52), raised by Phase 3 step 4. Estimates err high on purpose (gpt-oss about 2.7 GiB by structure against 5.06 GiB projected); real figures UNKNOWN until Phase 3. | F7: Before Day 1 | G7: Arsenal CR C1 (L230); verification_named_heavyweight_moe row 6; arbiter.py L151. Roster baseline notes L149-L150; Roster gap_closure L359. FRAMEWORK_REVIEW 23 S52 (L1197); loadtest.py L2267-L2547.
A8: B-04 | B8: Apex decode band (V10) | C8: Section 5.1 and engines.json L171 expect 25-32 tok/s for the Apex; loadtest.py check_band fails V10 below the lower bound, and no measurement supports the band. | D8: Re-base it before Phase 3 on the chosen rung with the arsenal projections (about 11 tok/s at UD-Q4_K_XL, about 7 at UD-Q8_K_XL on mainline Vulkan, both floors), or make the Apex row informational until measured (D-33). | E8: Open: engines.json L171 sets 25 and 32; every V4 measurement predates the in-pin kernels #27453 and #26578. | F8: Before Day 1 | G8: Arsenal CR C2 (L231); Arsenal report L18. Lucebox report path 0 (L355); loadtest.py L1686-L1699.
A9: B-05 | B9: Swap cost (Sections 4.2, 5.4) | C9: Sections 4.2 rule 4 and 5.4 give 15-45 s per swap. | D9: Restate as about 50-85 s per large swap plus re-prefill, pending the node swap test (T-14). | E9: Neither figure is measured on the node; the design assumes 4-6 GB/s reads, the research uses measured 2.4-6.3 GB/s plus LUKS. | F9: Before Day 1 | G9: Arsenal CR C19 (L248); Arsenal report sequential L76.
A10: B-06 | B10: V10 decode bands, other engines | C10: V10 expects all seven GGUF engines inside bands that exist only for the baseline engines; the vision engine and Meditron are about 3 tok/s in the document but [2, 4] in engines.json. | D10: Set bands for the approved engines from the research projections, marked as projections (GLM 12-14, Flash-Next 23-29, MiMo about 18, Baichuan-M3 / Intern-S1 8-13, Coder-Next Q8_0 37-44, gpt-oss 57-60, Nemotron 13.6-15.8 tok/s); the 72B and Meditron figures become moot if D-21 retires them. | E10: Bands exist only for the baseline engines; the vision / Meditron mismatch is at FRAMEWORK_REVIEW L319-L321 and engines.json L205, L234. | F10: Before Day 1 | G10: Arsenal report allocation L15-32; Arsenal CR section 2. Roster baseline notes L127.
A11: B-07 | B11: Licence fields in engines.json | C11: engines.json marks the Nemotron (L90), DeepSeek (L153) and bge reranker (L303) licences unverified, and the abliterated gpt-oss licence apache-2.0 (inherited, L61). | D11: Record Nemotron as read (NVIDIA Nemotron Open Model License: commercial, derivatives, no safety clause), DeepSeek as MIT, and that the abliterated file's base card returns 401. | E11: Closed by the research, not yet recorded. | F11: Before Day 1 | G11: Arsenal CR G5 (L134-141); Arsenal report Inputs L98. Roster baseline notes L71-L72; Roster gap_closure L393, L403-L410.
A12: B-08 | B12: Nemotron active parameters | C12: Section 5.1 says 12B active (A12B) while Section 2 and the 5.1 paragraph say 12.7B; S6 records 12.7B as superseded and engines.json notes the conflict. | D12: Use one figure everywhere: the NVIDIA-NeMo README gives 120.6B total and 12.7B active, so restore 12.7B unless a card stating 12B is cited. | E12: Inconsistent across FRAMEWORK_REVIEW L96, L309, L313, S6 L1151 and engines.json L107. Still valid: Nemotron stays in the arsenal. | F12: Before Day 1 | G12: Roster baseline notes L125; Roster discipline_specific_models L19.
A13: B-09 | B13: Nemotron footprint | C13: The document gives 120-123 GB and engines.json footprint_gb 123, but the unsloth Q8_0 is 128,472,991,680 bytes (128.47 GB, 119.65 GiB) in 4 shards, while engines.json expects 3. | D13: Record 119.65 GiB (or the exact bytes) and 4 shards, and correct the 186 GB Nemotron plus gpt-oss figure to 191.86 GB. | E13: Inconsistent and partly wrong (FRAMEWORK_REVIEW L239-L241, engines.json L95, L107). | F13: Before Day 1 | G13: Roster baseline notes L128; Roster gap_closure L95, L380.
A14: B-10 | B14: Qwen2.5-VL-72B licence | C14: The document and workbook say Official Apache-2.0 release; engines.json says Qwen License, not Apache 2.0, unverified. | D14: Moot if D-21 retires the 72B; otherwise read the official card and correct whichever record is wrong. | E14: Inconsistent (FRAMEWORK_REVIEW L798, workbook Ref Multimodal C20, engines.json L188). | F14: Before Day 1 | G14: Roster baseline notes L126.
A15: B-11 | B15: Phase 4 step list and UI-TARS references | C15: Section 17 Phase 4 step 2 still lists TimesFM or Chronos and UI-TARS 2.0, and Section 13 names UI-TARS 2.0, while 15.2 and the manifest build Chronos and UI-TARS-1.5-7B; UI-TARS 2.0 has no open weights (S16). | D15: Change the step and Section 13 to Chronos and UI-TARS-1.5-7B; keep UI-TARS 2.0 on the watch-list and re-check on an open-weights release. | E15: Inconsistent (FRAMEWORK_REVIEW L953 against L800, L803 and phase4-engines.json L177, L209); watch-list since September 2026. | F15: Before Day 1 | G15: Roster baseline notes L129. FRAMEWORK_REVIEW 15.5 L849, 23 S16, 13, 17 Phase 4 step 2.
A16: B-12 | B16: Modulus wording in the workbook | C16: Workbook Ref Multimodal C35 says Modulus would need an NVIDIA card in the PCIe slot; the document says a USB4 external GPU dock, since the machine has no PCIe slot. | D16: Correct the workbook to the document's wording. | E16: Inconsistent (workbook C35 against FRAMEWORK_REVIEW L813). | F16: Before Day 1 | G16: Roster baseline notes L130.
... A84: B-80 | B84: Operations | C84: R10: external cooling the Principal is adding for sustained load. | D84: Optional: confirm it is in place before Phase 3's long load tests; monitor temperatures in Cockpit. | E84: Named in the risk register, not confirmed in the checklist; the chip's configurable ceiling is 120 W. | F84: Optional | G84: docs/ATLAS_FRAMEWORK_REVIEW.md R10 line 1049

Sheet 7 Node tests
A1: Node tests
A2: Measurements and trials on the node that settle open decisions. Approve to add each to the Phase 3 test plan.
A4: ID | B4: Test or trial | C4: What it settles | D4: When | E4: Source | F4: Your response | G4: Your choice or alternative | H4: Your comments
A5: T-01 | B5: V3 / V3a / V3b on kernel 7.0: the GTT pool and Vulkan device memory llama.cpp actually sees for the 192 GiB request (about 176-189 GiB, or the vendor's 160 GB / 149.01 GiB cap), checked against the largest approved engine plus its KV. | C5: D-36 (kernel line and V3b floor); whether any rung above about 149 GiB is viable (V4 UD-Q8_K_XL, 5-bit 235B-class, Flash-Next Q6, MiMo MXFP4). | D5: Day 1, Phase 1 step 5 and the Phase 2 gate (V3, V3a, V3b) | E5: Arsenal report gaps L90; Arsenal CR C18 (L247). Roster report L114; Roster gap_closure L359.
A6: T-02 | B6: Output parity: the same prompts on v0.4.1 and the re-pin, with -fa on and off, for every engine that loads on both (gpt-oss-120b, Nemotron, DeepSeek-V4-Flash, Qwen3.8-Flash-Next, the at-pin Q5_K_S 235B-class engines, Qwen3-Coder-Next and the router); Flash-Next is the named case, because the #29751 qwen4exp attention fix is post-pin and the review asks for the pinned Flash-Next output to be parity-checked, scored with llama-perplexity --kl-divergence and a deterministic task set. | C6: D-01 and exposure to the non-FA KV-view bug fixed in #28956; the -fa setting in Appendix B; GLM --kv-unified coherence for D-48. | D6: Before the re-pin is adopted (Phase 3) | E6: Arsenal report Inputs L97, gaps L90; Arsenal CR G1 (L64). Structure review (pin parity step).
A7: T-03 | B7: KLD run: llama-perplexity --kl-divergence-base on a native reference (UD-Q8_K_XL, or BF16 where it fits) over Wikitext-2 plus a domain corpus, then --kl-divergence for each candidate file and KV type (GLM UD-IQ4_XS, V4-Flash UD-Q8_K_XL, Flash-Next UD-Q6_K_XL, the Q5_K_S 235B-class rungs, Nemotron Q8_0, Coder-Next, the abliterated GGUFs), plus changed answers on a small deterministic set. | C7: D-02, D-11, D-16, D-28, D-29 and the uncensored choices (D-07, D-08). | D7: Phase 3, after the re-pin. GLM's Q8_0 reference (317 GiB) exceeds memory, so its check is a task delta against published full-precision scores or streamed base logits. | E7: Arsenal report quantisation L72, gaps L90, conclusion L107. Roster report L114; Roster gap_closure L352.
A8: T-04 | B8: GLM-5.3-Flash after the re-pin: whether its hyper-connection op runs on the GPU or falls back to the CPU on Vulkan, whether -fa off is still required, multi-slot use with --kv-unified, the DSA indexer KV in practice, and decode at 32K and 128K (15.0 tok/s at 32K on the Gorgon build; about 6 by 128K in review; 17.4 at 3.84 bpw on a PRO 495). | C8: The conditions on GLM (D-02); D-48; GLM's KV type in D-29. | D8: Phase 3, after the re-pin | E8: Roster report L56, L86; Roster gap_closure L385, L467. Arsenal report gaps L90; Arsenal CR G2.
A9: T-05 | B9: Load, decode, prefill, context memory and compute buffers of every approved engine on the PRO 495 at the chosen pin, against the Arbiter's projections (to-do kv-estimates) and the projected bands; includes gpt-oss-120b against 53.8-55.6 tok/s measured on 128 GB boxes, Nemotron without MTP at the pin, and Qwen3.5-122B MTP only if D-21 keeps it. | C9: D-10, D-29, D-31, D-33, D-48; the V10 bands; the Arbiter KV-projection baseline item. | D9: Phase 3 steps 2 to 4 | E9: Arsenal report gaps L90; Arsenal CR G2, open gap 1. Roster gap_closure L355, L357, L359.
A10: T-06 | B10: DeepSeek-V4-Flash-0731 on mainline Vulkan: first load, then decode and prefill at UD-Q4_K_XL and UD-Q8_K_XL at 16K-32K with f16 and q8_0 caches, with and without --spec-type draft-dspark; whether UD-Q8_K_XL leaves a usable context inside ~164 GiB, and decode against about 7 (Q8) and 11 (Q4) tok/s projected. | C10: D-11 (rung), D-29 (Apex ladder), D-33 and D-47 (band and floor), D-61 (DSpark). | D10: Day 1, Phase 3 (V10, V22) | E10: Roster report L54, L114; Roster gap_closure L354. Lucebox report Inputs row 1 (L392), path 0 (L355).
A11: T-07 | B11: Qwen3.8-Flash-Next UD-Q6_K_XL decode against the 23-29 tok/s projection (no UD-Q6_K_XL measurement exists: 26.9 tok/s without MTP and 41.3 with MTP on fork builds were both at UD-IQ4_XS on 128 GB Ryzen AI Max+ 395 boxes; a GMKtec buyer reported 15 tok/s on this machine, build, quant source and context unknown). | C11: Flash-Next's role as challenger and third opinion; whether its post-pin Vulkan fixes are needed (D-01, D-28). | D11: Phase 3 | E11: Arsenal report gaps L90; Arsenal CR C20 (L249). Roster report Addendum L136.
A12: T-08 | B12: Already answered by the arsenal research: the ggml-org Qwen3.8-Flash-Next Q8_0 (162.62 GB) stores per_layer_token_embd (the n-gram table) at Q4_0 (28.80 GB) and every other matrix at Q8_0, which explains the 25.6 GB gap to unsloth's 188.23 GB. What remains is its KLD against UD-Q6_K_XL (fold into T-03). | C12: D-28. | D12: Before any Flash-Next pull | E12: verification_named_heavyweight_moe row 19 (GGUF header parse 2026-10-15); verification_quantization_value row 14. Roster report Addendum L128; Roster gap_closure L365.
A13: T-09 | B13: MiMo-V2.6-Flash uncensored MXFP4 load and generation at v0.4.1 (mimo2 arch in the pin, converter later) and at the re-pin. | C13: Whether Valerie's default (D-07) needs the re-pin; the roster/arsenal contradiction on MiMo support. | D13: Phase 3 | E13: Arsenal CR C6 (L235), G4. Roster gap_closure L378, L463.
A14: T-10 | B14: Refusal rate, KLD and a small capability set on the Principal's prompts: MiMo uncensored and gpt-oss Derestricted against their bases; abliterated Qwen3.5-122B Q8_0 against base Q8_0 if considered; the current noctrex file against base gpt-oss-120b only if D-09 keeps it; a mtp.layers check on any Nemotron Heretic GGUF. | C14: D-07, D-08, D-09, D-58. | D14: Phase 3 or after Day 1 | E14: Arsenal report uncensored L82, gaps L90; Arsenal CR open gap 3. Roster report L110; Roster gap_closure L349, L361.
A15: T-11 | B15: Baichuan-M3-235B: load at the pin (official Q4_K_M and mradermacher Q5_K_S) and a HealthBench subset with a fixed judge against gpt-oss-120b and GLM-5.3-Flash. | C15: D-15 and the rung in D-16; Baichuan-M3 has no independent score. | D15: Phase 3, before adoption | E15: Roster gap_closure L350. Arsenal report Minerva row L23.
A16: T-12 | B16: Nemotron 3 Super Q8_0 (128.47 GB) stability with a prompt of 20K tokens or more and a server health check (#20732). | C16: D-13 (long-context utility); the Nemotron #20732 baseline item. | D16: Phase 3 | E16: Arsenal CR G11 (L220-224). Roster gap_closure L356, L437.
... A37: T-33 | B37: Only if an R9700 is bought: the card in a USB4 v2 dock (thunderbolt.host_reset=false, amdgpu.runpm=0, dock powered before boot), checking BAR size and iGPU peer access, then Lucebox ds41-gorgon with a placement learned on the node, against Lucebox's 48.7 tok/s on code and 31-33 at 2K-31K (Gen3 x4). | C37: D-62 (b), after purchase. | D37: Optional, only if D-62 becomes (b) | E37: Lucebox report L323-L325, path E (L360).
